Workbook

Sheet Projets
A1: PROJETS (reconstruit à partir d'Accords_consolides — fusion sans doublon)
A2: Code_Projet | B2: Intitule_Projet | C2: Annee_Collecte | D2: Categorie | E2: Envergure | F2: Secteur_Activite_1 | G2: Secteur_Activite_2 | H2: Secteur_Activite_3 | I2: Sous_Secteur | J2: Tutelle | K2: Agence_Exécution | L2: Contexte_Justification | M2: Problematique | N2: Objectif_Global | O2: Objectifs_Specifiques | P2: Principaux_Resultats | Q2: Composantes_Projet | R2: Activites_Principales | S2: Beneficiaires_Directs | T2: Beneficiaires_Indirects | U2: Departement | V2: Commune | W2: Arrondissement | X2: Village_Quartier | Y2: Coordonnees_GPS | Z2: Date_Approbation | AA2: Date_Signature | AB2: Date_Vigueur | AC2: Date_Demarrage | AD2: Date_Cloture | AE2: Duree_Initiale_Mois | AF2: Est_Proroge | AG2: Date_Prorogation | AH2: Motif_Prorogation | AI2: Nouvelle_Date_Cloture | AJ2: Nb_Prorogations | AK2: Cout_Total_USD | AL2: Devise | AM2: Taux_Change | AN2: Cout_Total_FCFA | AO2: Milliards_FCFA | AP2: Contrepartie_BN_USD | AQ2: Contrepartie_BN_FCFA | AR2: Don_Attendu_FCFA | AS2: Pret_Attendu_FCFA | AT2: PPP_Attendu_FCFA | AU2: Contribution_Benef_FCFA | AV2: Gap_Financement | AW2: Pourcentage_Acquis | AX2: Source_Financement | AY2: APD_Oui_Non | AZ2: Type_Financement | BA2: Contributeur | BB2: Sigle_Partenaire | BC2: Type_Contributeur | BD2: Co_Partenaire_1 | BE2: Co_Partenaire_2 | BF2: Co_Partenaire_3 | BG2: Co_Partenaire_4 | BH2: Co_Partenaire_5 | BI2: Co_Partenaire_6 | BJ2: Co_Partenaire_7 | BK2: Statut_Projet | BL2: Secteur_PAG | BM2: Pilier_PAG | BN2: Axe_PAG | BO2: ODD | BP2: Cible_ODD | BQ2: Pilier_National | BR2: Resp_Banque_Nom | BS2: Resp_Banque_Tel1 | BT2: Resp_Banque_Tel2 | BU2: Resp_Banque_Email | BV2: Coord_Projet_Nom | BW2: Coord_Projet_Tel1 | BX2: Coord_Projet_Tel2 | BY2: Coord_Projet_Email | BZ2: RAF_Nom | CA2: RAF_Tel1 | CB2: RAF_Tel2 | CC2: RAF_Email | CD2: Resp_SE_Nom | CE2: Resp_SE_Tel1 | CF2: Resp_SE_Tel2 | CG2: Resp_SE_Email | CH2: Niveau_Maturite | CI2: Etude_Faisabilite | CJ2: Etude_Environnementale | CK2: Plan_Affaires | CL2: Dossier_Technique | CM2: Categorie_Env | CN2: Theme_Genre | CO2: Theme_Inclusion | CP2: Theme_Climat | CQ2: Theme_Emploi_Jeunes | CR2: Risques_Identifies | CS2: Mesures_Attenuation | CT2: Niveau_Risque | CU2: Date_Soumission | CV2: Avis_Technique | CW2: Avis_DGFD | CX2: Avis_Ministere | CY2: Decision_Comite | CZ2: Date_Validation | DA2: Note_Conceptuelle | DB2: Cadre_Logique | DC2: Budget_Detaille | DD2: Cartographie | DE2: Lettre_Demande | DF2: Zone_intervention | DG2: Modalite_Intervention | DH2: Nature_Financement | DI2: Instrument_Financement | DJ2: Source_Verifiable | DK2: Montant_Devise_Origine
A3: P-0001-BIDC-2011 | B3: Projet d'électrification rurale de soixante sept (67) localités en République du Bénin | F3: ÉNERGIE | N3: Accroître le taux d'accès à l'électricité en milieu rural en raccordant 67 localités isolées au réseau électrique de la SBEE pour stimuler l'économie locale et améliorer les services sociaux de base. | U3: Alibori, Borgou, Collines, Zou, Couffo, Mono, Atlantique, Ouémé, Plateau | V3: Banikoara, Gogounou, Kandi, Malanville, Segbana, Bembérèké, Kalalé, N'Dali, Nikki, Parakou, Pérére, Sinendé, Tchaourou, Bantè, Dassa-Zoumé, Glazoué, Ouèssè, Savalou, Savè, Abomey, Agbangnizoun, Bohicon, Covè, Djidja, Ouinhi, Za-Kpota, Zagnanado, Zogbodomey, Aplahoué, Djakotomey, Dogbo, Klouékanmè, Lalo, Toviklin, Athiémé, Bopa, Comè, Grand-Popo, Houéyogbé, Lokossa, Abomey-Calavi, Allada, Kpomassè, Ouidah, Sô-Ava, Toffo, Tori-Bossito, Zè, Adjarra, Adjohoun, Agégué, Akpro-Missérété, Avrankou, Bonou, Dangbo, Porto-Novo, Sèmè-Podji, Adja-Ouéré, Ifangni, Kétou, Pobè, Sakété | Z3: 40511 | AA3: 40548 | AD3: 43100 | AL3: EUR | AN3: 10000000000 | AR3: 0 | AS3: 10000000000 | BA3: Banque d’Investissement et de Développement de la CEDEAO | BB3: BIDC | BC3: MULTILATERAUX | DF3: ALIBORI (BANIKOARA, GOGOUNOU, KANDI, MALANVILLE, SEGBANA) ; BORGOU (BEMBÉRÈKÉ, KALALÉ, N'DALI, NIKKI, PARAKOU, PÉRÉRE, SINENDÉ, TCHAOUROU) ; COLLINES (BANTÈ, DASSA-ZOUMÉ, GLAZOUÉ, OUÈSSÈ, SAVALOU, SAVÈ) ; ZOU (ABOMEY, AGBANGNIZOUN, BOHICON, COVÈ, DJIDJA, OUINHI, ZA-KPOTA, ZAGNANADO, ZOGBODOMEY) ; COUFFO (APLAHOUÉ, DJAKOTOMEY, DOGBO, KLOUÉKANMÈ, LALO, TOVIKLIN) ; MONO (ATHIÉMÉ, BOPA, COMÈ, GRAND-POPO, HOUÉYOGBÉ, LOKOSSA) ; ATLANTIQUE (ABOMEY-CALAVI, ALLADA, KPOMASSÈ, OUIDAH, SÔ-AVA, TOFFO, TORI-BOSSITO, ZÈ) ; OUÉMÉ (ADJARRA, ADJOHOUN, AGÉGUÉ, AKPRO-MISSÉRÉTÉ, AVRANKOU, BONOU, DANGBO, PORTO-NOVO, SÈMÈ-PODJI) ; PLATEAU (ADJA-OUÉRÉ, IFANGNI, KÉTOU, POBÈ, SAKÉTÉ). | DG3: Projet d'investissement | DH3: Prêt | DI3: Prêt non concessionnel | DJ3: https://evaluation.gouv.bj | DK3: 20000000
A4: P-0002-BOAD-2011 | B4: Projet de construction de la ligne d'interconnexion électrique 161 KV Bembèrèkè-Kandi-Malanville | F4: ÉNERGIE | N4: Sécuriser et accroître l'approvisionnement en énergie électrique des localités septentrionales du Bénin et faciliter l'interconnexion avec le réseau du Niger grâce à la construction d'une ligne de transport haute tension. | U4: Borgou, Alibori | V4: Bembérèké, Gogounou, Kandi, Malanville | W4: Bembérèké Centre, Gogounou Centre, Bagou, Gounarou, Kandi I, Kandi II, Donwari, Sam, Malanville Centre, Guéné, Garou | Z4: 40527 | AA4: 40565 | AD4: 42735 | AL4: XOF | AN4: 20000000000 | AR4: 0 | AS4: 20000000000 | BA4: Banque Ouest Africaine de Développement | BB4: BOAD | BC4: MULTILATERAUX | DF4: BORGOU (BEMBÉRÈKÉ(BEMBÉRÈKÉ CENTRE)) ; ALIBORI (GOGOUNOU(GOGOUNOU CENTRE, BAGOU, GOUNAROU), KANDI(KANDI I, KANDI II, DONWARI, SAM), MALANVILLE(MALANVILLE CENTRE, GUÉNÉ, GAROU)). | DG4: Projet d'investissement | DH4: Prêt | DI4: Prêt non concessionnel | DJ4: https://boad.org | DK4: 20000000000
A5: P-0003-OFID/OPEP-2011 | B5: Projet de construction de la route Kandi-Ségbana-Frontière du Nigeria | F5: INFRASTRUCTURES ROUTIERES ET TRANSPORT | N5: Améliorer le niveau de service de l'axe routier reliant Kandi à la frontière du Nigeria afin de réduire les coûts de transport, désenclaver les zones agricoles traversées et dynamiser le commerce transfrontalier. | U5: Alibori | V5: Kandi, Ségbana | W5: Kandi I, Ségbana Centre, Liboussou, Lougou, Sokotindji | X5: Samia | Z5: 40528 | AA5: 40556 | AD5: 43281 | AL5: EUR | AN5: 5225000000 | AR5: 0 | AS5: 5225000000 | BA5: Fonds de l’OPEP pour le Développement International | BB5: OFID/OPEP | BC5: MULTILATERAUX | DF5: ALIBORI (KANDI(KANDI I), SÉGBANA(SÉGBANA CENTRE, LIBOUSSOU, LOUGOU, SOKOTINDJI(SAMIA))). | DG5: Projet d'investissement | DH5: Prêt | DI5: Prêt concessionnel | DJ5: https://documentation-anbenin.org | DK5: 11000000
A6: P-0004-FND-2011 | B6: Projet de Développement de l'Accès à l'Energie Moderne par la Biomasse | F6: ÉNERGIE | N6: Promouvoir l'utilisation de technologies énergétiques durables basées sur la biomasse, réduire la pression sur les ressources forestières à travers la diffusion de foyers améliorés et renforcer les capacités des acteurs de la filière bois-énergie. | U6: Collines, Zou, Borgou | V6: Savalou, Dassa-Zoumé, Glazoué, Ouèssè, Djidja, Tchaourou | Z6: 40522 | AA6: 40574 | AD6: 43100 | AL6: EUR | AN6: 983935500 | AR6: 983935500 | AS6: 0 | BA6: Fonds Nordique de Développement | BB6: FND | BC6: MULTILATERAUX | DF6: COLLINES (SAVALOU, DASSA-ZOUMÉ, GLAZOUÉ, OUÈSSÈ) ; ZOU (DJIDJA, SAVALOU) ; BORGOU (TCHAOUROU). | DG6: Projet d'investissement | DH6: Don | DI6: Don | DJ6: https://direction-energie.gouv.bj | DK6: 1500000
A7: P-0005-BID-2011 | B7: Assistance technique au profit du Ministère de la Prospective, du Développement, de l'Evaluation des Politiques Publiques et de la Coordination de l'Action Gouvernementale | F7: GOUVERNANCE | N7: Renforcer les capacités institutionnelles et techniques du ministère dans la formulation des politiques de développement, la planification stratégique à long terme et l'évaluation d'impact des politiques publiques. | U7: Littoral | V7: Cotonou | Z7: 40532 | AA7: 40588 | AD7: 42004 | AL7: DI | AN7: 150000000 | AR7: 150000000 | AS7: 0 | BA7: Banque Islamique de Développement | BB7: BID | BC7: MULTILATERAUX | DF7: LITTORAL (COTONOU). | DG7: Assistance technique / Renforcement institutionnel | DH7: Don | DI7: Assistance technique | DJ7: https://gouv.bj | DK7: 200000
A8: P-0006-BM-2011 | B8: Financement supplémentaire au sixième Crédit d'Appui à la Réduction de la Pauvreté (PRSC-6) | F8: GOUVERNANCE | N8: Soutenir la mise en œuvre de la stratégie de croissance pour la réduction de la pauvreté en améliorant la gestion des finances publiques, l'efficacité de la dépense sociale et le climat des investissements. | U8: National | Z8: 40631 | AA8: 40660 | AD8: 41274 | AL8: DTS | AN8: 11000000000 | AR8: 11000000000 | AS8: 0 | BA8: Banque mondiale | BB8: BM | BC8: MULTILATERAUX | DF8: NATIONAL | DG8: Appui budgétaire sectoriel | DH8: Don | DI8: Don | DJ8: https://banquemondiale.org | DK8: 14000000
A9: P-0007-BOAD-2011 | B9: Projet d'Aménagement et de Bitumage de la route Ouidah-Allada et de la bretelle Pahou-Tori. | F9: INFRASTRUCTURES ROUTIERES ET TRANSPORT | N9: Assurer la liaison routière moderne entre les communes de Ouidah et d'Allada afin de faciliter la circulation des personnes et des biens, de désenclaver les zones de production agricole et de soutenir l'axe touristique de l'Atlantique. | U9: Atlantique | V9: Ouidah, Tori-Bossito, Allada | W9: Ouidah I, Ouidah II, Savi, Tori-Cada, Tori-Gbégamey, Tori-Bossito Centre, Allada Centre, Lon-Agonmey, Hinvi | Z9: 40527 | AA9: 40681 | AD9: 42735 | AL9: XOF | AN9: 5320000000 | AR9: 0 | AS9: 5320000000 | BA9: Banque Ouest Africaine de Développement | BB9: BOAD | BC9: MULTILATERAUX | DF9: ATLANTIQUE (OUIDAH(OUIDAH I, OUIDAH II, SAVI), TORI-BOSSITO(TORI-CADA, TORI-GBÉGAMEY, TORI-BOSSITO CENTRE), ALLADA(ALLADA CENTRE, LON-AGONMEY, HINVI)). | DG9: Projet d'investissement | DH9: Prêt | DI9: Prêt non concessionnel | DJ9: https://boad.org | DK9: 5320000000
A10: P-0008-BM-2011 | B10: Projet de Productivité Agricole en Afrique de l'Ouest (PPAAO) | F10: AGRICULTURE | N10: Générer et diffuser des technologies agricoles améliorées dans les filières prioritaires du Bénin, tout en renforçant les systèmes de recherche agricole et la coopération scientifique régionale en Afrique de l'Ouest. | U10: Borgou, Atlantique, Ouémé | V10: Bembérèké, Allada, Adjohoun, Bonou, Dangbo | W10: Ina, Niaouli | Z10: 40626 | AA10: 40701 | AD10: 42735 | AL10: DTS | AN10: 8400000000 | AR10: 8400000000 | AS10: 0 | BA10: Banque mondiale | BB10: BM | BC10: MULTILATERAUX | DF10: BORGOU (BEMBÉRÈKÉ(INA)) ; ATLANTIQUE (ALLADA(NIAOULI)) ; OUÉMÉ (ADJOHOUN, BONOU, DANGBO). | DG10: Projet d'investissement | DH10: Don | DI10: Don | DJ10: https://banquemondiale.org | DK10: 11000000
A11: P-0009-BM-2011 | B11: Projet d'Appui à la Diversification Agricole (PADA) | F11: AGRICULTURE | N11: Restaurer et améliorer la productivité et la compétitivité des filières agricoles cibles (notamment le riz, le maïs, l'anacarde et l'ananas) pour accroître les revenus des petits producteurs et sécuriser la souveraineté alimentaire. | U11: Ouémé, Zou, Collines, Atlantique | V11: Dangbo, Adjohoun, Bonou, Abomey, Bohicon, Zakpota, Dassa-Zoumé, Savalou, Abomey-Calavi, Zè | Z11: 40626 | AA11: 40701 | AD11: 42794 | AL11: DTS | EUR | AN11: 23000000000 | AR11: 7500000000 | AS11: 15500000000 | BA11: Banque mondiale | BB11: BM | BC11: MULTILATERAUX | DF11: OUÉMÉ (DANGBO, ADJOHOUN, BONOU) ; ZOU (ABOMEY, BOHICON, ZAKPOTA) ; COLLINES (DASSA-ZOUMÉ, SAVALOU) ; ATLANTIQUE (ABOMEY-CALAVI, ZÈ). | DG11: Projet d'investissement | DH11: Don | Prêt | DI11: Fonds fiduciaire (Trust Fund) | Prêt concessionnel | DJ11: https://banquemondiale.org | DK11: 35000000
A12: P-0010-BM-2011 | B12: Projet d'Appui à la Gestion des Aires Protégées | F12: CADRE DE VIE | N12: Consolider et étendre les investissements destinés à la structuration des chaînes de valeur agricoles afin d'amplifier l'accès aux marchés des groupements de producteurs et d'améliorer la commercialisation des produits locaux. | U12: Ouémé, Zou, Collines, Atlantique | V12: Dangbo, Adjohoun, Bonou, Abomey, Bohicon, Zakpota, Dassa-Zoumé, Savalou, Abomey-Calavi, Zè | Z12: 40631 | AA12: 40701 | AD12: 43646 | AL12: DTS | EUR | AN12: 3450000000 | AR12: 3450000000 | AS12: 0 | BA12: Banque mondiale | BB12: BM | BC12: MULTILATERAUX | DF12: OUÉMÉ (DANGBO, ADJOHOUN, BONOU) ; ZOU (ABOMEY, BOHICON, ZAKPOTA) ; COLLINES (DASSA-ZOUMÉ, SAVALOU) ; ATLANTIQUE (ABOMEY-CALAVI, ZÈ). | DG12: Projet d'investissement | DH12: Don | DI12: Don | Fonds fiduciaire (Trust Fund) | DJ12: https://banquemondiale.org | DK12: 5200000
A13: P-0011-BM-2011 | B13: Projet d'Urgence de Gestion Environnementale en Milieu Urbain | F13: CADRE DE VIE | N13: Améliorer la gestion durable des écosystèmes des parcs nationaux du W et de la Pendjari, renforcer la conservation de la biodiversité et impliquer les communautés locales dans la gouvernance des ressources naturelles. | U13: Atacora, Alibori | V13: Tanguiéta, Kérou, Banikoara | W13: Tanguiéta Centre, Banikoara Centre | Z13: 40631 | AA13: 40701 | AD13: 43496 | AL13: DTS | AN13: 25000000000 | AR13: 0 | AS13: 25000000000 | BA13: Banque mondiale | BB13: BM | BC13: MULTILATERAUX | DF13: ATACORA (TANGUIÉTA(TANGUIÉTA CENTRE), KÉROU) ; ALIBORI (BANIKOARA(BANIKOARA CENTRE)). | DG13: Projet d'investissement | DH13: Prêt | DI13: Prêt concessionnel | DJ13: https://banquemondiale.org | DK13: 31600000
A14: P-0012-BM-2011 | B14: Projet de Nutrition Communautaire | F14: SANTÉ | N14: Réduire la vulnérabilité des populations du Grand Nokoué face aux inondations récurrentes, améliorer les infrastructures d'assainissement pluvial et optimiser la gestion des déchets solides ménagers. | U14: Littoral, Atlantique, Ouémé | V14: Cotonou, Abomey-Calavi, Ouidah, Porto-Novo, Sèmè-Podji | W14: Du 1er au 13ème, Godomey, Abomey-Calavi Centre, Akassato, Du 1er au 5ème | Z14: 40687 | AA14: 40724 | AD14: 42735 | AL14: EUR | AN14: 1398890500 | AR14: 1398890500 | AS14: 0 | BA14: Banque mondiale | BB14: BM | BC14: MULTILATERAUX | DF14: LITTORAL (COTONOU(DU 1ER AU 13ÈME)) ; ATLANTIQUE (ABOMEY-CALAVI(GODOMEY, ABOMEY-CALAVI CENTRE, AKASSATO), OUIDAH) ; OUÉMÉ (PORTO-NOVO(DU 1ER AU 5ÈME), SÈMÈ-PODJI). | DG14: Projet d'investissement | DH14: Don | DI14: Don | DJ14: https://evaluation.gouv.bj | DK14: 2797781
A15: P-0013-BOAD-2011 | B15: Projet de pavage de rues et d'assainissement dans la Commune d'Abomey-Calavi | F15: CADRE DE VIE | N15: Moderniser la voirie urbaine des arrondissements centraux d'Abomey-Calavi par le pavage et la construction de collecteurs d'eaux pluviales afin d'améliorer les conditions de circulation et d'hygiène des populations. | U15: Atlantique | V15: Abomey-Calavi | W15: Abomey-Calavi Centre, Godomey, Akassato, Zinvié | Z15: 40688 | AA15: 40739 | AD15: 42735 | AL15: XOF | AN15: 6500000000 | AR15: 0 | AS15: 6500000000 | BA15: Banque Ouest Africaine de Développement | BB15: BOAD | BC15: MULTILATERAUX | DF15: ATLANTIQUE (ABOMEY-CALAVI(ABOMEY-CALAVI CENTRE, GODOMEY, AKASSATO, ZINVIÉ)). | DG15: Projet d'investissement | DH15: Prêt | DI15: Prêt non concessionnel | DJ15: https://boad.org | DK15: 6500000000
A16: P-0014-BM-2011 | B16: Projet d'appui institutionnel au profit du Ministère du Développement, de l'Analyse Economique et de la Prospective et de la Primature | F16: GOUVERNANCE | N16: Renforcer les compétences techniques des cadres de l'administration centrale pour améliorer le suivi des indicateurs macroéconomiques, l'évaluation des politiques sectorielles et la coordination gouvernementale. | U16: Littoral | V16: Cotonou | Z16: 40709 | AA16: 40781 | AD16: 42369 | AL16: EUR | AN16: 240875000 | AR16: 240875000 | AS16: 0 | BA16: Banque mondiale | BB16: BM | BC16: MULTILATERAUX | DF16: LITTORAL (COTONOU). | DG16: Assistance technique / Renforcement institutionnel | DH16: Don | DI16: Appui institutionnel | DJ16: https://gouv.bj | DK16: 481750
A17: P-0015-BOAD-2011 | B17: Avance de fonds pour le financement des études de faisabilité du projet de développement d'infrastructures socio-économiques et de sécurité alimentaire dans le bassin du Niger | F17: AGRICULTURE | N17: Réaliser les études techniques, environnementales et sociales préalables requises pour concevoir des aménagements hydro-agricoles et de stockage visant la sécurité alimentaire dans les communes du bassin du Niger. | U17: Alibori, Borgou, Atacora, Donga | V17: Banikoara, Karimama, Malanville, Bembérèké, Kalalé, Ndali, Nikki, Sinendé, Kérou, Kouandé, Péhunco, Tanguiéta, Djougou | Z17: 40688 | AA17: 40794 | AD17: 41820 | AL17: XOF | AN17: 380000000 | AR17: 0 | AS17: 380000000 | BA17: Banque Ouest Africaine de Développement | BB17: BOAD | BC17: MULTILATERAUX | DF17: ALIBORI (BANIKOARA, KARIMAMA, MALANVILLE) ; BORGOU (BEMBÉRÈKÉ, KALALÉ, NDALI, NIKKI, SINENDÉ) ; ATACORA (KÉROU, KOUANDÉ, PÉHUNCO, TANGUIÉTA) ; DONGA (DJOUGOU). | DG17: Étude / Préparation | DH17: Prêt | DI17: Avance de préparation de projet | DJ17: https://boad.org | DK17: 380000000
A18: P-0016-FKDEA-2011 | B18: Financement des micro et petites entreprises agricoles au Bénin. | F18: AGRICULTURE | N18: Faciliter l'accès aux crédits de campagne et d'équipement pour les petits exploitants et groupements agricoles à travers le refinancement des systèmes financiers décentralisés. | U18: National | Z18: 40724 | AA18: 40808 | AD18: 43465 | AL18: EUR | AN18: 2500000000 | AR18: 2500000000 | AS18: 0 | BA18: Fonds Koweïtien pour le Développement Économique Arabe | BB18: FKDEA | BC18: BILATERAUX | DF18: NATIONAL | DG18: Projet d'investissement | DH18: Don | DI18: Don | DJ18: https://evaluation.gouv.bj | DK18: 5000000
A19: P-0017-BM-2011 | B19: Projet Régional de Facilitation du Commerce-Phase II | F19: INDUSTRIE ET COMMERCE | N19: Réduire les barrières commerciales le long des corridors d'échanges, moderniser les procédures douanières aux frontières et simplifier le transit des marchandises pour stimuler l'intégration économique régionale. | U19: Littoral, Atlantique, Zou, Collines, Borgou, Alibori, Ouémé | V19: Cotonou, Allada, Bohicon, Savalou, Tchaourou, Parakou, Kandi, Malanville, Porto-Novo | W19: Malanville Centre | Z19: 40715 | AA19: 40856 | AD19: 43008 | AL19: DTS | AN19: 3750000000 | AR19: 3750000000 | AS19: 0 | BA19: Banque mondiale | BB19: BM | BC19: MULTILATERAUX | DF19: LITTORAL (COTONOU) ; ATLANTIQUE (ALLADA) ; ZOU (BOHICON) ; COLLINES (SAVALOU, TCHAOUROU) ; BORGOU (PARAKOU) ; ALIBORI (KANDI, MALANVILLE(MALANVILLE CENTRE)) ; OUÉMÉ (PORTO-NOVO). | DG19: Projet d'investissement | DH19: Don | DI19: Don | DJ19: https://banquemondiale.org | DK19: 4800000
A20: P-0018-BM-2011 | B20: Projet d'Appui à la Promotion Apicole (PAPA) | F20: AGRICULTURE | N20: Soutenir les filières horticoles et maraîchères en fournissant des intrants de qualité, en structurant les coopératives et en développant de petites infrastructures de marché dans les zones de production. | U20: Ouémé, Plateau, Zou, Collines | V20: Adjohoun, Bonou, Dangbo, Pobè, Kétou, Abomey, Bohicon, Zakpota, Dassa-Zoumé, Savalou | Z20: 40673 | AA20: 40856 | AD20: 42735 | AL20: EUR | AN20: 1282658000 | AR20: 1282658000 | AS20: 0 | BA20: Banque mondiale | BB20: BM | BC20: MULTILATERAUX | DF20: OUÉMÉ (ADJOHOUN, BONOU, DANGBO) ; PLATEAU (POBÈ, KÉTOU) ; ZOU (ABOMEY, BOHICON, ZAKPOTA) ; COLLINES (DASSA-ZOUMÉ, SAVALOU). | DG20: Projet d'investissement | DH20: Don | DI20: Don | DJ20: https://banquemondiale.org | DK20: 2565316
A21: P-0019-BM-2011 | B21: Projet de Développement de l'Accès à l'Energie Moderne (DAEM) | F21: ÉNERGIE | N21: Élargir l'accès aux services électriques et aux solutions de cuisson propres dans les zones rurales et périurbaines à travers des mécanismes de financement adaptés et la promotion des énergies renouvelables. | U21: Collines, Zou, Borgou, Donga | V21: Dassa-Zoumé, Savalou, Bohicon, Djidja, Tchaourou, Parakou, Djougou | Z21: 40717 | AA21: 40856 | AD21: 43100 | AL21: EUR | AN21: 1000000000 | AR21: 1000000000 | AS21: 0 | BA21: Banque mondiale | BB21: BM | BC21: MULTILATERAUX | DF21: COLLINES (DASSA-ZOUMÉ, SAVALOU) ; ZOU (BOHICON, DJIDJA) ; BORGOU (TCHAOUROU, PARAKOU) ; DONGA (DJOUGOU). | DG21: Projet d'investissement | DH21: Don | DI21: Fonds fiduciaire (Trust Fund) | DJ21: https://direction-energie.gouv.bj | DK21: 2000000
A22: P-0020-Allemagne-2011 | B22: Augmentation cofinancement pots communs de l'alimentation en eau potable | F22: EAU ET ASSAINISSEMENT | N22: Accroître la desserte en eau potable en milieu rural et semi-urbain dans l'Atacora et la Donga par la réhabilitation et l'extension de systèmes d'adduction d'eau villageoise. | U22: Atacora, Donga | V22: Natitingou, Boukoumbé, Toucountouna, Tanguiéta, Djougou, Copargo, Ouaké | Z22: 40861 | AA22: 40871 | AD22: 42369 | AL22: EUR | AN22: 13776000000 | AR22: 13776000000 | AS22: 0 | BA22: Allemagne | BB22: Allemagne | BC22: BILATERAUX | DF22: ATACORA (NATITINGOU, BOUKOUMBÉ, TOUCOUNTOUNA, TANGUIÉTA) ; DONGA (DJOUGOU, COPARGO, OUAKÉ). | DG22: Projet d'investissement | DH22: Don | DI22: Cofinancement | DJ22: https://evaluation.gouv.bj | DK22: 21000000
A23: P-0021-BAD-2011 | B23: Projet de réhabilitation de la route Lomé-Cotonou et de facilitation du transport sur le corridor Abidjan-Lagos-phase I | F23: INFRASTRUCTURES ROUTIERES ET TRANSPORT | N23: Consolider les investissements d'aménagement routier sur le corridor côtier, incluant les travaux de protection de l'infrastructure contre l'érosion marine sur les segments critiques. | U23: Mono, Atlantique, Littoral | V23: Grand-Popo, Ouidah, Cotonou | W23: Agoué | X23: Agoué, Hillacondji | Z23: 40837 | AA23: 40879 | AD23: 43830 | AL23: UC | AN23: 52330000000 | AR23: 24520000000 | AS23: 27810000000 | BA23: Banque Africaine de Développement | BB23: BAD | BC23: MULTILATERAUX | DF23: MONO (GRAND-POPO(AGOUÉ(AGOUÉ, HILLACONDJI))) ; ATLANTIQUE (OUIDAH) ; LITTORAL (COTONOU). | DG23: Projet d'investissement | DH23: Don | Prêt | DI23: Don | Prêt concessionnel | DJ23: https://documentation-anbenin.org | DK23: 73140000
A24: P-0022-Allemagne-2011 | B24: Financement de la phase II du Fonds d'Appui au Développement des Communes (FADEC) | F24: DÉCENTRALISATION | N24: Assurer le transfert effectif de ressources financières aux collectivités locales pour le financement de leurs infrastructures sociocommunautaires (écoles, dispensaires, marchés). | U24: National | Z24: 40855 | AA24: 40892 | AD24: 42004 | AL24: EUR | AN24: 5903613000 | AR24: 5903613000 | AS24: 0 | BA24: Allemagne | BB24: Allemagne | BC24: BILATERAUX | DF24: NATIONAL | DG24: Fonds commun | DH24: Don | DI24: Don | DJ24: https://evaluation.gouv.bj | DK24: 9000000
A25: P-0023-BM-2011 | B25: Septième don d'appui à la réduction de la pauvreté (PRSG-7) | F25: GOUVERNANCE | N25: Appuyer les réformes macroéconomiques sectorielles de l'État visant la transparence budgétaire, la stabilité fiscale et le financement adéquat des services sociaux essentiels. | U25: National | Z25: 40631 | AA25: 40898 | AD25: 41274 | AL25: EUR | AN25: 15000000000 | AR25: 15000000000 | AS25: 0 | BA25: Banque mondiale | BB25: BM | BC25: MULTILATERAUX | DF25: NATIONAL | DG25: Projet d'investissement | DH25: Don | DI25: Don | DJ25: https://banquemondiale.org | DK25: 30000000
A26: P-0024-BOAD-2011 | B26: Projet de pavage et d'assainissement de rues dans les villes de Kétou, Tchaourou et Savè | F26: CADRE DE VIE | N26: Améliorer le cadre de vie urbain dans les trois communes bénéficiaires par le revêtement des voies secondaires et la construction d'ouvrages de drainage des eaux pluviales. | U26: Plateau, Borgou, Collines | V26: Kétou, Tchaourou, Savè | Z26: 40681 | AA26: 40908 | AD26: 42185 | AL26: XOF | AN26: 7000000000 | AR26: 0 | AS26: 7000000000 | BA26: Banque Ouest Africaine de Développement | BB26: BOAD | BC26: MULTILATERAUX | DF26: PLATEAU (KÉTOU) ; BORGOU (TCHAOUROU) ; COLLINES (SAVÈ). | DG26: Projet d'investissement | DH26: Prêt | DI26: Prêt non concessionnel | DJ26: https://boad.org | DK26: 7000000000
A27: P-0003-FSD-2012 | B27: Projet de construction de la route Kandi-Ségbana-Frontière du Nigeria | F27: INFRASTRUCTURES ROUTIERES ET TRANSPORT | N27: Cofinancer les travaux de terrassement et de bitumage de l'axe routier reliant Kandi à la frontière nigériane pour soutenir le transit sous-régional des marchandises. | U27: Alibori | V27: Kandi, Ségbana | W27: Ségbana Centre | X27: Samia | Z27: 40994 | AA27: 41043 | AD27: 43830 | AL27: SAR | AN27: 8000000000 | AR27: 0 | AS27: 8000000000 | BA27: Fonds Saoudien de Développement | BB27: FSD | BC27: BILATERAUX | DF27: ALIBORI (KANDI, SÉGBANA(SÉGBANA CENTRE(SAMIA))). | DG27: Projet d'investissement | DH27: Prêt | DI27: Prêt concessionnel | DJ27: https://documentation-anbenin.org | DK27: 60000000
A28: P-0025-BADEA-2012 | B28: Projet de pont sur le fleuve "Mono" | F28: INFRASTRUCTURES ROUTIERES ET TRANSPORT | N28: Faciliter les échanges transfrontaliers et sécuriser la liaison permanente entre le Bénin et le Togo par la construction d'un ouvrage de franchissement moderne sur le fleuve Mono à Athiémé. | U28: Mono | V28: Athiémé | W28: Athiémé Centre | Z28: 40865 | AA28: 40926 | AD28: 43646 | AL28: EUR | AN28: 5200000000 | AR28: 0 | AS28: 5200000000 | BA28: Banque Arabe pour le Développement Économique en Afrique | BB28: BADEA | BC28: MULTILATERAUX | DF28: MONO (ATHIÉMÉ(ATHIÉMÉ CENTRE)). | DG28: Projet d'investissement | DH28: Prêt | DI28: Prêt concessionnel | DJ28: https://documentation-anbenin.org | DK28: 10400000
A29: P-0026-Danemark-2012 | B29: Contribution au Fonds d'Appui au Développement des Communes (FADEC) | F29: DÉCENTRALISATION | N29: Contribuer à la réduction de la pauvreté et à l'amélioration durable des conditions de vie des populations par le renforcement de la décentralisation et le financement des investissements des collectivités territoriales, afin d'améliorer la fourniture des services publics locaux. | U29: National | Z29: 40941 | AA29: 41011 | AD29: 43465 | AL29: DKK | AN29: 3520000000 | AR29: 3520000000 | AS29: 0 | BA29: Danemark | BB29: Danemark | BC29: BILATERAUX | DF29: NATIONAL | DG29: Fonds commun | DH29: Don | DI29: Don | DJ29: Programme d'appui danois à la décentralisation (Danida) et FADeC - Ministère de la Décentralisation ; documentation du FADeC | DK29: 40000000
A30: P-0027-Danemark-2012 | B30: Programme d'appui au sous-secteur de l'enseignement primaire au Bénin | F30: ÉDUCATION | N30: Renforcer les capacités financières locales des communes à travers des transferts budgétaires dédiés au développement d'infrastructures de base sous maîtrise d'ouvrage communale. | U30: National | Z30: 40984 | AA30: 41044 | AD30: 42916 | AL30: DKK | AN30: 11060000000 | AR30: 11060000000 | AS30: 0 | BA30: Danemark | BB30: Danemark | BC30: BILATERAUX | DF30: NATIONAL | DG30: Programme d'investissement | DH30: Don | DI30: Don | DJ30: https://evaluation.gouv.bj | DK30: 125000000
A31: P-0028-Danemark-2012 | B31: Programme d'appui au sous-secteur du transport rural au Bénin | F31: INFRASTRUCTURES ROUTIERES ET TRANSPORT | N31: Améliorer la qualité et l'accès à l'éducation primaire publique en milieu rural, notamment dans les départements du Nord, à travers la construction de salles de classe et la formation des enseignants. | U31: Alibori, Atacora, Borgou, Donga | Z31: 40984 | AA31: 41082 | AD31: 43830 | AL31: DKK | AN31: 8850000000 | AR31: 8850000000 | AS31: 0 | BA31: Danemark | BB31: Danemark | BC31: BILATERAUX | DF31: ALIBORI ; ATACORA ; BORGOU ; DONGA. | DG31: Programme d'investissement | DH31: Don | DI31: Don | DJ31: https://evaluation.gouv.bj | DK31: 100000000
A32: P-0028-PAYS-BAS-2012 | B32: Programme d'appui au sous-secteur du transport rural au Bénin | F32: INFRASTRUCTURES ROUTIERES ET TRANSPORT | N32: Co-investir dans l'extension des linéaires de pistes de desserte rurale réhabilitées dans les bassins de production agricole pour optimiser les circuits de commercialisation. | U32: Alibori, Atacora, Borgou, Donga | Z32: 41193 | AA32: 41201 | AD32: 43100 | AL32: EUR | AN32: 3481277936 | AR32: 3481277936 | AS32: 0 | BA32: Royaume des Pays-Bas / Coopération néerlandaise | BB32: PAYS-BAS | BC32: BILATERAUX | DF32: ALIBORI ; ATACORA ; BORGOU ; DONGA. | DG32: Programme d'investissement | DH32: Don | DI32: Don | DJ32: evaluation.gouv.bj | DK32: 5307635.2
A33: P-0029-BOAD-2012 | B33: Etudes de faisabilité technique et d'impact environnemental et social du projet d'aménagement et de bitumage de la route Lalo-Agbangnizoun-Abomey-Djidja-Agouna-Tchetti-Doumè-Ottola-Bantè | F33: INFRASTRUCTURES ROUTIERES ET TRANSPORT | N33: Réaliser les études techniques détaillées et d'ingénierie nécessaires pour la future construction et le bitumage de cet axe routier transversal reliant les départements du Couffo, du Zou et des Collines. | U33: Couffo, Zou, Collines | V33: Lalo, Agbangnizoun, Abomey, Djidja, Savalou | W33: Agouna, Tchetti) ; Savè(Dovè, Obola | Z33: 40988 | AA33: 41054 | AD33: 42369 | AL33: XOF | AN33: 480000000 | AR33: 0 | AS33: 480000000 | BA33: Banque Ouest Africaine de Développement | BB33: BOAD | BC33: MULTILATERAUX | DF33: COUFFO (LALO) ; ZOU (AGBANGNIZOUN, ABOMEY, DJIDJA) ; COLLINES (SAVALOU(AGOUNA, TCHETTI) ; SAVÈ(DOVÈ, OBOLA)). | DG33: Étude / Préparation | DH33: Prêt | DI33: Prêt non concessionnel | DJ33: https://boad.org | DK33: 480000000
A34: P-0030-AFD-2012 | B34: Programme d'Appui à la Santé Maternelle et Infantile (PASMI) | F34: SANTÉ | N34: Réduire la mortalité maternelle et néonatale dans les zones cibles en améliorant la qualité des soins obstétricaux d'urgence et en équipant les maternités des hôpitaux de zone. | U34: Ouémé, Plateau, Zou, Collines | V34: Porto-Novo, Akpro-Missérété, Avrankou, Pobè, Adja-Ouéré, Kétou, Abomey, Bohicon, Dassa-Zoumé, Savalou | Z34: 41044 | AA34: 41079 | AD34: 43281 | AL34: EUR | AN34: 6559570000 | AR34: 6559570000 | AS34: 0 | BA34: Agence Française de Développement | BB34: AFD | BC34: BILATERAUX | DF34: OUÉMÉ (PORTO-NOVO, AKPRO-MISSÉRÉTÉ, AVRANKOU) ; PLATEAU (POBÈ, ADJA-OUÉRÉ, KÉTOU) ; ZOU (ABOMEY, BOHICON) ; COLLINES (DASSA-ZOUMÉ, SAVALOU). | DG34: Programme d'investissement | DH34: Don | DI34: Don | DJ34: https://evaluation.gouv.bj | DK34: 10000000
A35: P-0031-BM-2012 | B35: Projet de services décentralisées conduits par les communautés (PSDCC) | F35: DÉCENTRALISATION | N35: Améliorer l'accès des communautés vulnérables à des infrastructures socio-économiques de base gérées de façon participative et renforcer le système national de filets sociaux. | U35: National | Z35: 41025 | AA35: 41087 | AD35: 43465 | AL35: DTS | AN35: 23000000000 | AR35: 0 | AS35: 23000000000 | BA35: Banque mondiale | BB35: BM | BC35: MULTILATERAUX | DF35: NATIONAL | DG35: Projet d'investissement | DH35: Prêt | DI35: Prêt concessionnel | DJ35: https://banquemondiale.org | DK35: 29600000
A36: P-0032-BIDC-2012 | B36: Projet d'équipement et de réhabilitation de formations sanitaires | F36: SANTÉ | N36: Moderniser le plateau technique de plusieurs hôpitaux de référence au Bénin par l'acquisition de matériels d'imagerie, de laboratoire et de réanimation médicale. | U36: Littoral, Borgou, Ouémé, Atacora | V36: Cotonou, Parakou, Porto-Novo, Natitingou | Z36: 41093 | AA36: 41116 | AD36: 43100 | AL36: EUR | AN36: 5000000000 | AR36: 0 | AS36: 5000000000 | BA36: Banque d’Investissement et de Développement de la CEDEAO | BB36: BIDC | BC36: MULTILATERAUX | DF36: LITTORAL (COTONOU) ; BORGOU (PARAKOU) ; OUÉMÉ (PORTO-NOVO) ; ATACORA (NATITINGOU). | DG36: Projet d'investissement | DH36: Prêt | DI36: Prêt non concessionnel | DJ36: evaluation.gouv.bj | DK36: 10000000
A37: P-0033-BOAD-2012 | B37: Projet d'aménagement de la route des pêches | F37: INFRASTRUCTURES ROUTIERES ET TRANSPORT | N37: Développer le potentiel touristique et halieutique de la zone côtière par la construction d'une route bitumée reliant Cotonou à Ouidah le long du littoral. | U37: Littoral, Atlantique | V37: Cotonou, Abomey-Calavi | W37: Fidjrossè, Godomey(Togbin)) ; Ouidah(Avlékété, Houakpè-Daho | Z37: 41054 | AA37: 41120 | AD37: 42735 | AL37: XOF | AN37: 12000000000 | AR37: 0 | AS37: 12000000000 | BA37: Banque Ouest Africaine de Développement | BB37: BOAD | BC37: MULTILATERAUX | DF37: LITTORAL (COTONOU(FIDJROSSÈ)) ; ATLANTIQUE (ABOMEY-CALAVI(GODOMEY(TOGBIN)) ; OUIDAH(AVLÉKÉTÉ, HOUAKPÈ-DAHO)). | DG37: Projet d'investissement | DH37: Prêt | DI37: Prêt non concessionnel | DJ37: boad.org | DK37: 12000000000
A38: P-0034-Chine-2012 | B38: Financement de divers projets | F38: GOUVERNANCE | N38: Appuyer l'État béninois dans la réalisation d'infrastructures administratives et d'équipements socioculturels définis dans le cadre des accords bilatéraux de coopération. | U38: Littoral, Atlantique | V38: Cotonou, Abomey-Calavi | Z38: 41142 | AA38: 41170 | AD38: 43100 | AL38: CNY | AN38: 10790000000 | AR38: 0 | AS38: 10790000000 | BA38: Chine | BB38: Chine | BC38: BILATERAUX | DF38: LITTORAL (COTONOU) ; ATLANTIQUE (ABOMEY-CALAVI). | DG38: Projet d'investissement | DH38: Prêt | DI38: Prêt | DJ38: https://gouv.bj | DK38: 141000000
A39: P-0035-EXIMBANK INDE-2012 | B39: Projet d'installation d'une usine de montage de tracteurs et d'équipements agricoles à Ouidah | F39: AGRICULTURE | N39: Promouvoir la mécanisation de l'agriculture béninoise par la mise en place d'une unité industrielle de montage de tracteurs et de machines agricoles afin de réduire la pénibilité du travail de terre. | U39: Atlantique | V39: Ouidah | W39: Pahou | Z39: 41064 | AA39: 41144 | AD39: 42735 | AL39: EUR | AN39: 7500000000 | AR39: 0 | AS39: 7500000000 | BA39: Export-Import Bank of India | BB39: EXIMBANK INDE | BC39: BILATERAUX | DF39: ATLANTIQUE (OUIDAH(PAHOU)). | DG39: Projet d'investissement | DH39: Prêt | DI39: Prêt concessionnel | DJ39: documentation-anbenin.org | DK39: 15000000
A40: P-0036-BM-2012 | B40: Première phase du Programme Régional Ouest Africain d'Infrastructures de Communication-Projet Bénin | F40: NUMÉRIQUE | N40: Accroître la connectivité numérique internationale du Bénin et réduire les coûts des services de télécommunications à large bande grâce à l'extension du réseau de fibre optique. | U40: Littoral, Atlantique, Ouémé | V40: Cotonou, Abomey-Calavi, Porto-Novo | Z40: 41102 | AA40: 41156 | AD40: 43646 | AL40: DTS | AN40: 17500000000 | AR40: 0 | AS40: 17500000000 | BA40: Banque mondiale | BB40: BM | BC40: MULTILATERAUX | DF40: LITTORAL (COTONOU) ; ATLANTIQUE (ABOMEY-CALAVI) ; OUÉMÉ (PORTO-NOVO). | DG40: Projet d'investissement | DH40: Prêt | DI40: Prêt concessionnel | DJ40: banquemondiale.org | DK40: 23200000
A41: P-0037-BM-2012 | B41: Financement additionnel du Projet de Renforcement de la Performance du Système de Santé (PRPSS) | F41: SANTÉ | N41: Améliorer la qualité des soins de santé maternelle et infantile en étendant le mécanisme de financement basé sur les résultats aux formations sanitaires des départements sélectionnés. | U41: Atacora, Donga, Borgou, Alibori, Zou, Collines | Z41: 41025 | AA41: 41156 | AD41: 43100 | AL41: EUR | AN41: 5000000000 | AR41: 5000000000 | AS41: 0 | BA41: Banque mondiale | BB41: BM | BC41: MULTILATERAUX | DF41: ATACORA ; DONGA ; BORGOU ; ALIBORI ; ZOU ; COLLINES. | DG41: Projet d'investissement | DH41: Don | DI41: Don | DJ41: banquemondiale.org | DK41: 10000000
A42: P-0038-Chine-2012 | B42: Projet de réhabilitation de la route Akassato-Bohicon (Accord cadre) | F42: INFRASTRUCTURES ROUTIERES ET TRANSPORT | N42: Moderniser et élargir l'axe routier central RNIE 2 reliant l'agglomération de Cotonou au centre du pays afin d'améliorer la sécurité routière et de fluidifier le transport de marchandises. | U42: Atlantique, Zou | V42: Abomey-Calavi, Zè, Toffo, Zogbodomey, Bohicon | W42: Akassato | Z42: 41187 | AA42: 41227 | AD42: 43465 | AL42: CNY | AN42: 64232000000 | AR42: 0 | AS42: 64232000000 | BA42: Chine | BB42: Chine | BC42: BILATERAUX | DF42: ATLANTIQUE (ABOMEY-CALAVI(AKASSATO), ZÈ, TOFFO) ; ZOU (ZOGBODOMEY, BOHICON). | DG42: Projet d'investissement | DH42: Prêt | DI42: Prêt | DJ42: documentation-anbenin.org | DK42: 800000000
A43: P-0039-BAD-2012 | B43: Programme d'Appui aux Réformes Economiques et Financières (PAREF) | F43: GOUVERNANCE | N43: Soutenir les réformes de l'administration publique visant à renforcer l'efficacité de la mobilisation des recettes fiscales et à améliorer la gouvernance des entreprises publiques. | U43: National | Z43: 41199 | AA43: 41206 | AD43: 42369 | AL43: UC | AN43: 23470000000 | AR43: 0 | AS43: 23470000000 | BA43: Banque Africaine de Développement | BB43: BAD | BC43: MULTILATERAUX | DF43: NATIONAL | DG43: Programme d'investissement | DH43: Prêt | DI43: Prêt concessionnel | DJ43: documentation-anbenin.org | DK43: 30000000
A44: P-0040-Iran-2012 | B44: Projet de construction et d'équipement d'un bloc pédagogique de type R+2 à l'Université d'Abomey-Calavi | F44: ÉDUCATION | N44: Accroître les capacités d'accueil des étudiants à l'Université d'Abomey-Calavi par l'érection de salles de cours et d'amphithéâtres modernes équipés. | U44: Atlantique | V44: Abomey-Calavi | Z44: 41093 | AA44: 41227 | AD44: 42369 | AL44: EUR | AN44: 500000000 | AR44: 500000000 | AS44: 0 | BA44: Iran | BB44: Iran | BC44: BILATERAUX | DF44: ATLANTIQUE (ABOMEY-CALAVI). | DG44: Projet d'investissement | DH44: Don | DI44: Don | DJ44: https://gouv.bj | DK44: 1000000
A45: P-0041-AFD-2012 | B45: Projet d'Appui à la Décentralisation et à la Déconcentration au Bénin (PA2D) | F45: DÉCENTRALISATION | N45: Renforcer la gouvernance locale et l'efficacité des préfectures et des mairies dans la planification du développement du territoire et la gestion budgétaire. | U45: National | Z45: 41235 | AA45: 41240 | AD45: 42735 | AL45: EUR | AN45: 327978500 | AR45: 327978500 | AS45: 0 | BA45: Agence Française de Développement | BB45: AFD | BC45: BILATERAUX | DF45: NATIONAL | DG45: Projet d'investissement | DH45: Don | DI45: Don | DJ45: evaluation.gouv.bj | DK45: 500000
A46: P-0042-PAYS-BAS-2012 | B46: Programme Pluriannuel d'appui au secteur Eau et Assainissement-Phase 2 | F46: EAU ET ASSAINISSEMENT | N46: Fournir un accès durable à l'eau potable et à des infrastructures d'assainissement adéquates pour les populations rurales à travers des réformes sectorielles intégrées. | U46: National | Z46: 40918 | AA46: 41254 | AD46: 42369 | AL46: EUR | AN46: 40524000000 | AR46: 40524000000 | AS46: 0 | BA46: Royaume des Pays-Bas / Coopération néerlandaise | BB46: PAYS-BAS | BC46: BILATERAUX | DF46: NATIONAL | DG46: Programme d'investissement | DH46: Don | DI46: Don | DJ46: evaluation.gouv.bj | DK46: 61783809
A47: P-0043-BOAD-2013 | B47: Avance de fonds pour le financement des études technico-économique, environnementales et sociales du projet de reconstruction en 2x2 voies de la traversée et du contournement de la ville de Parakou | F47: INFRASTRUCTURES ROUTIERES ET TRANSPORT | N47: Élaborer les dossiers d'avant-projet détaillé et d'impact environnemental pour la modernisation routière de la traversée urbaine de Parakou. | U47: Borgou | V47: Parakou | Z47: 41313 | AA47: 41409 | AD47: 42735 | AL47: XOF | AN47: 195382000 | AR47: 0 | AS47: 195382000 | BA47: Banque Ouest Africaine de Développement | BB47: BOAD | BC47: MULTILATERAUX | DF47: BORGOU (PARAKOU). | DG47: Étude / Préparation | DH47: Prêt | DI47: Avance de préparation de projet | DJ47: boad.org | DK47: 195382000
A48: P-0044-BIDC-2013 | B48: Projet de pavage de rues et d'assainissement dans les communes de Ouidah, Bohicon, Pobè, Sakété et Dassa-Zoumé | F48: CADRE DE VIE | N48: Améliorer les conditions environnementales et sanitaires dans les centres urbains de cinq communes par le pavage de voies et la pose de collecteurs d'égouts. | U48: Atlantique, Zou, Plateau, Collines | V48: Ouidah, Bohicon, Pobè, Sakété, Dassa-Zoumé | Z48: 41317 | AA48: 41466 | AD48: 43830 | AL48: UC | AN48: 4505921562 | AR48: 0 | AS48: 4505921562 | BA48: Banque d’Investissement et de Développement de la CEDEAO | BB48: BIDC | BC48: MULTILATERAUX | DF48: ATLANTIQUE (OUIDAH) ; ZOU (BOHICON) ; PLATEAU (POBÈ, SAKÉTÉ) ; COLLINES (DASSA-ZOUMÉ). | DG48: Projet d'investissement | DH48: Prêt | DI48: Prêt non concessionnel | DJ48: evaluation.gouv.bj | DK48: 5731765
A49: P-0045-BID-2013 | B49: Projet de construction du pont de Tovégbamè | F49: INFRASTRUCTURES ROUTIERES ET TRANSPORT | N49: Assurer la continuité territoriale et désenclaver les localités riveraines de la vallée de l'Ouémé à Adjohoun en construisant un ouvrage de franchissement permanent. | U49: Ouémé | V49: Adjohoun | Z49: 41321 | AA49: 41374 | AD49: 43100 | AL49: DI | AN49: 4500000000 | AR49: 0 | AS49: 4500000000 | BA49: Banque Islamique de Développement | BB49: BID | BC49: MULTILATERAUX | DF49: OUÉMÉ (ADJOHOUN). | DG49: Projet d'investissement | DH49: Prêt | DI49: Prêt concessionnel | DJ49: documentation-anbenin.org | DK49: 5880000
A50: P-0046-BID-2013 | B50: Programme d'amélioration de la productivité agricole des petits exploitants (PAPAPE) | F50: AGRICULTURE | N50: Accroître les rendements rizicoles et maraîchers des petits producteurs par l'aménagement de bas-fonds irrigués et la fourniture d'équipements de transformation post-récolte. ; Financer de petits périmètres maraîchers et pastoraux pour renforcer l'autonomie économique des femmes et jeunes ruraux dans les zones de production. ; Développer les capacités logistiques et de stockage des coopératives agricoles pour réduire les pertes après récolte des céréales et des produits vivriers. ; Renforcer les services de conseil agricole de proximité et l'accès aux intrants certifiés pour optimiser les performances agropastorales régionales. | U50: Borgou, Alibori, Atacora, Donga, Zou, Collines | Z50: 41374 | AA50: 41437 | AD50: 44196 | AL50: DI | AN50: 6800000000 | AR50: 0 | AS50: 6800000000 | BA50: Banque Islamique de Développement | BB50: BID | BC50: MULTILATERAUX | DF50: BORGOU ; ALIBORI ; ATACORA ; DONGA ; ZOU ; COLLINES. | DG50: Programme d'investissement | DH50: Prêt | DI50: Istisna'a | Prêt (FISD) | Prêt (vente à tempérament) | Prêt concessionnel | DJ50: documentation-anbenin.org | DK50: 8940000
A51: P-0047-BM-2013 | B51: Financement additionnel du Projet de gestion des Forêts et Terroirs Riverains (PGFTR) | F51: CADRE DE VIE | N51: Renforcer les investissements communautaires dans la réhabilitation des forêts classées et promouvoir des activités génératrices de revenus alternatives durables pour réduire le déboisement. | U51: Alibori, Atacora, Borgou | V51: Banikoara, Karimama, Tanguiéta, Kérou, Tchaourou | Z51: 41354 | AA51: 41374 | AD51: 43343 | AL51: EUR | AN51: 1000000000 | AR51: 0 | AS51: 1000000000 | BA51: Banque mondiale | BB51: BM | BC51: MULTILATERAUX | DF51: ALIBORI (BANIKOARA, KARIMAMA) ; ATACORA (TANGUIÉTA, KÉROU) ; BORGOU (TCHAOUROU). | DG51: Projet d'investissement | DH51: Prêt | DI51: Prêt concessionnel | DJ51: banquemondiale.org | DK51: 2000000
A52: P-0047-FEM / GEF-2013 | B52: Financement additionnel du Projet de gestion des Forêts et Terroirs Riverains (PGFTR) | F52: CADRE DE VIE | N52: Appuyer l'atténuation du changement climatique par la conservation du carbone forestier et l'amélioration de la gestion intégrée des écosystèmes forestiers riverains. | U52: Alibori, Atacora, Borgou | V52: Banikoara, Karimama, Tanguiéta, Kérou, Tchaourou | Z52: 41354 | AA52: 41374 | AD52: 43343 | AL52: EUR | AN52: 2780000000 | AR52: 2780000000 | AS52: 0 | BA52: Fonds pour l’Environnement Mondial | BB52: FEM / GEF | BC52: MULTILATERAUX | DF52: ALIBORI (BANIKOARA, KARIMAMA) ; ATACORA (TANGUIÉTA, KÉROU) ; BORGOU (TCHAOUROU). | DG52: Projet d'investissement | DH52: Don | DI52: Fonds fiduciaire (Trust Fund) | DJ52: banquemondiale.org | DK52: 5560000
A53: P-0048-BM-2013 | B53: Huitième financement d'appui à la réduction de la pauvreté (PRSC-8) | F53: GOUVERNANCE | N53: Consolider les performances de gestion macroéconomique, améliorer le cadre de passation des marchés publics et accroître l'efficience budgétaire dans les secteurs sociaux. | U53: National | Z53: 41381 | AA53: 41450 | AD53: 42004 | AL53: DTS | AN53: 15000000000 | AR53: 0 | AS53: 15000000000 | BA53: Banque mondiale | BB53: BM | BC53: MULTILATERAUX | DF53: NATIONAL | DG53: Projet d'investissement | DH53: Prêt | DI53: Prêt concessionnel | DJ53: banquemondiale.org | DK53: 19900000
A54: P-0049-Allemagne-2013 | B54: Fonds Commun Budgétaire - Programme Education-phase 3 | F54: ÉDUCATION | N54: Appuyer la mise en œuvre de la stratégie sectorielle de l'éducation en cofinançant les plans nationaux pour l'universalisation de la scolarisation primaire de qualité. | U54: National | Z54: 41430 | AA54: 41562 | AD54: 42735 | AL54: EUR | AN54: 3279785000 | AR54: 3279785000 | AS54: 0 | BA54: Allemagne | BB54: Allemagne | BC54: BILATERAUX | DF54: NATIONAL | DG54: Fonds commun | DH54: Don | DI54: Don | DJ54: evaluation.gouv.bj | DK54: 5000000
A55: P-0050-BAD-2013 | B55: Projet d'amélioration de la gestion des boues de vidange du Grand-Nokoué | F55: CADRE DE VIE | N55: Assainir l'environnement urbain du Grand Nokoué en construisant des stations d'épuration des boues de vidange et en structurant la filière de collecte et de traitement. ; Améliorer les conditions d'assainissement de la zone côtière par la mise en place d'infrastructures adéquates de collecte, de transport et de traitement écologique des boues sanitaires. | U55: Littoral, Atlantique, Ouémé | V55: Cotonou, Abomey-Calavi, Ouidah, Porto-Novo, Sèmè-Podji | Z55: 41435 | AA55: 41600 | AD55: 43830 | AL55: EUR | AN55: 728309057 | AR55: 728309057 | AS55: 0 | BA55: Banque Africaine de Développement | BB55: BAD | BC55: MULTILATERAUX | DF55: LITTORAL (COTONOU) ; ATLANTIQUE (ABOMEY-CALAVI, OUIDAH) ; OUÉMÉ (PORTO-NOVO, SÈMÈ-PODJI). | DG55: Projet d'investissement | DH55: Don | DI55: Fonds fiduciaire (Trust Fund) | DJ55: documentation-anbenin.org | DK55: 1110300
A56: P-0051-BOAD-2013 | B56: Avance de fonds pour le financement de l'étude de faisabilité du volet pistes rurales du Projet d'Appui à la Croissance Economique Rurale (PACER) | F56: AGRICULTURE | N56: Définir la cartographie technique et économique des réseaux de pistes de desserte rurale prioritaires à réhabiliter au sein des communes agricoles du Bénin. | U56: National | Z56: 41437 | AA56: 41620 | AD56: 42369 | AL56: XOF | AN56: 285000000 | AR56: 0 | AS56: 285000000 | BA56: Banque Ouest Africaine de Développement | BB56: BOAD | BC56: MULTILATERAUX | DF56: NATIONAL | DG56: Étude / Préparation | DH56: Prêt | DI56: Avance de préparation de projet | DJ56: boad.org | DK56: 285000000
A57: P-0052-ECOBANK-Bénin-2013 | B57: Financement des travaux d'achèvement de la construction de l'aéroport de Tourou (Parakou) | F57: INFRASTRUCTURES ROUTIERES ET TRANSPORT | N57: Mener à bien les infrastructures terminales, de piste et de balisage de la plateforme aéroportuaire de Tourou afin de doter le Septentrion d'un aéroport moderne opérationnel. | U57: Borgou | V57: Parakou | W57: Tourou | Z57: 41436 | AA57: 41461 | AD57: 42369 | AL57: XOF | AN57: 15500000000 | AR57: 0 | AS57: 15500000000 | BA57: ECOBANK-Bénin | BB57: ECOBANK-Bénin | BC57: PRIVE | DF57: BORGOU (PARAKOU(TOUROU)). | DG57: Projet d'investissement | DH57: Prêt | DI57: Prêt commercial | DJ57: documentation-anbenin.org | DK57: 15500000000
A58: P-0053-FIDA / IFAD-2013 | B58: Projet d'appui à la promotion des services financiers ruraux adaptés (PAPSFRA) | F58: MICROFINANCE | N58: Améliorer les conditions de vie des populations rurales pauvres en favorisant leur accès durable à des services financiers de microfinance diversifiés et adaptés à l'agriculture. ; Consolider les capacités de gouvernance des mutuelles de crédit et appuyer l'innovation technologique pour le déploiement de produits d'épargne rurale. | U58: National | Z58: 41374 | AA58: 41470 | AD58: 43830 | AL58: EUR | AN58: 15300000000 | AR58: 7650000000 | AS58: 7650000000 | BA58: Fonds International de Développement Agricole | BB58: FIDA / IFAD | BC58: MULTILATERAUX | DF58: NATIONAL | DG58: Projet d'investissement | DH58: Don | Prêt | DI58: Don | Prêt concessionnel | DJ58: evaluation.gouv.bj | DK58: 30600000
A59: P-0054-BOAD-2013 | B59: Avance de fonds pour le financement des études économique, technique détaillée, d'impact environnemental et social et l'élaboration du dossier d'appel d'offres relatives au projet d'aménagement et de bitumage de la route Bétérou-Tchaourou-Frontière du Nigeria et de construction du pont sur le fleuve Okpara au Bénin. | F59: INFRASTRUCTURES ROUTIERES ET TRANSPORT | N59: Préparer l'ingénierie et l'évaluation environnementale complexes nécessaires au bitumage de cet axe routier international stratégique. | U59: Borgou | V59: Tchaourou | W59: Bétérou, Tchaourou Centre | Z59: 41358 | AA59: 41485 | AD59: 42369 | AL59: XOF | AN59: 294845000 | AR59: 0 | AS59: 294845000 | BA59: Banque Ouest Africaine de Développement | BB59: BOAD | BC59: MULTILATERAUX | DF59: BORGOU (TCHAOUROU(BÉTÉROU, TCHAOUROU CENTRE)). | DG59: Étude / Préparation | DH59: Prêt | DI59: Avance de préparation de projet | DJ59: boad.org | DK59: 294845000
A60: P-0055-BOAD-2013 | B60: Projet de pavage de rues et d'assainissement dans les communes de Kandi et Savalou et de construction d'un collecteur d'assainissement de crête à Bohicon | F60: CADRE DE VIE | N60: Améliorer la mobilité urbaine à Kandi et Savalou, et résoudre durablement les problèmes d'érosion et d'inondations pluviales à Bohicon par un collecteur de crête majeur. | U60: Alibori, Collines, Zou | V60: Kandi, Savalou, Bohicon | Z60: 41450 | AA60: 41485 | AD60: 43465 | AL60: XOF | AN60: 6000000000 | AR60: 0 | AS60: 6000000000 | BA60: Banque Ouest Africaine de Développement | BB60: BOAD | BC60: MULTILATERAUX | DF60: ALIBORI (KANDI) ; COLLINES (SAVALOU) ; ZOU (BOHICON). | DG60: Projet d'investissement | DH60: Prêt | DI60: Prêt non concessionnel | DJ60: boad.org | DK60: 6000000000
A61: P-0056-BOAD-2013 | B61: Projet de pavage de rues et d'assainissement dans les communes de Kétou, Tchaourou, Savè (phase 2) et de Kpomassè | F61: CADRE DE VIE | N61: Étendre le réseau de voirie assainie dans les quartiers centraux des quatre communes afin de valoriser l'habitat urbain et de faciliter le transport local. | U61: Plateau, Borgou, Collines, Atlantique | V61: Kétou, Tchaourou, Savè, Kpomassè | Z61: 41485 | AA61: 41620 | AD61: 43465 | AL61: XOF | AN61: 8000000000 | AR61: 0 | AS61: 8000000000 | BA61: Banque Ouest Africaine de Développement | BB61: BOAD | BC61: MULTILATERAUX | DF61: PLATEAU (KÉTOU) ; BORGOU (TCHAOUROU) ; COLLINES (SAVÈ) ; ATLANTIQUE (KPOMASSÈ). | DG61: Projet d'investissement | DH61: Prêt | DI61: Prêt non concessionnel | DJ61: boad.org | DK61: 8000000000
A62: P-0057-BM-2013 | B62: Projet d'Appui au Renforcement de la Capacité de Pilotage et d'Administration des Politiques et Programmes de l'Alimentation et de la Nutrition | F62: SANTÉ | N62: Structurer la réponse multisectorielle face à la malnutrition chronique à travers un appui institutionnel au CAN et la mise en œuvre de plans de suivi de nutrition déconcentrés. | U62: National | Z62: 41492 | AA62: 41626 | AD62: 43465 | AL62: EUR | AN62: 372908500 | AR62: 372908500 | AS62: 0 | BA62: Banque mondiale | BB62: BM | BC62: MULTILATERAUX | DF62: NATIONAL | DG62: Projet d'investissement | DH62: Don | DI62: Don | DJ62: banquemondiale.org | DK62: 745817
A63: P-0058-EXIMBANK DE CHINE-2013 | B63: Projet de réhabilitation de la route Akassato-Bohicon-Lot 3 | F63: INFRASTRUCTURES ROUTIERES ET TRANSPORT | N63: Achever la réhabilitation lourde et le calibrage de la section routière centrale reliant Toffo à Bohicon afin d'assurer la sécurité sur le corridor de transport international. | U63: Atlantique, Zou | V63: Abomey-Calavi, Zè, Toffo, Zogbodomey, Bohicon | W63: Akassato | Z63: 41418 | AA63: 41509 | AD63: 42521 | AL63: CNY | AN63: 64800000000 | AR63: 0 | AS63: 64800000000 | BA63: Banque chinoise d’import-export | BB63: EXIMBANK DE CHINE | BC63: BILATERAUX | DF63: ATLANTIQUE (ABOMEY-CALAVI(AKASSATO), ZÈ, TOFFO) ; ZOU (ZOGBODOMEY, BOHICON). | DG63: Projet d'investissement | DH63: Prêt | DI63: Prêt concessionnel | DJ63: documentation-anbenin.org | DK63: 800000000
A64: P-0059-EXIMBANK INDE-2013 | B64: Projet de renforcement du système d'adduction d'eau dans 69 villages | F64: EAU ET ASSAINISSEMENT | N64: Améliorer significativement le taux de desserte en eau potable en milieu rural par le forage et la construction de réseaux complets d'adduction d'eau villageoise dans 69 localités. | U64: National | Z64: 41382 | AA64: 41523 | AD64: 43465 | AL64: EUR | AN64: 21305000000 | AR64: 0 | AS64: 21305000000 | BA64: Export-Import Bank of India | BB64: EXIMBANK INDE | BC64: BILATERAUX | DF64: NATIONAL | DG64: Projet d'investissement | DH64: Prêt | DI64: Prêt concessionnel | DJ64: documentation-anbenin.org | DK64: 42610000
A65: P-0060-BM-2013 | B65: Projet d'aménagement urbain et d'appui à la décentralisation (PAURAD) | F65: DÉCENTRALISATION | N65: Rehausser la capacité de gestion financière et d'investissement des municipalités béninoises clés et cofinancer des infrastructures urbaines de voirie et de drainage. | U65: Littoral, Atlantique, Ouémé, Borgou, Zou, Atacora, Donga, Mono, Couffo, Plateau, Collines | V65: Cotonou, Abomey-Calavi, Porto-Novo, Parakou, Abomey, Bohicon, Natitingou, Djougou, Lokossa, Aplahoué, Pobè, Dassa-Zoumé | Z65: 41431 | AA65: 41556 | AD65: 44196 | AL65: DTS | AN65: 30000000000 | AR65: 0 | AS65: 30000000000 | BA65: Banque mondiale | BB65: BM | BC65: MULTILATERAUX | DF65: LITTORAL (COTONOU) ; ATLANTIQUE (ABOMEY-CALAVI) ; OUÉMÉ (PORTO-NOVO) ; BORGOU (PARAKOU) ; ZOU (ABOMEY, BOHICON) ; ATACORA (NATITINGOU) ; DONGA (DJOUGOU) ; MONO (LOKOSSA) ; COUFFO (APLAHOUÉ) ; PLATEAU (POBÈ) ; COLLINES (DASSA-ZOUMÉ). | DG65: Projet d'investissement | DH65: Prêt | DI65: Prêt concessionnel | DJ65: banquemondiale.org | DK65: 40100000
A66: P-0061-Pays-Bas-2013 | B66: Projet de consolidation des acquis et des actions de sécurisation foncière | F66: GOUVERNANCE | N66: Soutenir la mise en place du cadre légal et opérationnel du nouveau code foncier et domanial, et appuyer l'ANDF pour sécuriser les transactions foncières urbaines et rurales. | U66: National | Z66: 41344 | AA66: 41607 | AD66: 43100 | AL66: EUR | AN66: 889000000 | AR66: 889000000 | AS66: 0 | BA66: Pays-Bas | BB66: Pays-Bas | BC66: BILATERAUX | DF66: NATIONAL | DG66: Projet d'investissement | DH66: Don | DI66: Don | DJ66: evaluation.gouv.bj | DK66: 1355389.5
A67: P-0062-BOAD-2013 | B67: Projet de réhabilitation et de renforcement de la route Parakou-Djougou | F67: INFRASTRUCTURES ROUTIERES ET TRANSPORT | N67: Améliorer la liaison transversale RNIE 3 entre Parakou et Djougou en renforçant la chaussée routière pour supporter le trafic croissant de transit et régional. | U67: Borgou, Donga | V67: Parakou, Djougou | Z67: 41450 | AA67: 41631 | AD67: 43100 | AL67: XOF | AN67: 25000000000 | AR67: 0 | AS67: 25000000000 | BA67: Banque Ouest Africaine de Développement | BB67: BOAD | BC67: MULTILATERAUX | DF67: BORGOU (PARAKOU) ; DONGA (DJOUGOU). | DG67: Projet d'investissement | DH67: Prêt | DI67: Prêt non concessionnel | DJ67: boad.org | DK67: 25000000000
A68: P-0063-BOAD-2013 | B68: Projet de renforcement du système d'alimentation en eau potable du centre secondaire de Djougou et des localités de Tchaourou, Savè et Tanguiéta en République du Bénin | F68: EAU ET ASSAINISSEMENT | N68: Sécuriser et accroître la production d'eau potable de la SONEB dans quatre centres urbains intermédiaires par la rénovation des stations de pompage et l'extension du réseau. | U68: Donga, Borgou, Collines, Atacora | V68: Djougou, Tchaourou, Savè, Tanguiéta | Z68: 41450 | AA68: 41631 | AD68: 43465 | AL68: XOF | AN68: 5811000000 | AR68: 0 | AS68: 5811000000 | BA68: Banque Ouest Africaine de Développement | BB68: BOAD | BC68: MULTILATERAUX | DF68: DONGA (DJOUGOU) ; BORGOU (TCHAOUROU) ; COLLINES (SAVÈ) ; ATACORA (TANGUIÉTA). | DG68: Projet d'investissement | DH68: Prêt | DI68: Prêt non concessionnel | DJ68: boad.org | DK68: 5811000000
A69: P-0064-BIDC-2013 | B69: Projet de pavage de rues et d'assainissement dans les communes de Ouidah, Bohicon, Pobè, Sakété et Dassa-Zoumé, Phase 2 | F69: CADRE DE VIE | N69: densifier les interventions d'assainissement routier urbain dans les quartiers à forte densité des cinq municipalités bénéficiaires. | U69: Atlantique, Zou, Plateau, Collines | V69: Ouidah, Bohicon, Pobè, Sakété, Dassa-Zoumé | Z69: 41466 | AA69: 41634 | AD69: 43465 | AL69: UC | AN69: 5833956921 | AR69: 0 | AS69: 5833956921 | BA69: Banque d’Investissement et de Développement de la CEDEAO | BB69: BIDC | BC69: MULTILATERAUX | DF69: ATLANTIQUE (OUIDAH) ; ZOU (BOHICON) ; PLATEAU (POBÈ, SAKÉTÉ) ; COLLINES (DASSA-ZOUMÉ). | DG69: Projet d'investissement | DH69: Prêt | DI69: Prêt non concessionnel | DJ69: evaluation.gouv.bj | DK69: 7742900
A70: P-0062-BIDC-2014 | B70: Projet de réhabilitation et de renforcement de la route Parakou-Djougou | F70: INFRASTRUCTURES ROUTIERES ET TRANSPORT | N70: Financer les couches de roulement en béton bitumineux pour garantir la pérennité structurelle de la chaussée reliant le Borgou à la Donga. | U70: Borgou, Donga | V70: Parakou, Djougou | Z70: 41831 | AA70: 41978 | AD70: 43100 | AL70: UC | AN70: 4000000000 | AR70: 0 | AS70: 4000000000 | BA70: Banque d’Investissement et de Développement de la CEDEAO | BB70: BIDC | BC70: MULTILATERAUX | DF70: BORGOU (PARAKOU) ; DONGA (DJOUGOU). | DG70: Projet d'investissement | DH70: Prêt | DI70: Prêt non concessionnel | DJ70: evaluation.gouv.bj | DK70: 5000000
A71: P-0065-BAD-2014 | B71: Projet d'appui aux infrastructures agricoles dans la vallée de l'Ouémé (PAIA-VO) | F71: AGRICULTURE | N71: Améliorer la productivité et la production rizicoles et maraîchères de la vallée par l'aménagement de périmètres irrigués sous maîtrise d'eau et de pistes rurales connexes. ; Financer des infrastructures collectives de commercialisation, de stockage et d'équipements de transformation agroalimentaire gérées par les coopératives locales. | U71: Ouémé, Atlantique | V71: Adjohoun, Bonou, Dangbo, Agégué, Zè | Z71: 41648 | AA71: 41716 | AD71: 44561 | AL71: UC | AN71: 30251000000 | AR71: 401000000 | AS71: 29850000000 | BA71: Banque Africaine de Développement | BB71: BAD | BC71: MULTILATERAUX | DF71: OUÉMÉ (ADJOHOUN, BONOU, DANGBO, AGÉGUÉ) ; ATLANTIQUE (ZÈ). | DG71: Projet d'investissement | DH71: Don | Prêt | DI71: Don | Prêt concessionnel | DJ71: documentation-anbenin.org | DK71: 40030000
A72: P-0065-FEM / GEF-2014 | B72: Projet d'appui aux infrastructures agricoles dans la vallée de l'Ouémé (PAIA-VO) | F72: AGRICULTURE | N72: Promouvoir des pratiques de gestion durable des terres, d'adaptation climatique et de résilience des systèmes agricoles basés sur les zones humides de la vallée. | U72: Ouémé, Atlantique | V72: Adjohoun, Bonou, Dangbo, Agégué, Zè | Z72: 41716 | AA72: 41929 | AD72: 44561 | AL72: UC | AN72: 3600000000 | AR72: 3600000000 | AS72: 0 | BA72: Fonds pour l’Environnement Mondial | BB72: FEM / GEF | BC72: MULTILATERAUX | DF72: OUÉMÉ (ADJOHOUN, BONOU, DANGBO, AGÉGUÉ) ; ATLANTIQUE (ZÈ). | DG72: Projet d'investissement | DH72: Don | DI72: Fonds fiduciaire (Trust Fund) | DJ72: banquemondiale.org | DK72: 4800000
A73: P-0066-BM-2014 | B73: Projet multisectoriel de l'alimentation, de la santé et de la nutrition | F73: SANTÉ | N73: Améliorer les pratiques de nutrition communautaire et accroître l'utilisation des services de santé et d'alimentation essentiels dans les communes rurales vulnérables. | U73: National | Z73: 41681 | AA73: 41992 | AD73: 43830 | AL73: DTS | AN73: 14000000000 | AR73: 0 | AS73: 14000000000 | BA73: Banque mondiale | BB73: BM | BC73: MULTILATERAUX | DF73: NATIONAL | DG73: Projet d'investissement | DH73: Prêt | DI73: Prêt concessionnel | DJ73: banquemondiale.org | DK73: 18300000
A74: P-0067-BM-2014 | B74: Projet de Partenariat Mondial pour l'Education (PPME) | F74: ÉDUCATION | N74: Améliorer l'accès équitable à l'enseignement de base, accroître la rétention scolaire des filles et renforcer la qualité des apprentissages dans les zones d'apprentissage défavorisées. | U74: National | Z74: 41708 | AA74: 41719 | AD74: 43434 | AL74: EUR | AN74: 21150000000 | AR74: 21150000000 | AS74: 0 | BA74: Banque mondiale | BB74: BM | BC74: MULTILATERAUX | DF74: NATIONAL | DG74: Projet d'investissement | DH74: Don | DI74: Don | DJ74: banquemondiale.org | DK74: 42300000
A75: P-0068-BOAD-2014 | B75: Projet de transport urbain à Parakou : Reconstruction de la traversée et du contournement de la ville | F75: INFRASTRUCTURES ROUTIERES ET TRANSPORT | N75: Améliorer la fluidité du trafic et la sécurité des transports urbains au sein de la ville de Parakou par l'aménagement de voies de contournement en double voie. | U75: Borgou | V75: Parakou | Z75: 41722 | AA75: 41729 | AD75: 43830 | AL75: XOF | AN75: 10000000000 | AR75: 0 | AS75: 10000000000 | BA75: Banque Ouest Africaine de Développement | BB75: BOAD | BC75: MULTILATERAUX | DF75: BORGOU (PARAKOU). | DG75: Projet d'investissement | DH75: Prêt | DI75: Prêt non concessionnel | DJ75: boad.org | DK75: 10000000000
A76: P-0069-BOAD-2014 | B76: Projet d'aménagement et de bitumage de routes structurantes : (i) Comé – Lokossa – Dogbo et Bretelle Zounhouè - Athiémé – frontière du Togo (71 km), (ii) Savalou – Tchetti – frontière du Togo (42 km) et Bretelle Logozohè – Glazoué (17 km) et (iii) Djèrègbè – Dja - Owodé Frontière du Nigéria (9,67 km) | F76: INFRASTRUCTURES ROUTIERES ET TRANSPORT | N76: Assurer le bitumage de trois axes routiers hautement stratégiques pour interconnecter les pôles de développement internes aux pays voisins (Togo et Nigeria). | U76: Mono, Couffo, Collines, Ouémé, Plateau | V76: Comè, Lokossa, Athiémé, Dogbo, Savalou, Glazoué, Sèmè-Podji, Ifangni | Z76: 41729 | AA76: 41989 | AD76: 44196 | AL76: XOF | AN76: 25000000000 | AR76: 0 | AS76: 25000000000 | BA76: Banque Ouest Africaine de Développement | BB76: BOAD | BC76: MULTILATERAUX | DF76: MONO (COMÈ, LOKOSSA, ATHIÉMÉ) ; COUFFO (DOGBO) ; COLLINES (SAVALOU, GLAZOUÉ) ; OUÉMÉ (SÈMÈ-PODJI) ; PLATEAU (IFANGNI). | DG76: Projet d'investissement | DH76: Prêt | DI76: Prêt non concessionnel | DJ76: boad.org | DK76: 25000000000
A77: P-0070-BM-2014 | B77: Financement additionnel du projet de Services Décentralisés Conduits par les Communautés | F77: DÉCENTRALISATION | N77: Amplifier le programme de transferts monétaires directs aux ménages extrêmement pauvres et accroître la couverture des infrastructures communautaires villageoises de base. | U77: National | Z77: 41739 | AA77: 41936 | AD77: 43281 | AL77: EUR | AN77: 15000000000 | AR77: 0 | AS77: 15000000000 | BA77: Banque mondiale | BB77: BM | BC77: MULTILATERAUX | DF77: NATIONAL | DG77: Projet d'investissement | DH77: Prêt | DI77: Prêt concessionnel | DJ77: banquemondiale.org | DK77: 30000000
A78: P-0071-BM-2014 | B78: Projet Emploi des Jeunes | F78: PROTECTION SOCIALE ET EMPLOI | N78: Améliorer l'accès des jeunes sous-employés ou peu qualifiés à des opportunités d'emploi à travers des formations techniques de courte durée et l'octroi d'appuis financiers à l'auto-emploi. | U78: National | Z78: 41709 | AA78: 41739 | AD78: 44012 | AL78: EUR | AN78: 17500000000 | AR78: 0 | AS78: 17500000000 | BA78: Banque mondiale | BB78: BM | BC78: MULTILATERAUX | DF78: NATIONAL | DG78: Projet d'investissement | DH78: Prêt | DI78: Prêt concessionnel | DJ78: banquemondiale.org | DK78: 35000000
A79: P-0072-BM-2014 | B79: Neuvième Crédit d'Appui à la Stratégie de Réduction de la Pauvreté (PRSC-9) | F79: GOUVERNANCE | N79: Soutenir la consolidation de la gouvernance économique nationale en finançant la mise en œuvre de réformes clés pour l'efficience des dépenses de santé et d'éducation. | U79: National | Z79: 41739 | AA79: 41956 | AD79: 42369 | AL79: EUR | AN79: 10000000000 | AR79: 0 | AS79: 10000000000 | BA79: Banque mondiale | BB79: BM | BC79: MULTILATERAUX | DF79: NATIONAL | DG79: Projet d'investissement | DH79: Prêt | DI79: Prêt concessionnel | DJ79: banquemondiale.org | DK79: 20000000
A80: P-0073-BADEA-2014 | B80: Projet de construction et d'équipement de l'école normale supérieure de l'enseignement technique de Lokossa | F80: ÉDUCATION | N80: Améliorer la formation des enseignants de l'enseignement technique au Bénin en érigeant et dotant de laboratoires spécialisés l'infrastructure académique de l'ENSET à Lokossa. | U80: Mono | V80: Lokossa | Z80: 41751 | AA80: 41773 | AD80: 43830 | AL80: EUR | AN80: 4000000000 | AR80: 0 | AS80: 4000000000 | BA80: Banque Arabe pour le Développement Économique en Afrique | BB80: BADEA | BC80: MULTILATERAUX | DF80: MONO (LOKOSSA). | DG80: Projet d'investissement | DH80: Prêt | DI80: Prêt concessionnel | DJ80: documentation-anbenin.org | DK80: 8000000
A81: P-0074-AFD-2014 | B81: Programme d'appui à la formation professionnelle et à l'insertion des jeunes (AFPIJe) | F81: PROTECTION SOCIALE ET EMPLOI | N81: Développer l'offre de formation par alternance et apprentissage de type dual pour adapter les qualifications professionnelles des jeunes aux besoins réels des entreprises privées et artisanales. | U81: National | Z81: 41765 | AA81: 41814 | AD81: 43830 | AL81: EUR | AN81: 2623828000 | AR81: 2623828000 | AS81: 0 | BA81: Agence Française de Développement | BB81: AFD | BC81: BILATERAUX | DF81: NATIONAL | DG81: Programme d'investissement | DH81: Don | DI81: Don | DJ81: evaluation.gouv.bj | DK81: 4000000
A82: P-0075-BID-2014 | B82: Financement additionnel du projet d'appui au développement du système de santé | F82: SANTÉ | N82: Étendre les services de santé de base de qualité et renforcer la surveillance épidémiologique dans les zones frontalières des départements septentrionaux. | U82: Atacora, Donga, Borgou, Alibori | Z82: 41713 | AA82: 41768 | AD82: 43465 | AL82: DI | AN82: 3675000000 | AR82: 0 | AS82: 3675000000 | BA82: Banque Islamique de Développement | BB82: BID | BC82: MULTILATERAUX | DF82: ATACORA ; DONGA ; BORGOU ; ALIBORI. | DG82: Projet d'investissement | DH82: Prêt | DI82: Prêt concessionnel | DJ82: documentation-anbenin.org | DK82: 4830000
A83: P-0076-BM-2014 | B83: Projet de centres d'excellence d'enseignement supérieur en Afrique | F83: ÉDUCATION | N83: Appuyer l'émergence de pôles d'excellence académique régionaux à l'Université d'Abomey-Calavi dans les filières de sciences mathématiques et d'ingénierie appliquée. | U83: Atlantique | V83: Abomey-Calavi | Z83: 41744 | AA83: 41779 | AD83: 43830 | AL83: EUR | AN83: 4000000000 | AR83: 0 | AS83: 4000000000 | BA83: Banque mondiale | BB83: BM | BC83: MULTILATERAUX | DF83: ATLANTIQUE (ABOMEY-CALAVI). | DG83: Projet d'investissement | DH83: Prêt | DI83: Prêt concessionnel | DJ83: banquemondiale.org | DK83: 8000000
A84: P-0077-BM-2014 | B84: Financement additionnel du projet d'Urgence de Gestion Environnementale en Milieu Urbain | F84: CADRE DE VIE | N84: Financer des travaux complémentaires d'urgence pour la sécurisation de collecteurs pluviaux majeurs et l'éradication de points noirs d'inondations dans l'agglomération de Cotonou. | U84: Littoral, Atlantique, Ouémé | V84: Cotonou, Abomey-Calavi, Ouidah, Porto-Novo, Sèmè-Podji | W84: Du 1er au 13ème, Godomey, Abomey-Calavi Centre, Akassato, Du 1er au 5ème | Z84: 41739 | AA84: 41795 | AD84: 42735 | AL84: EUR | AN84: 4000000000 | AR84: 0 | AS84: 4000000000 | BA84: Banque mondiale | BB84: BM | BC84: MULTILATERAUX | DF84: LITTORAL (COTONOU(DU 1ER AU 13ÈME)) ; ATLANTIQUE (ABOMEY-CALAVI(GODOMEY, ABOMEY-CALAVI CENTRE, AKASSATO), OUIDAH) ; OUÉMÉ (PORTO-NOVO(DU 1ER AU 5ÈME), SÈMÈ-PODJI). | DG84: Projet d'investissement | DH84: Prêt | DI84: Prêt concessionnel | DJ84: evaluation.gouv.bj | DK84: 9000000
A85: P-0078-BID-2014 | B85: Projet de Développement de l'Education de Base-Phase IV | F85: ÉDUCATION | N85: Accroître la capacité d'accueil et la mixité du système scolaire par la construction d'infrastructures de collèges ruraux intégrés équipés de blocs sanitaires adaptés. ; Acquérir et distribuer des manuels scolaires et des guides didactiques et renforcer la formation pédagogique continue des instituteurs et enseignants contractuels. | U85: National | Z85: 41800 | AA85: 41802 | AD85: 44012 | AL85: DI | EUR | AN85: 6080000000 | AR85: 0 | AS85: 6080000000 | BA85: Banque Islamique de Développement | BB85: BID | BC85: MULTILATERAUX | DF85: NATIONAL | DG85: Projet d'investissement | DH85: Prêt | DI85: Istisna'a | DJ85: documentation-anbenin.org | DK85: 9670000
A86: P-0079-BID-2014 | B86: Projet BID-UEMOA d'hydraulique et d'assainissement en milieu rural | F86: EAU ET ASSAINISSEMENT | I86: ACCÈS À L’EAU POTABLE | N86: Approvisionner durablement en eau potable les localités rurales cibles des départements du Bénin à travers la réalisation de forages équipés de pompes manuelles ou solaires. | U86: Atacora, Donga, Borgou, Alibori, Zou, Collines | Z86: 41690 | AA86: 41816 | AD86: 43465 | AL86: EUR | AN86: 6250000000 | AR86: 0 | AS86: 6250000000 | AY86: APD | AZ86: PRÊT | BA86: Banque Islamique de Développement | BB86: BID | BC86: MULTILATERAUX | BK86: en cours | BM86: PILIER 3 | BN86: AXE 6 | BO86: ODD 6 | BP86: 6.1 | BQ86: Environnemental | DF86: ATACORA ; DONGA ; BORGOU ; ALIBORI ; ZOU ; COLLINES. | DG86: Projet d'investissement | DH86: Prêt | DI86: Istisna'a | DJ86: documentation-anbenin.org | DK86: 12500000
A87: P-0080-UEMOA-2014 | B87: Bonification du taux d'intérêt du prêt relatif au financement partiel du Projet de renforcement du système d'alimentation en eau potable dans 69 villages | F87: EAU ET ASSAINISSEMENT | N87: Réduire le coût financier global de la dette contractée pour les infrastructures d'adduction d'eau villageoise au profit de la viabilité budgétaire du programme. | U87: National | Z87: 41774 | AA87: 41815 | AD87: 43465 | AL87: XOF | AN87: 1124584425 | AR87: 1124584425 | AS87: 0 | BA87: Union Économique et Monétaire Ouest Africaine | BB87: UEMOA | BC87: MULTILATERAUX | DF87: NATIONAL | DG87: Projet d'investissement | DH87: Don | DI87: Don | DJ87: documentation-anbenin.org | DK87: 1124584425
A88: P-0081-AFD-2014 | B88: Projet d'appui au renforcement des acteurs du secteur privé | F88: PROTECTION SOCIALE ET EMPLOI | N88: Mettre en œuvre des programmes d'appui à la mise à niveau des entreprises industrielles locales et faciliter leur accès aux financements de trésorerie et d'investissement. | U88: National | Z88: 41856 | AA88: 41922 | AD88: 43465 | AL88: EUR | AN88: 682195280 | AR88: 682195280 | AS88: 0 | BA88: Agence Française de Développement | BB88: AFD | BC88: BILATERAUX | DF88: NATIONAL | DG88: Projet d'investissement | DH88: Don | DI88: Don | DJ88: evaluation.gouv.bj | DK88: 1040090.4
A89: P-0081-UE-2014 | B89: Projet d'appui au renforcement des acteurs du secteur privé | F89: PROTECTION SOCIALE ET EMPLOI | N89: Améliorer la compétitivité des micro, petites et moyennes entreprises en renforçant l'offre de services d'appui-conseil de la Chambre de Commerce et d'Industrie du Bénin. | U89: National | Z89: 41856 | AA89: 41922 | AD89: 43465 | AL89: EUR | AN89: 5885221934 | AR89: 5885221934 | AS89: 0 | BA89: Union Européenne | BB89: UE | BC89: MULTILATERAUX | DF89: NATIONAL | DG89: Projet d'investissement | DH89: Don | DI89: Don | DJ89: evaluation.gouv.bj | DK89: 8972742.7
A90: P-0082-BOA-BENIN-2014 | B90: Projet d'aménagement et de bitumage de la route Djèrègbè – Dja - Owodé Frontière du Nigéria (9,67 km) | F90: INFRASTRUCTURES ROUTIERES ET TRANSPORT | N90: Apporter le concours financier complémentaire requis pour le bitumage et la signalisation sécurisée de l'axe frontalier commercial de Dja. | U90: Ouémé, Plateau | V90: Sèmè-Podji, Ifangni | Z90: 41801 | AA90: 41878 | AD90: 43100 | AL90: XOF | AN90: 9000000000 | AR90: 0 | AS90: 9000000000 | BA90: Bank of Africa – Bénin | BB90: BOA-BENIN | BC90: PRIVE | DF90: OUÉMÉ (SÈMÈ-PODJI) ; PLATEAU (IFANGNI). | DG90: Projet d'investissement | DH90: Prêt | DI90: Prêt commercial | DJ90: documentation-anbenin.org | DK90: 9000000000
A91: P-0082-ECOBANK-Bénin-2014 | B91: Projet d'aménagement et de bitumage de la route Djèrègbè – Dja - Owodé Frontière du Nigéria (9,67 km) | F91: INFRASTRUCTURES ROUTIERES ET TRANSPORT | N91: Financer de façon syndiquée les travaux de voirie lourde sur cet axe routier commercial majeur reliant l'Ouémé au marché nigérian. | U91: Ouémé, Plateau | V91: Sèmè-Podji, Ifangni | Z91: 41801 | AA91: 41877 | AD91: 43100 | AL91: XOF | AN91: 2000000000 | AR91: 0 | AS91: 2000000000 | BA91: ECOBANK-Bénin | BB91: ECOBANK-Bénin | BC91: PRIVE | DF91: OUÉMÉ (SÈMÈ-PODJI) ; PLATEAU (IFANGNI). | DG91: Projet d'investissement | DH91: Prêt | DI91: Prêt commercial | DJ91: documentation-anbenin.org | DK91: 2000000000
A92: P-0083-BOAD-2014 | B92: Projet d'Appui à l'assurance Mutuelle Agricole du Bénin (AMAB) pour la mise en place d'une assurance récolte des filières coton et Riz au Bénin | F92: AGRICULTURE | N92: Sécuriser les investissements des petits exploitants agricoles face aux aléas climatiques (sécheresses, inondations) en développant des produits d'assurance récolte indicielle. ; Sécuriser les investissements des petits exploitants agricoles face aux aléas climatiques (sécheresse, inondations) en structurant et en lançant un produit d'assurance récolte indicielle. | U92: Alibori, Borgou, Atacora, Donga, Zou, Collines, Ouémé | Z92: 41722 | AA92: 41909 | AD92: 43465 | AL92: XOF | AN92: 1089000000 | AR92: 0 | AS92: 1089000000 | BA92: Banque Ouest Africaine de Développement | BB92: BOAD | BC92: MULTILATERAUX | DF92: ALIBORI ; BORGOU ; ATACORA ; DONGA ; ZOU ; COLLINES ; OUÉMÉ. | DG92: Projet d'investissement | DH92: Prêt | DI92: Prêt non concessionnel | DJ92: boad.org ; https://boad.org | DK92: 1089000000
A93: P-0084-BOAD-2014 | B93: Projet de pavage de rues et d'assainissement dans les villes d'Athiémé, d'Avrankou, d'Azovè, de Calavi (phase 2), de Kérou, de Malanville et de Zogbodomey et de Projet de construction d'un pont sur la traversée lagunaire de Djonou entre Cocotomey et Womey | F93: CADRE DE VIE | N93: Améliorer la voirie dans sept agglomérations et résoudre l'enclavement critique du quartier Womey par l'érection du pont de franchissement sur la lagune de Djonou. | U93: Mono, Ouémé, Couffo, Atlantique, Atacora, Alibori, Zou, Littoral | V93: Athiémé, Avrankou, Aplahoué, Abomey-Calavi, Kérou, Malanville, Zogbodomey, Cotonou | W93: Azovè, Womey, Abomey-Calavi Centre | Z93: 41722 | AA93: 41909 | AD93: 43830 | AL93: XOF | AN93: 20000000000 | AR93: 0 | AS93: 20000000000 | BA93: Banque Ouest Africaine de Développement | BB93: BOAD | BC93: MULTILATERAUX | DF93: MONO (ATHIÉMÉ) ; OUÉMÉ (AVRANKOU) ; COUFFO (APLAHOUÉ(AZOVÈ)) ; ATLANTIQUE (ABOMEY-CALAVI(WOMEY, ABOMEY-CALAVI CENTRE)) ; ATACORA (KÉROU) ; ALIBORI (MALANVILLE) ; ZOU (ZOGBODOMEY) ; LITTORAL (COTONOU). | DG93: Projet d'investissement | DH93: Prêt | DI93: Prêt non concessionnel | DJ93: boad.org | DK93: 20000000000
A94: P-0085-BADEA-2014 | B94: Etudes environnementale et sociale du Projet de protection de la côte ouest de la ville de Cotonou (littoral Hillacondji-Grand-Popo) | F94: CADRE DE VIE | N94: Réaliser les analyses d'impact et d'ingénierie côtière requises pour concevoir des ouvrages de stabilisation du trait de côte face à l'avancée de la mer sur le littoral ouest. | U94: Mono, Littoral | V94: Grand-Popo, Cotonou | W94: Hillacondji | Z94: 41773 | AA94: 41911 | AD94: 42369 | AL94: EUR | AN94: 225000000 | AR94: 0 | AS94: 225000000 | BA94: Banque Arabe pour le Développement Économique en Afrique | BB94: BADEA | BC94: MULTILATERAUX | DF94: MONO (GRAND-POPO(HILLACONDJI)) ; LITTORAL (COTONOU). | DG94: Projet d'investissement | DH94: Prêt | DI94: Prêt concessionnel | DJ94: documentation-anbenin.org | DK94: 450000
A95: P-0086-BADEA-2014 | B95: Financement additionnel du projet de protection de la côte à l'Est de la ville de Cotonou | F95: CADRE DE VIE | N95: Participer au financement de la construction d'un système d'épis rocheux et de rechargement en sable pour stabiliser la plage Est de Cotonou contre l'érosion marine accélérée. | U95: Littoral, Ouémé | V95: Cotonou, Sèmè-Podji | Z95: 41922 | AA95: 41963 | AD95: 43830 | AL95: EUR | AN95: 1000000000 | AR95: 0 | AS95: 1000000000 | BA95: Banque Arabe pour le Développement Économique en Afrique | BB95: BADEA | BC95: MULTILATERAUX | DF95: LITTORAL (COTONOU) ; OUÉMÉ (SÈMÈ-PODJI). | DG95: Projet d'investissement | DH95: Prêt | DI95: Prêt concessionnel | DJ95: documentation-anbenin.org | DK95: 2000000
A96: P-0086-FKDEA-2014 | B96: Financement additionnel du projet de protection de la côte à l'Est de la ville de Cotonou | F96: CADRE DE VIE | N96: Cofinancer les travaux de génie civil côtier lourds pour protéger les infrastructures portuaires et les zones habitées de la bande littorale Est de Cotonou. | U96: Littoral, Ouémé | V96: Cotonou, Sèmè-Podji | Z96: 41922 | AA96: 41963 | AD96: 43830 | AL96: KWD | AN96: 5000000000 | AR96: 0 | AS96: 5000000000 | BA96: Fonds Koweïtien pour le Développement Économique Arabe | BB96: FKDEA | BC96: BILATERAUX | DF96: LITTORAL (COTONOU) ; OUÉMÉ (SÈMÈ-PODJI). | DG96: Projet d'investissement | DH96: Prêt | DI96: Prêt concessionnel | DJ96: documentation-anbenin.org | DK96: 3000000
A97: P-0086-OPEP-2014 | B97: Financement additionnel du projet de protection de la côte à l'Est de la ville de Cotonou | F97: CADRE DE VIE | N97: Apporter les ressources budgétaires complémentaires pour étendre la couverture de la protection côtière par épis rocheux vers le secteur de Sèmè-Podji. | U97: Littoral, Ouémé | V97: Cotonou, Sèmè-Podji | Z97: 41922 | AA97: 41963 | AD97: 43830 | AL97: EUR | AN97: 1500000000 | AR97: 0 | AS97: 1500000000 | BA97: OPEP | BB97: OFID/OPEP | BC97: MULTILATERAUX | DF97: LITTORAL (COTONOU) ; OUÉMÉ (SÈMÈ-PODJI). | DG97: Projet d'investissement | DH97: Prêt | DI97: Prêt concessionnel | DJ97: documentation-anbenin.org | DK97: 3000000
A98: P-0087-BAD-2014 | B98: Projet de transport urbain à Parakou : Reconstruction de la traversée et du contournement de la ville en République du Bénin | F98: INFRASTRUCTURES ROUTIERES ET TRANSPORT | N98: Financer les travaux d'infrastructures lourdes de dédoublement de la chaussée urbaine centrale et d'aménagement de voies cyclables et piétonnes à Parakou. | U98: Borgou | V98: Parakou | Z98: 41929 | AA98: 41991 | AD98: 44561 | AL98: UC | AN98: 17468176600 | AR98: 0 | AS98: 17468176600 | BA98: Banque Africaine de Développement | BB98: BAD | BC98: MULTILATERAUX | DF98: BORGOU (PARAKOU). | DG98: Projet d'investissement | DH98: Prêt | DI98: Prêt concessionnel | DJ98: documentation-anbenin.org | DK98: 23800000
A99: P-0087-FAD/FEM-2014 | B99: Projet de transport urbain à Parakou : Reconstruction de la traversée et du contournement de la ville en République du Bénin | F99: INFRASTRUCTURES ROUTIERES ET TRANSPORT | N99: Réduire les émissions de gaz à effet de serre du transport urbain à Parakou en favorisant la fluidité du trafic par des aménagements d'espaces verts et d'intersections optimisées. | U99: Borgou | V99: Parakou | Z99: 41929 | AA99: 41991 | AD99: 44561 | AL99: EUR | AN99: 930787000 | AR99: 930787000 | AS99: 0 | BA99: Fonds Africain de Développement – financement associé au Fonds pour l’Environnement Mondial | BB99: FAD/FEM | BC99: MULTILATERAUX | DF99: BORGOU (PARAKOU). | DG99: Projet d'investissement | DH99: Don | DI99: Fonds fiduciaire (Trust Fund) | DJ99: documentation-anbenin.org | DK99: 1861574
A100: P-0088-BAD-2014 | B100: Aide d'urgence à Malanville et à Karimanan | F100: PROTECTION SOCIALE ET EMPLOI | N100: Fournir une assistance d'urgence humanitaire et de réhabilitation rapide des infrastructures d'eau et de santé dégradées à la suite des inondations catastrophiques du fleuve Niger. | U100: Alibori | V100: Malanville, Karimama | Z100: 41922 | AA100: 41929 | AD100: 42369 | AL100: USD | AN100: 400000000 | AR100: 400000000 | AS100: 0 | BA100: Banque Africaine de Développement | BB100: BAD | BC100: MULTILATERAUX | DF100: ALIBORI (MALANVILLE, KARIMAMA). | DG100: Aide humanitaire | DH100: Don | DI100: Don | DJ100: evaluation.gouv.bj | DK100: 609849.06
...

Sheet Localisation
A1: N° | B1: Département | C1: Commune | D1: Arrondissement | E1: Village ou quartier de Ville
A2: 1 | B2: ALIBORI | C2: KANDI | D2: ANGARADEBOU | E2: 1. Akoïtchaou
A3: 2 | B3: ALIBORI | C3: KANDI | D3: ANGARADEBOU | E3: 2. Alfakoara
A4: 3 | B4: ALIBORI | C4: KANDI | D4: ANGARADEBOU | E4: 3. Angaradébou
A5: 4 | B5: ALIBORI | C5: KANDI | D5: ANGARADEBOU | E5: 4. Dogban
A6: 5 | B6: ALIBORI | C6: KANDI | D6: ANGARADEBOU | E6: 5. Fafa
A7: 6 | B7: ALIBORI | C7: KANDI | D7: ANGARADEBOU | E7: 6. Fouet
A8: 7 | B8: ALIBORI | C8: KANDI | D8: ANGARADEBOU | E8: 7. Kabagbèdè
A9: 8 | B9: ALIBORI | C9: KANDI | D9: ANGARADEBOU | E9: 8. Kpalolo
A10: 9 | B10: ALIBORI | C10: KANDI | D10: ANGARADEBOU | E10: 9. Sékalé
A11: 10 | B11: ALIBORI | C11: KANDI | D11: ANGARADEBOU | E11: 10. Sondo
A12: 11 | B12: ALIBORI | C12: KANDI | D12: ANGARADEBOU | E12: 11. Soundou
A13: 12 | B13: ALIBORI | C13: KANDI | D13: ANGARADEBOU | E13: 12. Tchoka
... A5291: 5320 | B5291: ZOU | C5291: ZOGBODOMEY | D5291: ZOUKOU | E5291: 6. Zoukou

Sheet Paramètres
A1: SECTEUR | B1: SOUS_SECTEUR | C1: PARTENAIRE | D1: TYPE_FINANC | E1: TYPE_PARTEN | F1: SECTEUR_PAG | G1: PILIER_PAG | H1: AXE_PAG | I1: STATUT_PROJET | J1: DEPARTEMENTS | K1: basePart | L1: type_engagem | M1: annee | N1: trimestre | O1: ODD | P1: COMMUNES | Q1: DEVISE | R1: MODALITE_INTERV | S1: NATURE_FINANC
A2: ÉNERGIE | B2: Production d’électricité | C2: AFD | D2: Don | E2: Bilatéral | F2: Transformation économique | G2: PILIER 1 | H2: AXE 1 | I2: En approbation | J2: Alibori | K2: MAEP | L2: Projet d'investissement | M2: 2011 | N2: trim1 | O2: ODD 1 | P2: Cotonou | Q2: XOF - Franc CFA BCEAO | R2: Aide humanitaire | S2: Don
A3: ÉNERGIE | B3: Transport d’énergie | C3: ALLEMAGNE | D3: Prêt concessionnel | E3: Multilatéral | F3: Capital humain | G3: PILIER 2 | H3: AXE 2 | I3: En cours | J3: Atacora | K3: MS | L3: Programme sectoriel | M3: 2012 | N3: trim2 | O3: ODD 2 | P3: Porto-Novo | Q3: EUR - Euro | R3: Appui budgétaire général | S3: Prêt
A4: ÉNERGIE | B4: Distribution d’électricité | C4: BAD | D4: Prêt non-concessionnel | E4: Fonds fiduciaire | F4: Gouvernance | G4: PILIER 3 | H4: AXE 3 | I4: Achevé | J4: Atlantique | K4: MENFP | L4: Appui budgétaire général | M4: 2013 | N4: trim3 | O4: ODD 3 | P4: Parakou | Q4: USD - Dollar américain | R4: Appui budgétaire sectoriel | S4: Don | Prêt
A5: ÉNERGIE | B5: Électrification rurale | C5: BADEA | D5: PPP | E5: ONG internationale | F5: Croissance inclusive | H5: AXE 4 | I5: En retard | J5: Borgou | K5: MEF | L5: Assistance technique | M5: 2014 | N5: trim4 | O5: ODD 4 | P5: Abomey-Calavi | Q5: GBP - Livre sterling | R5: Assistance technique / Renforcement institutionnel
A6: ÉNERGIE | B6: Électrification urbaine | C6: BANQUE ATLANTIQUE BENIN | D6: Subvention | E6: Agence spécialisée | F6: Infrastructures | H6: AXE 5 | I6: Abandonné | J6: Collines | K6: DGFD | L6: Étude / Préparation | M6: 2015 | O6: ODD 5 | P6: Bohicon | Q6: CAD - Dollar canadien | R6: Fonds commun
A7: ÉNERGIE | B7: Énergies renouvelables | C7: BCI | D7: Garantie souveraine | E7: Institution financière | F7: Numérique | H7: AXE 6 | I7: Suspendu | J7: Couffo | K7: MTP | L7: Appui budgétaire ciblé | M7: 2016 | O7: ODD 6 | P7: Natitingou | Q7: CHF - Franc suisse | R7: Gestion de la dette
A8: ÉNERGIE | B8: Énergie solaire | C8: BEI | D8: Appui budgétaire | E8: Secteur privé | F8: Environnement | H8: AXE 7 | J8: Donga | K8: MCVDD | M8: 2017 | O8: ODD 7 | P8: Lokossa | Q8: CNY - Yuan chinois | R8: Ligne de crédit
A9: ÉNERGIE | B9: Biomasse et biogaz | C9: BELGIQUE | D9: Co-financement | E9: Marché financier | J9: Littoral | K9: MERS | M9: 2018 | O9: ODD 8 | P9: Ouidah | Q9: JPY - Yen japonais | R9: PforR
A10: ÉNERGIE | B10: Efficacité énergétique | C10: BGFI | D10: Emprunt obligataire | J10: Mono | K10: MDN | M10: 2019 | O10: ODD 9 | P10: Djougou | Q10: NGN - Naira nigérian | R10: Programme d'investissement
A11: ÉNERGIE | B11: Éclairage public | C11: BID | J11: Ouémé | K11: MISP | M11: 2020 | O11: ODD 10 | P11: Kandi | Q11: GHS - Cedi ghanéen | R11: Projet d'investissement
A12: ÉNERGIE | B12: Mines | C12: BIDC | J12: Plateau | K12: MTCA | M12: 2021 | O12: ODD 11 | P12: Abomey | Q12: ZAR - Rand sud-africain | R12: Étude / Préparation
A13: AGRICULTURE | B13: Production végétale | C13: BM | J13: Zou | K13: MEN | M13: 2022 | O13: ODD 12 | P13: Dogbo | Q13: AUD - Dollar australien
A14: AGRICULTURE | B14: Riziculture | C14: BNP-PARIBAS | K14: MSP | M14: 2023 | O14: ODD 13 | P14: Dassa-Zoumè | Q14: NZD - Dollar néo-zélandais
A15: AGRICULTURE | B15: Maraîchage | C15: BOA-BENIN | K15: MJLDH | M15: 2024 | O15: ODD 14 | P15: Savalou | Q15: SEK - Couronne suédoise
A16: AGRICULTURE | B16: Cultures de rente | C16: BOAD | K16: MERPMEDER | M16: 2025 | O16: ODD 15 | P16: Bassila | Q16: NOK - Couronne norvégienne
A17: AGRICULTURE | B17: Irrigation et maîtrise de l’eau | C17: BRESIL | K17: Présidence | M17: 2026 | O17: ODD 17 | P17: Malanville | Q17: AED - Dirham des Émirats arabes unis
A18: AGRICULTURE | B18: Mécanisation agricole | C18: CANADA | K18: Autre | M18: 2027 | P18: Nikki | Q18: SAR - Riyal saoudien
A19: AGRICULTURE | B19: Stockage et conservation | C19: CHINE | M19: 2028 | P19: Tchaourou | Q19: QAR - Riyal qatari
A20: AGRICULTURE | B20: Transformation agroalimentaire | C20: COOPÉRATION SUISSE | M20: 2029 | P20: Pobè | Q20: KWD - Dinar koweïtien
A21: AGRICULTURE | B21: Recherche et innovation agricoles | C21: DEUTSCHE BANK | M21: 2030 | P21: Sakété | Q21: BHD - Dinar bahreïni
A22: AGRICULTURE | B22: Conseil agricole | C22: DIAMOND BANK | M22: 2031 | P22: Adjohoun | Q22: OMR - Rial omanais
A23: AGRICULTURE | B23: Élevage | C23: EUROBOND | M23: 2032 | P23: Avrankou | Q23: INR - Roupie indienne
A24: AGRICULTURE | B24: Pêche et aquaculture | C24: EUROBOND_21 | M24: 2033 | P24: Dangbo | Q24: KRW - Won sud-coréen
A25: AGRICULTURE | B25: Sécurité alimentaire | C25: FIDA | M25: 2034 | P25: Akpro-Missérété | Q25: SGD - Dollar de Singapour
A26: CADRE DE VIE | B26: Urbanisme | C26: FKDEA | M26: 2035 | P26: Sèmè-Kpodji | Q26: HKD - Dollar de Hong Kong
A27: CADRE DE VIE | B27: Aménagement urbain | C27: FMI | M27: 2036 | P27: Aguégués | Q27: TRY - Livre turque
A28: CADRE DE VIE | B28: Habitat et logements sociaux | C28: FND | P28: Sotouboua | Q28: RUB - Rouble russe
A29: CADRE DE VIE | B29: Voirie urbaine | C29: FONROCHE | P29: Glazoué | Q29: MAD - Dirham marocain
A30: CADRE DE VIE | B30: Assainissement pluvial | C30: FSD | P30: Savé | Q30: TND - Dinar tunisien
A31: CADRE DE VIE | B31: Gestion des déchets solides | C31: JAPON | P31: Bantè | Q31: DZD - Dinar algérien
A32: CADRE DE VIE | B32: Espaces verts et embellissement | C32: KBC ET RABOBANK | P32: Ouèssè | Q32: EGP - Livre égyptienne
A33: CADRE DE VIE | B33: Gestion des marchés et équipements urbains | C33: KFW | P33: Zagnanado | Q33: XAF - Franc CFA BEAC
A34: CADRE DE VIE | B34: Environnement et changements climatiques | C34: LUXDEV | P34: Zangnanado
A35: CADRE DE VIE | B35: Gestion des ressources naturelles | C35: LUXEMBOURG | P35: Covè
A36: CADRE DE VIE | B36: Lutte contre les inondations | C36: Marché financier | P36: Djidja
A37: CADRE DE VIE | B37: Lutte contre l’érosion côtière | C37: Mfin | P37: Zogbodomey
A38: CULTURE ET TOURISME | B38: Patrimoine culturel | C38: NATIXIS | P38: Lalo
A39: CULTURE ET TOURISME | B39: Musées et sites historiques | C39: NORVEGE | P39: Aplahoué
A40: CULTURE ET TOURISME | B40: Arts et spectacles | C40: ODDO-BHF | P40: Djakotomey
A41: CULTURE ET TOURISME | B41: Industries culturelles et créatives | C41: OFID/OPEP | P41: Klouékanmè
A42: CULTURE ET TOURISME | B42: Festivals et événements culturels | C42: PAYS-BAS | P42: Toviklin
A43: CULTURE ET TOURISME | B43: Aménagement de sites touristiques | C43: SNU | P43: Athiémé
A44: CULTURE ET TOURISME | B44: Écotourisme | C44: TURQUIE | P44: Bopa
A45: CULTURE ET TOURISME | B45: Tourisme balnéaire | C45: UE | P45: Grand-Popo
... A48: CULTURE ET TOURISME | B48: Formation aux métiers du tourisme | C48: Autre | P48: Toffo
A49: DÉCENTRALISATION | B49: Appui aux communes | P49: Allada
A50: DÉCENTRALISATION | B50: Gouvernance locale | P50: Kpomassè
A51: DÉCENTRALISATION | B51: Planification locale | P51: Tori-Bossito
A52: DÉCENTRALISATION | B52: Développement territorial | P52: Zê
A53: DÉCENTRALISATION | B53: Participation citoyenne | P53: Sô-Ava
A54: DÉCENTRALISATION | B54: Fiscalité locale | P54: Kétou
A55: DÉCENTRALISATION | B55: Renforcement des capacités des collectivités | P55: Adja-Ouèrè
A56: DÉCENTRALISATION | B56: Intercommunalité | P56: Ifangni
A57: DÉCENTRALISATION | B57: Gestion des services publics locaux | P57: Autre
A58: DÉVELOPPEMENT SOCIAL | B58: Développement communautaire
A59: DÉVELOPPEMENT SOCIAL | B59: Inclusion sociale
A60: DÉVELOPPEMENT SOCIAL | B60: Promotion de la femme
A61: DÉVELOPPEMENT SOCIAL | B61: Développement de la famille
A62: DÉVELOPPEMENT SOCIAL | B62: Cohésion sociale
A63: DÉVELOPPEMENT SOCIAL | B63: Appui aux groupes vulnérables
A64: DÉVELOPPEMENT SOCIAL | B64: Développement local participatif
A65: DÉVELOPPEMENT SOCIAL | B65: Action humanitaire
A66: DÉVELOPPEMENT SOCIAL | B66: Résilience communautaire
A67: DIVERS SECTEURS | B67: Programmes multisectoriels
A68: DIVERS SECTEURS | B68: Développement intégré
A69: DIVERS SECTEURS | B69: Appui budgétaire sectoriel
... A227: SPORTS ET LOISIRS | B227: Formation des encadreurs sportifs

Sheet Suivi_Trimestriel
A1: Code_Projet | B1: Annee_Suivi | C1: Trimestre | D1: TEF_Trim | E1: Montant_Decaisse_USD | F1: Montant_Decaisse_FCFA | G1: TEP_Trim | H1: Activites_Realisees | I1: TEF_Cumule | J1: TEP_Cumule | K1: Difficultes_Rencontrees | L1: Approches_Solution | M1: Recommandations | N1: Date_Saisie
A2: PRJ-2025-001 | B2: 2025 | C2: trim1 | D2: 0.12 | E2: 450000 | F2: =IFERROR(E2*610,"") -> 274500000 | G2: 0.15 | H2: Études techniques lancées, recrutement en cours | I2: =IFERROR(SUMIF(A:A,A2,D:D),"") -> 0.12 | J2: =IFERROR(AVERAGEIF(A:A,A2,G:G),"") -> 0.15 | K2: Retards dans les appels d'offres | L2: Renforcement équipe passation des marchés | M2: Accélérer procédures DAO Q2 | N2: =TODAY() -> 46238
F3: =IFERROR(E3*VLOOKUP(TODAY(),Paramètres!$A:$B,2,1),"") | I3: =IFERROR(SUMIF(A:A,A3,D:D),"") -> 0 | J3: =IFERROR(AVERAGEIF(A:A,A3,G:G),"") | N3: =TODAY() -> 46238
F4: =IFERROR(E4*VLOOKUP(TODAY(),Paramètres!$A:$B,2,1),"") | I4: =IFERROR(SUMIF(A:A,A4,D:D),"") -> 0 | J4: =IFERROR(AVERAGEIF(A:A,A4,G:G),"") | N4: =TODAY() -> 46238
F5: =IFERROR(E5*VLOOKUP(TODAY(),Paramètres!$A:$B,2,1),"") | I5: =IFERROR(SUMIF(A:A,A5,D:D),"") -> 0 | J5: =IFERROR(AVERAGEIF(A:A,A5,G:G),"") | N5: =TODAY() -> 46238
F6: =IFERROR(E6*VLOOKUP(TODAY(),Paramètres!$A:$B,2,1),"") | I6: =IFERROR(SUMIF(A:A,A6,D:D),"") -> 0 | J6: =IFERROR(AVERAGEIF(A:A,A6,G:G),"") | N6: =TODAY() -> 46238
F7: =IFERROR(E7*VLOOKUP(TODAY(),Paramètres!$A:$B,2,1),"") | I7: =IFERROR(SUMIF(A:A,A7,D:D),"") -> 0 | J7: =IFERROR(AVERAGEIF(A:A,A7,G:G),"") | N7: =TODAY() -> 46238
F8: =IFERROR(E8*VLOOKUP(TODAY(),Paramètres!$A:$B,2,1),"") | I8: =IFERROR(SUMIF(A:A,A8,D:D),"") -> 0 | J8: =IFERROR(AVERAGEIF(A:A,A8,G:G),"") | N8: =TODAY() -> 46238
F9: =IFERROR(E9*VLOOKUP(TODAY(),Paramètres!$A:$B,2,1),"") | I9: =IFERROR(SUMIF(A:A,A9,D:D),"") -> 0 | J9: =IFERROR(AVERAGEIF(A:A,A9,G:G),"") | N9: =TODAY() -> 46238
F10: =IFERROR(E10*VLOOKUP(TODAY(),Paramètres!$A:$B,2,1),"") | I10: =IFERROR(SUMIF(A:A,A10,D:D),"") -> 0 | J10: =IFERROR(AVERAGEIF(A:A,A10,G:G),"") | N10: =TODAY() -> 46238
F11: =IFERROR(E11*VLOOKUP(TODAY(),Paramètres!$A:$B,2,1),"") | I11: =IFERROR(SUMIF(A:A,A11,D:D),"") -> 0 | J11: =IFERROR(AVERAGEIF(A:A,A11,G:G),"") | N11: =TODAY() -> 46238
F12: =IFERROR(E12*VLOOKUP(TODAY(),Paramètres!$A:$B,2,1),"") | I12: =IFERROR(SUMIF(A:A,A12,D:D),"") -> 0 | J12: =IFERROR(AVERAGEIF(A:A,A12,G:G),"") | N12: =TODAY() -> 46238
F13: =IFERROR(E13*VLOOKUP(TODAY(),Paramètres!$A:$B,2,1),"") | I13: =IFERROR(SUMIF(A:A,A13,D:D),"") -> 0 | J13: =IFERROR(AVERAGEIF(A:A,A13,G:G),"") | N13: =TODAY() -> 46238
F14: =IFERROR(E14*VLOOKUP(TODAY(),Paramètres!$A:$B,2,1),"") | I14: =IFERROR(SUMIF(A:A,A14,D:D),"") -> 0 | J14: =IFERROR(AVERAGEIF(A:A,A14,G:G),"") | N14: =TODAY() -> 46238
... F101: =IFERROR(E101*VLOOKUP(TODAY(),Paramètres!$A:$B,2,1),"") | I101: =IFERROR(SUMIF(A:A,A101,D:D),"") -> 0 | J101: =IFERROR(AVERAGEIF(A:A,A101,G:G),"") | N101: =TODAY() -> 46238

Sheet Accords_consolides
B1: ACCORDS DE DÉVELOPPEMENT DU BÉNIN — BASE CONSOLIDÉE ENRICHIE
B2: Source : RCD + mabase | 865 accords | Généré le 30/07/2026
B3: Cette feuille enrichit la base RCD avec 11 colonnes issues de mabase, appariées par titre d'accord. La colonne Statut_Appariement indique la fiabilité de chaque appariement.
B5: TABLE DES ACCORDS CONSOLIDÉS ENRICHIS
B6: Code Projet | C6: Annee de signature | D6: Annee de cloture | E6: Modalité d'intervention | F6: Objet de l'accord | G6: Objectif général | H6: Source vérifiable | I6: Partenaire | J6: Sigle_Part | K6: Secteur principal | L6: Nature (Prêt/Don/Mixte) | M6: Montant_Pret_FCFA | N6: Montant_Don_FCFA | O6: Montant_Total_FCFA | P6: Devise | Q6: Montant total (devise) | R6: Instrument de financement | S6: Date de signature | T6: Date d'approbation | U6: Date de clôture | V6: Zone | W6: APD Oui/non | X6: TYPE DE FINANCEMENT | Y6: TYPE DE CONTRIBUTEUR | Z6: SOUS SECTEUR | AA6: AXE PAG | AB6: PILIER PAG | AC6: ODD | AD6: Cible_ODD | AE6: Pilier | AF6: STATUT (en cours, achevé, en approbation) | AG6: Objectifs spécifiques | AH6: Resultats attendues | AI6: Principales composantes | AJ6: Bénéficiaires directes | AK6: Population cible
B7: P-0001-BIDC-2011 | C7: 2011 | D7: =YEAR(U7) -> 2017 | E7: Projet d'investissement | F7: Projet d'électrification rurale de soixante sept (67) localités en République du Bénin | G7: Accroître le taux d'accès à l'électricité en milieu rural en raccordant 67 localités isolées au réseau électrique de la SBEE pour stimuler l'économie locale et améliorer les services sociaux de base. | H7: https://evaluation.gouv.bj | I7: Banque d’Investissement et de Développement de la CEDEAO | J7: BIDC | K7: ÉNERGIE | L7: Prêt | M7: 10000000000 | N7: 0 | O7: 10000000000 | P7: EUR | Q7: 20000000 | R7: Prêt non concessionnel | S7: 40548 | T7: 40511 | U7: 43100 | V7: ALIBORI (BANIKOARA, GOGOUNOU, KANDI, MALANVILLE, SEGBANA) ; BORGOU (BEMBÉRÈKÉ, KALALÉ, N'DALI, NIKKI, PARAKOU, PÉRÉRE, SINENDÉ, TCHAOUROU) ; COLLINES (BANTÈ, DASSA-ZOUMÉ, GLAZOUÉ, OUÈSSÈ, SAVALOU, SAVÈ) ; ZOU (ABOMEY, AGBANGNIZOUN, BOHICON, COVÈ, DJIDJA, OUINHI, ZA-KPOTA, ZAGNANADO, ZOGBODOMEY) ; COUFFO (APLAHOUÉ, DJAKOTOMEY, DOGBO, KLOUÉKANMÈ, LALO, TOVIKLIN) ; MONO (ATHIÉMÉ, BOPA, COMÈ, GRAND-POPO, HOUÉYOGBÉ, LOKOSSA) ; ATLANTIQUE (ABOMEY-CALAVI, ALLADA, KPOMASSÈ, OUIDAH, SÔ-AVA, TOFFO, TORI-BOSSITO, ZÈ) ; OUÉMÉ (ADJARRA, ADJOHOUN, AGÉGUÉ, AKPRO-MISSÉRÉTÉ, AVRANKOU, BONOU, DANGBO, PORTO-NOVO, SÈMÈ-PODJI) ; PLATEAU (ADJA-OUÉRÉ, IFANGNI, KÉTOU, POBÈ, SAKÉTÉ). | Y7: MULTILATERAUX | Z7: Production d’électricité
B8: P-0002-BOAD-2011 | C8: 2011 | D8: =YEAR(U8) -> 2016 | E8: Projet d'investissement | F8: Projet de construction de la ligne d'interconnexion électrique 161 KV Bembèrèkè-Kandi-Malanville | G8: Sécuriser et accroître l'approvisionnement en énergie électrique des localités septentrionales du Bénin et faciliter l'interconnexion avec le réseau du Niger grâce à la construction d'une ligne de transport haute tension. | H8: https://boad.org | I8: Banque Ouest Africaine de Développement | J8: BOAD | K8: ÉNERGIE | L8: Prêt | M8: 20000000000 | N8: 0 | O8: 20000000000 | P8: XOF | Q8: 20000000000 | R8: Prêt non concessionnel | S8: 40565 | T8: 40527 | U8: 42735 | V8: BORGOU (BEMBÉRÈKÉ(BEMBÉRÈKÉ CENTRE)) ; ALIBORI (GOGOUNOU(GOGOUNOU CENTRE, BAGOU, GOUNAROU), KANDI(KANDI I, KANDI II, DONWARI, SAM), MALANVILLE(MALANVILLE CENTRE, GUÉNÉ, GAROU)). | Y8: MULTILATERAUX
B9: P-0003-OFID/OPEP-2011 | C9: 2011 | D9: =YEAR(U9) -> 2018 | E9: Projet d'investissement | F9: Projet de construction de la route Kandi-Ségbana-Frontière du Nigeria | G9: Améliorer le niveau de service de l'axe routier reliant Kandi à la frontière du Nigeria afin de réduire les coûts de transport, désenclaver les zones agricoles traversées et dynamiser le commerce transfrontalier. | H9: https://documentation-anbenin.org | I9: Fonds de l’OPEP pour le Développement International | J9: OFID/OPEP | K9: INFRASTRUCTURES ROUTIERES ET TRANSPORT | L9: Prêt | M9: 5225000000 | N9: 0 | O9: 5225000000 | P9: EUR | Q9: 11000000 | R9: Prêt concessionnel | S9: 40556 | T9: 40528 | U9: 43281 | V9: ALIBORI (KANDI(KANDI I), SÉGBANA(SÉGBANA CENTRE, LIBOUSSOU, LOUGOU, SOKOTINDJI(SAMIA))). | Y9: MULTILATERAUX
B10: P-0004-FND-2011 | C10: 2011 | D10: =YEAR(U10) -> 2017 | E10: Projet d'investissement | F10: Projet de Développement de l'Accès à l'Energie Moderne par la Biomasse | G10: Promouvoir l'utilisation de technologies énergétiques durables basées sur la biomasse, réduire la pression sur les ressources forestières à travers la diffusion de foyers améliorés et renforcer les capacités des acteurs de la filière bois-énergie. | H10: https://direction-energie.gouv.bj | I10: Fonds Nordique de Développement | J10: FND | K10: ÉNERGIE | L10: Don | M10: 0 | N10: 983935500 | O10: 983935500 | P10: EUR | Q10: 1500000 | R10: Don | S10: 40574 | T10: 40522 | U10: 43100 | V10: COLLINES (SAVALOU, DASSA-ZOUMÉ, GLAZOUÉ, OUÈSSÈ) ; ZOU (DJIDJA, SAVALOU) ; BORGOU (TCHAOUROU). | Y10: MULTILATERAUX
B11: P-0005-BID-2011 | C11: 2011 | D11: =YEAR(U11) -> 2014 | E11: Assistance technique / Renforcement institutionnel | F11: Assistance technique au profit du Ministère de la Prospective, du Développement, de l'Evaluation des Politiques Publiques et de la Coordination de l'Action Gouvernementale | G11: Renforcer les capacités institutionnelles et techniques du ministère dans la formulation des politiques de développement, la planification stratégique à long terme et l'évaluation d'impact des politiques publiques. | H11: https://gouv.bj | I11: Banque Islamique de Développement | J11: BID | K11: GOUVERNANCE | L11: Don | M11: 0 | N11: 150000000 | O11: 150000000 | P11: DI | Q11: 200000 | R11: Assistance technique | S11: 40588 | T11: 40532 | U11: 42004 | V11: LITTORAL (COTONOU). | Y11: MULTILATERAUX
B12: P-0006-BM-2011 | C12: 2011 | D12: =YEAR(U12) -> 2012 | E12: Appui budgétaire sectoriel | F12: Financement supplémentaire au sixième Crédit d'Appui à la Réduction de la Pauvreté (PRSC-6) | G12: Soutenir la mise en œuvre de la stratégie de croissance pour la réduction de la pauvreté en améliorant la gestion des finances publiques, l'efficacité de la dépense sociale et le climat des investissements. | H12: https://banquemondiale.org | I12: Banque mondiale | J12: BM | K12: GOUVERNANCE | L12: Don | M12: 0 | N12: 11000000000 | O12: 11000000000 | P12: DTS | Q12: 14000000 | R12: Don | S12: 40660 | T12: 40631 | U12: 41274 | V12: NATIONAL | Y12: MULTILATERAUX
B13: P-0007-BOAD-2011 | C13: 2011 | D13: =YEAR(U13) -> 2016 | E13: Projet d'investissement | F13: Projet d'Aménagement et de Bitumage de la route Ouidah-Allada et de la bretelle Pahou-Tori. | G13: Assurer la liaison routière moderne entre les communes de Ouidah et d'Allada afin de faciliter la circulation des personnes et des biens, de désenclaver les zones de production agricole et de soutenir l'axe touristique de l'Atlantique. | H13: https://boad.org | I13: Banque Ouest Africaine de Développement | J13: BOAD | K13: INFRASTRUCTURES ROUTIERES ET TRANSPORT | L13: Prêt | M13: 5320000000 | N13: 0 | O13: 5320000000 | P13: XOF | Q13: 5320000000 | R13: Prêt non concessionnel | S13: 40681 | T13: 40527 | U13: 42735 | V13: ATLANTIQUE (OUIDAH(OUIDAH I, OUIDAH II, SAVI), TORI-BOSSITO(TORI-CADA, TORI-GBÉGAMEY, TORI-BOSSITO CENTRE), ALLADA(ALLADA CENTRE, LON-AGONMEY, HINVI)). | Y13: MULTILATERAUX
B14: P-0008-BM-2011 | C14: 2011 | D14: =YEAR(U14) -> 2016 | E14: Projet d'investissement | F14: Projet de Productivité Agricole en Afrique de l'Ouest (PPAAO) | G14: Générer et diffuser des technologies agricoles améliorées dans les filières prioritaires du Bénin, tout en renforçant les systèmes de recherche agricole et la coopération scientifique régionale en Afrique de l'Ouest. | H14: https://banquemondiale.org | I14: Banque mondiale | J14: BM | K14: AGRICULTURE | L14: Don | M14: 0 | N14: 8400000000 | O14: 8400000000 | P14: DTS | Q14: 11000000 | R14: Don | S14: 40701 | T14: 40626 | U14: 42735 | V14: BORGOU (BEMBÉRÈKÉ(INA)) ; ATLANTIQUE (ALLADA(NIAOULI)) ; OUÉMÉ (ADJOHOUN, BONOU, DANGBO). | Y14: MULTILATERAUX
B15: P-0009-BM-2011 | C15: 2011 | D15: =YEAR(U15) -> 2017 | E15: Projet d'investissement | F15: Projet d'Appui à la Diversification Agricole (PADA) | G15: Restaurer et améliorer la productivité et la compétitivité des filières agricoles cibles (notamment le riz, le maïs, l'anacarde et l'ananas) pour accroître les revenus des petits producteurs et sécuriser la souveraineté alimentaire. | H15: https://banquemondiale.org | I15: Banque mondiale | J15: BM | K15: AGRICULTURE | L15: Don | Prêt | M15: 15500000000 | N15: 7500000000 | O15: 23000000000 | P15: DTS | EUR | Q15: 35000000 | R15: Fonds fiduciaire (Trust Fund) | Prêt concessionnel | S15: 40701 | T15: 40626 | U15: 42794 | V15: OUÉMÉ (DANGBO, ADJOHOUN, BONOU) ; ZOU (ABOMEY, BOHICON, ZAKPOTA) ; COLLINES (DASSA-ZOUMÉ, SAVALOU) ; ATLANTIQUE (ABOMEY-CALAVI, ZÈ). | Y15: MULTILATERAUX
B16: P-0010-BM-2011 | C16: 2011 | D16: =YEAR(U16) -> 2019 | E16: Projet d'investissement | F16: Projet d'Appui à la Gestion des Aires Protégées | G16: Consolider et étendre les investissements destinés à la structuration des chaînes de valeur agricoles afin d'amplifier l'accès aux marchés des groupements de producteurs et d'améliorer la commercialisation des produits locaux. | H16: https://banquemondiale.org | I16: Banque mondiale | J16: BM | K16: CADRE DE VIE | L16: Don | M16: 0 | N16: 3450000000 | O16: 3450000000 | P16: DTS | EUR | Q16: 5200000 | R16: Don | Fonds fiduciaire (Trust Fund) | S16: 40701 | T16: 40631 | U16: 43646 | V16: OUÉMÉ (DANGBO, ADJOHOUN, BONOU) ; ZOU (ABOMEY, BOHICON, ZAKPOTA) ; COLLINES (DASSA-ZOUMÉ, SAVALOU) ; ATLANTIQUE (ABOMEY-CALAVI, ZÈ). | Y16: MULTILATERAUX
B17: P-0011-BM-2011 | C17: 2011 | D17: =YEAR(U17) -> 2019 | E17: Projet d'investissement | F17: Projet d'Urgence de Gestion Environnementale en Milieu Urbain | G17: Améliorer la gestion durable des écosystèmes des parcs nationaux du W et de la Pendjari, renforcer la conservation de la biodiversité et impliquer les communautés locales dans la gouvernance des ressources naturelles. | H17: https://banquemondiale.org | I17: Banque mondiale | J17: BM | K17: CADRE DE VIE | L17: Prêt | M17: 25000000000 | N17: 0 | O17: 25000000000 | P17: DTS | Q17: 31600000 | R17: Prêt concessionnel | S17: 40701 | T17: 40631 | U17: 43496 | V17: ATACORA (TANGUIÉTA(TANGUIÉTA CENTRE), KÉROU) ; ALIBORI (BANIKOARA(BANIKOARA CENTRE)). | Y17: MULTILATERAUX
B18: P-0012-BM-2011 | C18: 2011 | D18: =YEAR(U18) -> 2016 | E18: Projet d'investissement | F18: Projet de Nutrition Communautaire | G18: Réduire la vulnérabilité des populations du Grand Nokoué face aux inondations récurrentes, améliorer les infrastructures d'assainissement pluvial et optimiser la gestion des déchets solides ménagers. | H18: https://evaluation.gouv.bj | I18: Banque mondiale | J18: BM | K18: SANTÉ | L18: Don | M18: 0 | N18: 1398890500 | O18: 1398890500 | P18: EUR | Q18: 2797781 | R18: Don | S18: 40724 | T18: 40687 | U18: 42735 | V18: LITTORAL (COTONOU(DU 1ER AU 13ÈME)) ; ATLANTIQUE (ABOMEY-CALAVI(GODOMEY, ABOMEY-CALAVI CENTRE, AKASSATO), OUIDAH) ; OUÉMÉ (PORTO-NOVO(DU 1ER AU 5ÈME), SÈMÈ-PODJI). | Y18: MULTILATERAUX
B19: P-0013-BOAD-2011 | C19: 2011 | D19: =YEAR(U19) -> 2016 | E19: Projet d'investissement | F19: Projet de pavage de rues et d'assainissement dans la Commune d'Abomey-Calavi | G19: Moderniser la voirie urbaine des arrondissements centraux d'Abomey-Calavi par le pavage et la construction de collecteurs d'eaux pluviales afin d'améliorer les conditions de circulation et d'hygiène des populations. | H19: https://boad.org | I19: Banque Ouest Africaine de Développement | J19: BOAD | K19: CADRE DE VIE | L19: Prêt | M19: 6500000000 | N19: 0 | O19: 6500000000 | P19: XOF | Q19: 6500000000 | R19: Prêt non concessionnel | S19: 40739 | T19: 40688 | U19: 42735 | V19: ATLANTIQUE (ABOMEY-CALAVI(ABOMEY-CALAVI CENTRE, GODOMEY, AKASSATO, ZINVIÉ)). | Y19: MULTILATERAUX
... B89: P-0078-BID-2014 | C89: 2014 | D89: =YEAR(U89) -> 2020 | E89: Projet d'investissement | F89: Projet de Développement de l'Education de Base-Phase IV | G89: Accroître la capacité d'accueil et la mixité du système scolaire par la construction d'infrastructures de collèges ruraux intégrés équipés de blocs sanitaires adaptés. ; Acquérir et distribuer des manuels scolaires et des guides didactiques et renforcer la formation pédagogique continue des instituteurs et enseignants contractuels. | H89: documentation-anbenin.org | I89: Banque Islamique de Développement | J89: BID | K89: ÉDUCATION | L89: Prêt | M89: 6080000000 | N89: 0 | O89: 6080000000 | P89: DI | EUR | Q89: 9670000 | R89: Istisna'a | S89: 41802 | T89: 41800 | U89: 44012 | V89: NATIONAL | Y89: MULTILATERAUX
B90: P-0079-BID-2014 | C90: 2014 | D90: =YEAR(U90) -> 2018 | E90: Projet d'investissement | F90: Projet BID-UEMOA d'hydraulique et d'assainissement en milieu rural | G90: Approvisionner durablement en eau potable les localités rurales cibles des départements du Bénin à travers la réalisation de forages équipés de pompes manuelles ou solaires. | H90: documentation-anbenin.org | I90: Banque Islamique de Développement | J90: BID | K90: EAU ET ASSAINISSEMENT | L90: Prêt | M90: 6250000000 | N90: 0 | O90: 6250000000 | P90: EUR | Q90: 12500000 | R90: Istisna'a | S90: 41816 | T90: 41690 | U90: 43465 | V90: ATACORA ; DONGA ; BORGOU ; ALIBORI ; ZOU ; COLLINES. | W90: APD | X90: PRÊT | Y90: MULTILATERAUX | Z90: ACCÈS À L’EAU POTABLE | AA90: AXE 6 | AB90: PILIER 3 | AC90: ODD 6 | AD90: 6.1 | AE90: Environnemental | AF90: en cours
B91: P-0080-UEMOA-2014 | C91: 2014 | D91: =YEAR(U91) -> 2018 | E91: Projet d'investissement | F91: Bonification du taux d'intérêt du prêt relatif au financement partiel du Projet de renforcement du système d'alimentation en eau potable dans 69 villages | G91: Réduire le coût financier global de la dette contractée pour les infrastructures d'adduction d'eau villageoise au profit de la viabilité budgétaire du programme. | H91: documentation-anbenin.org | I91: Union Économique et Monétaire Ouest Africaine | J91: UEMOA | K91: EAU ET ASSAINISSEMENT | L91: Don | M91: 0 | N91: 1124584425 | O91: 1124584425 | P91: XOF | Q91: 1124584425 | R91: Don | S91: 41815 | T91: 41774 | U91: 43465 | V91: NATIONAL | Y91: MULTILATERAUX
B92: P-0081-AFD-2014 | C92: 2014 | D92: =YEAR(U92) -> 2018 | E92: Projet d'investissement | F92: Projet d'appui au renforcement des acteurs du secteur privé | G92: Mettre en œuvre des programmes d'appui à la mise à niveau des entreprises industrielles locales et faciliter leur accès aux financements de trésorerie et d'investissement. | H92: evaluation.gouv.bj | I92: Agence Française de Développement | J92: AFD | K92: PROTECTION SOCIALE ET EMPLOI | L92: Don | M92: 0 | N92: 682195280 | O92: 682195280 | P92: EUR | Q92: 1040090.4 | R92: Don | S92: 41922 | T92: 41856 | U92: 43465 | V92: NATIONAL | Y92: BILATERAUX
B93: P-0081-UE-2014 | C93: 2014 | D93: =YEAR(U93) -> 2018 | E93: Projet d'investissement | F93: Projet d'appui au renforcement des acteurs du secteur privé | G93: Améliorer la compétitivité des micro, petites et moyennes entreprises en renforçant l'offre de services d'appui-conseil de la Chambre de Commerce et d'Industrie du Bénin. | H93: evaluation.gouv.bj | I93: Union Européenne | J93: UE | K93: PROTECTION SOCIALE ET EMPLOI | L93: Don | M93: 0 | N93: 5885221934 | O93: 5885221934 | P93: EUR | Q93: 8972742.7 | R93: Don | S93: 41922 | T93: 41856 | U93: 43465 | V93: NATIONAL | Y93: MULTILATERAUX
B94: P-0082-BOA-BENIN-2014 | C94: 2014 | D94: =YEAR(U94) -> 2017 | E94: Projet d'investissement | F94: Projet d'aménagement et de bitumage de la route Djèrègbè – Dja - Owodé Frontière du Nigéria (9,67 km) | G94: Apporter le concours financier complémentaire requis pour le bitumage et la signalisation sécurisée de l'axe frontalier commercial de Dja. | H94: documentation-anbenin.org | I94: Bank of Africa – Bénin | J94: BOA-BENIN | K94: INFRASTRUCTURES ROUTIERES ET TRANSPORT | L94: Prêt | M94: 9000000000 | N94: 0 | O94: 9000000000 | P94: XOF | Q94: 9000000000 | R94: Prêt commercial | S94: 41878 | T94: 41801 | U94: 43100 | V94: OUÉMÉ (SÈMÈ-PODJI) ; PLATEAU (IFANGNI). | Y94: PRIVE
B95: P-0082-ECOBANK-Bénin-2014 | C95: 2014 | D95: =YEAR(U95) -> 2017 | E95: Projet d'investissement | F95: Projet d'aménagement et de bitumage de la route Djèrègbè – Dja - Owodé Frontière du Nigéria (9,67 km) | G95: Financer de façon syndiquée les travaux de voirie lourde sur cet axe routier commercial majeur reliant l'Ouémé au marché nigérian. | H95: documentation-anbenin.org | I95: ECOBANK-Bénin | J95: ECOBANK-Bénin | K95: INFRASTRUCTURES ROUTIERES ET TRANSPORT | L95: Prêt | M95: 2000000000 | N95: 0 | O95: 2000000000 | P95: XOF | Q95: 2000000000 | R95: Prêt commercial | S95: 41877 | T95: 41801 | U95: 43100 | V95: OUÉMÉ (SÈMÈ-PODJI) ; PLATEAU (IFANGNI). | Y95: PRIVE
B96: P-0083-BOAD-2014 | C96: 2014 | D96: =YEAR(U96) -> 2018 | E96: Projet d'investissement | F96: Projet d'Appui à l'assurance Mutuelle Agricole du Bénin (AMAB) pour la mise en place d'une assurance récolte des filières coton et Riz au Bénin | G96: Sécuriser les investissements des petits exploitants agricoles face aux aléas climatiques (sécheresses, inondations) en développant des produits d'assurance récolte indicielle. ; Sécuriser les investissements des petits exploitants agricoles face aux aléas climatiques (sécheresse, inondations) en structurant et en lançant un produit d'assurance récolte indicielle. | H96: boad.org ; https://boad.org | I96: Banque Ouest Africaine de Développement | J96: BOAD | K96: AGRICULTURE | L96: Prêt | M96: 1089000000 | N96: 0 | O96: 1089000000 | P96: XOF | Q96: 1089000000 | R96: Prêt non concessionnel | S96: 41909 | T96: 41722 | U96: 43465 | V96: ALIBORI ; BORGOU ; ATACORA ; DONGA ; ZOU ; COLLINES ; OUÉMÉ. | Y96: MULTILATERAUX
B97: P-0084-BOAD-2014 | C97: 2014 | D97: =YEAR(U97) -> 2019 | E97: Projet d'investissement | F97: Projet de pavage de rues et d'assainissement dans les villes d'Athiémé, d'Avrankou, d'Azovè, de Calavi (phase 2), de Kérou, de Malanville et de Zogbodomey et de Projet de construction d'un pont sur la traversée lagunaire de Djonou entre Cocotomey et Womey | G97: Améliorer la voirie dans sept agglomérations et résoudre l'enclavement critique du quartier Womey par l'érection du pont de franchissement sur la lagune de Djonou. | H97: boad.org | I97: Banque Ouest Africaine de Développement | J97: BOAD | K97: CADRE DE VIE | L97: Prêt | M97: 20000000000 | N97: 0 | O97: 20000000000 | P97: XOF | Q97: 20000000000 | R97: Prêt non concessionnel | S97: 41909 | T97: 41722 | U97: 43830 | V97: MONO (ATHIÉMÉ) ; OUÉMÉ (AVRANKOU) ; COUFFO (APLAHOUÉ(AZOVÈ)) ; ATLANTIQUE (ABOMEY-CALAVI(WOMEY, ABOMEY-CALAVI CENTRE)) ; ATACORA (KÉROU) ; ALIBORI (MALANVILLE) ; ZOU (ZOGBODOMEY) ; LITTORAL (COTONOU). | Y97: MULTILATERAUX
B98: P-0085-BADEA-2014 | C98: 2014 | D98: =YEAR(U98) -> 2015 | E98: Projet d'investissement | F98: Etudes environnementale et sociale du Projet de protection de la côte ouest de la ville de Cotonou (littoral Hillacondji-Grand-Popo) | G98: Réaliser les analyses d'impact et d'ingénierie côtière requises pour concevoir des ouvrages de stabilisation du trait de côte face à l'avancée de la mer sur le littoral ouest. | H98: documentation-anbenin.org | I98: Banque Arabe pour le Développement Économique en Afrique | J98: BADEA | K98: CADRE DE VIE | L98: Prêt | M98: 225000000 | N98: 0 | O98: 225000000 | P98: EUR | Q98: 450000 | R98: Prêt concessionnel | S98: 41911 | T98: 41773 | U98: 42369 | V98: MONO (GRAND-POPO(HILLACONDJI)) ; LITTORAL (COTONOU). | Y98: MULTILATERAUX
B99: P-0086-BADEA-2014 | C99: 2014 | D99: =YEAR(U99) -> 2019 | E99: Projet d'investissement | F99: Financement additionnel du projet de protection de la côte à l'Est de la ville de Cotonou | G99: Participer au financement de la construction d'un système d'épis rocheux et de rechargement en sable pour stabiliser la plage Est de Cotonou contre l'érosion marine accélérée. | H99: documentation-anbenin.org | I99: Banque Arabe pour le Développement Économique en Afrique | J99: BADEA | K99: CADRE DE VIE | L99: Prêt | M99: 1000000000 | N99: 0 | O99: 1000000000 | P99: EUR | Q99: 2000000 | R99: Prêt concessionnel | S99: 41963 | T99: 41922 | U99: 43830 | V99: LITTORAL (COTONOU) ; OUÉMÉ (SÈMÈ-PODJI). | Y99: MULTILATERAUX
B100: P-0086-FKDEA-2014 | C100: 2014 | D100: =YEAR(U100) -> 2019 | E100: Projet d'investissement | F100: Financement additionnel du projet de protection de la côte à l'Est de la ville de Cotonou | G100: Cofinancer les travaux de génie civil côtier lourds pour protéger les infrastructures portuaires et les zones habitées de la bande littorale Est de Cotonou. | H100: documentation-anbenin.org | I100: Fonds Koweïtien pour le Développement Économique Arabe | J100: FKDEA | K100: CADRE DE VIE | L100: Prêt | M100: 5000000000 | N100: 0 | O100: 5000000000 | P100: KWD | Q100: 3000000 | R100: Prêt concessionnel | S100: 41963 | T100: 41922 | U100: 43830 | V100: LITTORAL (COTONOU) ; OUÉMÉ (SÈMÈ-PODJI). | Y100: BILATERAUX
B101: P-0086-OPEP-2014 | C101: 2014 | D101: =YEAR(U101) -> 2019 | E101: Projet d'investissement | F101: Financement additionnel du projet de protection de la côte à l'Est de la ville de Cotonou | G101: Apporter les ressources budgétaires complémentaires pour étendre la couverture de la protection côtière par épis rocheux vers le secteur de Sèmè-Podji. | H101: documentation-anbenin.org | I101: OPEP | J101: OFID/OPEP | K101: CADRE DE VIE | L101: Prêt | M101: 1500000000 | N101: 0 | O101: 1500000000 | P101: EUR | Q101: 3000000 | R101: Prêt concessionnel | S101: 41963 | T101: 41922 | U101: 43830 | V101: LITTORAL (COTONOU) ; OUÉMÉ (SÈMÈ-PODJI). | Y101: MULTILATERAUX
B102: P-0087-BAD-2014 | C102: 2014 | D102: =YEAR(U102) -> 2021 | E102: Projet d'investissement | F102: Projet de transport urbain à Parakou : Reconstruction de la traversée et du contournement de la ville en République du Bénin | G102: Financer les travaux d'infrastructures lourdes de dédoublement de la chaussée urbaine centrale et d'aménagement de voies cyclables et piétonnes à Parakou. | H102: documentation-anbenin.org | I102: Banque Africaine de Développement | J102: BAD | K102: INFRASTRUCTURES ROUTIERES ET TRANSPORT | L102: Prêt | M102: 17468176600 | N102: 0 | O102: 17468176600 | P102: UC | Q102: 23800000 | R102: Prêt concessionnel | S102: 41991 | T102: 41929 | U102: 44561 | V102: BORGOU (PARAKOU). | Y102: MULTILATERAUX
... B110: P-0094-BIDC-2014 | C110: 2014 | D110: =YEAR(U110) -> 2018 | E110: Projet d'investissement | F110: Projet de réhabilitaion des marchés de Savalou et de Glazoué | G110: Rénover et étendre les infrastructures marchandes de Savalou et Glazoué par la construction de hangars modernes, de magasins de stockage et de blocs sanitaires. | H110: evaluation.gouv.bj | I110: Banque d’Investissement et de Développement de la CEDEAO | J110: BIDC | K110: CADRE DE VIE | L110: Prêt | M110: 800000000 | N110: 0 | O110: 800000000 | P110: UC | Q110: 1021092 | R110: Prêt non concessionnel | S110: 41978 | T110: 41831 | U110: 43404 | V110: COLLINES (SAVALOU, GLAZOUÉ). | Y110: MULTILATERAUX
B111: P-0095-EXIMBANK DE CHINE-2014 | C111: 2014 | D111: =YEAR(U111) -> #VALUE! | E111: Assistance technique / Renforcement institutionnel | F111: Accord de coopération économique et technique | G111: Apporter un appui financier sous forme de don pour la réalisation de grands chantiers d'infrastructures publiques prioritaires programmés par le gouvernement. ; Ouvrir des lignes de crédit concessionnelles pour appuyer le financement d'équipements technologiques et de télécommunications pour les services de l'État. | H111: documentation-anbenin.org | I111: Banque chinoise d’import-export | J111: EXIMBANK DE CHINE | K111: GOUVERNANCE | L111: Don | Prêt | M111: 20250000000 | N111: 4050000000 | O111: 24300000000 | P111: CNY | Q111: 300000000 | R111: Don | Prêt concessionnel | S111: 41978 | T111: 41897 | U111: Non spécifiée | V111: LITTORAL (COTONOU). | Y111: BILATERAUX
B112: P-0096-BID-2014 | C112: 2014 | D112: =YEAR(U112) -> 2019 | E112: Projet d'investissement | F112: Projet de construction d'une Centrale thermique de 120 MW à MARIA GLETA (PHASE I) en République du Bénin | G112: Réduire le déficit national en production d'électricité en construisant une centrale thermique moderne de 120 MW fonctionnant en cycle combiné dual à Maria-Gléta. | H112: documentation-anbenin.org | I112: Banque Islamique de Développement | J112: BID | K112: ÉNERGIE | L112: Prêt | M112: 78452457200 | N112: 0 | O112: 78452457200 | P112: EUR | Q112: 119600000 | R112: Crédit-bail | S112: 41984 | T112: 41983 | U112: 43830 | V112: ATLANTIQUE (ABOMEY-CALAVI(TOGBA(MARIA-GLÉTA))). | Y112: MULTILATERAUX
B113: P-0097-BID-2014 | C113: 2014 | D113: =YEAR(U113) -> 2021 | E113: Projet d'investissement | F113: Projet d'Aménagement et de bitumage de la route Banikoara-Kérémou-Frontière du Burkina-Faso | G113: Assurer le bitumage de cet axe routier stratégique de la zone cotonnière pour faciliter le désenclavement des communes du Nord-Ouest et l'interconnexion avec le Burkina Faso. | H113: documentation-anbenin.org | I113: Banque Islamique de Développement | J113: BID | K113: INFRASTRUCTURES ROUTIERES ET TRANSPORT | L113: Prêt | M113: 22958495000 | N113: 0 | O113: 22958495000 | P113: EUR | Q113: 35000000 | R113: Istisna'a | S113: 41984 | T113: 41983 | U113: 44561 | V113: ALIBORI (BANIKOARA) ; ATACORA (KÉROU). | Y113: MULTILATERAUX
B114: P-0098-BOAD-2014 | C114: 2014 | D114: =YEAR(U114) -> 2018 | E114: Projet d'investissement | F114: Projet de pavage de rues et d'assainissement dans les villes de Bembèrèkè, Bonou, Bopa, Dogbo, Ifangni, Kalalé, Karimama, Tanguiéta, Zakpota et Zè (10 villes) | G114: Rehausser l'attractivité et l'hygiène urbaine de dix chefs-lieux de communes intermédiaires par l'exécution de programmes de pavage et de drainage pluvial. | H114: boad.org | I114: Banque Ouest Africaine de Développement | J114: BOAD | K114: CADRE DE VIE | L114: Prêt | M114: 15000000000 | N114: 0 | O114: 15000000000 | P114: XOF | Q114: 15000000000 | R114: Prêt non concessionnel | S114: 41990 | T114: 41906 | U114: 43465 | V114: BORGOU (BEMBÉRÈKÉ, KALALÉ) ; OUÉMÉ (BONOU) ; MONO (BOPA) ; COUFFO (DOGBO) ; PLATEAU (IFANGNI) ; ALIBORI (KARIMAMA) ; ATACORA (TANGUIÉTA) ; ZOU (ZAKPOTA) ; ATLANTIQUE (ZÈ). | Y114: MULTILATERAUX
B115: P-0099-UEMOA-2014 | C115: 2014 | D115: =YEAR(U115) -> 2018 | E115: Projet d'investissement | F115: Convention d'appui à la mise en œuvre du projet de développement de la filière maïs | G115: Intensifier la production de maïs par la diffusion de semences améliorées, l'appui aux plateformes d'égrenage et la facilitation de la commercialisation au sein de l'espace communautaire. | H115: evaluation.gouv.bj | I115: Union Économique et Monétaire Ouest Africaine | J115: UEMOA | K115: AGRICULTURE | L115: Don | M115: 0 | N115: 300000000 | O115: 300000000 | P115: XOF | Q115: 300000000 | R115: Don | S115: 41999 | T115: 41961 | U115: 43465 | V115: NATIONAL | Y115: MULTILATERAUX
B116: P-0100-UEMOA-2014 | C116: 2014 | D116: =YEAR(U116) -> 2018 | E116: Projet d'investissement | F116: Convention d'appui à la structuration de la filière riz | G116: Améliorer la qualité du riz local étuvé béninois à travers la modernisation des petites unités de transformation et le renforcement des capacités des coopératives de producteurs. | H116: evaluation.gouv.bj | I116: Union Économique et Monétaire Ouest Africaine | J116: UEMOA | K116: AGRICULTURE | L116: Don | M116: 0 | N116: 225000000 | O116: 225000000 | P116: XOF | Q116: 225000000 | R116: Don | S116: 41999 | T116: 41961 | U116: 43465 | V116: NATIONAL | Y116: MULTILATERAUX
B117: P-0062-ATLANTIQUE BANK-2015 | C117: 2015 | D117: =YEAR(U117) -> 2019 | E117: Projet d'investissement | F117: Projet de réhabilitation et de renforcement de la route Parakou-Djougou | G117: Participer au pool bancaire national pour préfinancer les tranches de travaux urgents d'élargissement de la route d'interconnexion Parakou-Djougou. | H117: documentation-anbenin.org | I117: Banque Atlantique Bénin | J117: ATLANTIQUE BANK | K117: INFRASTRUCTURES ROUTIERES ET TRANSPORT | L117: Prêt | M117: 7800000000 | N117: 0 | O117: 7800000000 | P117: XOF | Q117: 7800000000 | R117: Prêt commercial | S117: 42152 | T117: 42121 | U117: 43830 | V117: BORGOU (PARAKOU) ; DONGA (DJOUGOU). | Y117: PRIVE
B118: P-0062-BOA-BENIN-2015 | C118: 2015 | D118: =YEAR(U118) -> 2019 | E118: Projet d'investissement | F118: Projet de réhabilitation et de renforcement de la route Parakou-Djougou | G118: Mobiliser les ressources du marché financier bancaire local pour sécuriser le bouclage budgétaire du projet de renforcement de la RNIE 3. | H118: documentation-anbenin.org | I118: Bank of Africa – Bénin | J118: BOA-BENIN | K118: INFRASTRUCTURES ROUTIERES ET TRANSPORT | L118: Prêt | M118: 17000000000 | N118: 0 | O118: 17000000000 | P118: XOF | Q118: 17000000000 | R118: Prêt commercial | S118: 42152 | T118: 42142 | U118: 43830 | V118: BORGOU (PARAKOU) ; DONGA (DJOUGOU). | Y118: PRIVE
B119: P-0062-ECOBANK-Bénin-2015 | C119: 2015 | D119: =YEAR(U119) -> 2019 | E119: Projet d'investissement | F119: Projet de réhabilitation et de renforcement de la route Parakou-Djougou | G119: Apporter le concours financier bancaire commercial local requis pour la libération des emprises et le paiement des entreprises de travaux routiers. | H119: documentation-anbenin.org | I119: ECOBANK-Bénin | J119: ECOBANK-Bénin | K119: INFRASTRUCTURES ROUTIERES ET TRANSPORT | L119: Prêt | M119: 3000000000 | N119: 0 | O119: 3000000000 | P119: XOF | Q119: 3000000000 | R119: Prêt commercial | S119: 42152 | T119: 42048 | U119: 43830 | V119: BORGOU (PARAKOU) ; DONGA (DJOUGOU). | Y119: PRIVE
B120: P-0086-FSD-2015 | C120: 2015 | D120: =YEAR(U120) -> 2019 | E120: Projet d'investissement | F120: Financement additionnel du projet de protection de la côte à l'Est de la ville de Cotonou | G120: Apporter les ressources du Fonds Saoudien pour achever la construction de la barrière d'épis rocheux protectrice de la zone industrielle littorale de Cotonou. | H120: documentation-anbenin.org | I120: Fonds Saoudien de Développement | J120: FSD | K120: CADRE DE VIE | L120: Prêt | M120: 3000000000 | N120: 0 | O120: 3000000000 | P120: EUR | Q120: 6000000 | R120: Prêt concessionnel | S120: 42165 | T120: 42108 | U120: 43830 | V120: LITTORAL (COTONOU) ; OUÉMÉ (SÈMÈ-PODJI). | Y120: BILATERAUX
B121: P-0101-AFD-2015 | C121: 2015 | D121: =YEAR(U121) -> 2021 | E121: Projet d'investissement | F121: Projet de restructuration et d'extension du réseau de la SBEE dans la commune d'Abomey-Calavi et le département de l'Atlantique | G121: Fiabiliser et moderniser le réseau de distribution électrique basse et moyenne tension de l'Atlantique, réduire les pertes techniques et raccorder de nouveaux abonnés ménagers. ; Construire de nouveaux sous-postes d'injection électrique haute tension pour sécuriser l'alimentation de la commune en pleine croissance démographique d'Abomey-Calavi. | H121: evaluation.gouv.bj | I121: Agence Française de Développement | J121: AFD | K121: ÉNERGIE | L121: Don | Prêt | M121: 13119140000 | N121: 13119140000 | O121: 26238280000 | P121: EUR | Q121: 40000000 | R121: Don | Prêt concessionnel | S121: 42110 | T121: 42027 | U121: 44561 | V121: ATLANTIQUE (ABOMEY-CALAVI, ALLADA, KPOMASSÈ, OUIDAH, SÔ-AVA, TOFFO, TORI-BOSSITO, ZÈ). | Y121: BILATERAUX
B122: P-0101-BEI-2015 | C122: 2015 | D122: =YEAR(U122) -> 2021 | E122: Projet d'investissement | F122: Projet de restructuration et d'extension du réseau de la SBEE dans la commune d'Abomey-Calavi et le département de l'Atlantique | G122: Financer l'acquisition de compteurs à prépaiement intelligents et le déploiement de lignes de distribution électrique aériennes et souterraines dans l'Atlantique. | H122: evaluation.gouv.bj | I122: Banque Européenne d’Investissement | J122: BEI | K122: ÉNERGIE | L122: Prêt | M122: 11807226000 | N122: 0 | O122: 11807226000 | P122: EUR | Q122: 18000000 | R122: Prêt | S122: 42157 | T122: 42038 | U122: 44561 | V122: ATLANTIQUE (ABOMEY-CALAVI, ALLADA, KPOMASSÈ, OUIDAH, SÔ-AVA, TOFFO, TORI-BOSSITO, ZÈ). | Y122: MULTILATERAUX
B123: P-0102-AFD-2015 | C123: 2015 | D123: =YEAR(U123) -> 2022 | E123: Projet d'investissement | F123: Projet d'Appui au Développement Agricole des Collines | G123: Accroître de manière durable les revenus des exploitants agricoles du département des Collines en développant les filières porteuses (anacarde, manioc, maïs). ; Financer les infrastructures marchandes agricoles locales (magasins d'anacarde, marchés d'arrondissement) et appuyer l'intercommunalité du département. | H123: evaluation.gouv.bj | I123: Agence Française de Développement | J123: AFD | K123: AGRICULTURE | L123: Don | Prêt | M123: 7237527000 | N123: 655957000 | O123: 7893484000 | P123: EUR | Q123: 12000000 | R123: Don | Prêt concessionnel | S123: 42165 | T123: 42051 | U123: 44742 | V123: COLLINES (BANTÈ, DASSA-ZOUMÉ, GLAZOUÉ, OUÈSSÈ, SAVALOU, SAVÈ). | Y123: BILATERAUX
... B133: P-0112-AFD-2015 | C133: 2015 | D133: =YEAR(U133) -> 2021 | E133: Projet d'investissement | F133: Projet d'Appui à l'Enseignement Secondaire au Bénin | G133: Améliorer les conditions d'apprentissage dans les collèges publics par l'érection de modules de classes, de laboratoires de sciences et l'appui à la formation des enseignants de mathématiques et de sciences physiques. | H133: evaluation.gouv.bj | I133: Agence Française de Développement | J133: AFD | K133: ÉDUCATION | L133: Don | M133: 0 | N133: 6559570000 | O133: 6559570000 | P133: EUR | Q133: 10000000 | R133: Don | S133: 42187 | T133: 42179 | U133: 44561 | V133: NATIONAL | Y133: BILATERAUX
B134: P-0113-ATLANTIQUE BANK-2015 | C134: 2015 | D134: =YEAR(U134) -> #VALUE! | E134: Projet d'investissement | F134: Transition numérique au Bénin | G134: Apporter un soutien financier commercial pour accélérer la modernisation des réseaux de diffusion et de télécommunications de l'État béninois. | H134: https://gouv.bj | I134: Banque Atlantique Bénin | J134: ATLANTIQUE BANK | K134: NUMÉRIQUE | L134: Prêt | M134: 8800000000 | N134: 0 | O134: 8800000000 | P134: XOF | Q134: 8800000000 | R134: Prêt commercial | S134: 42207 | T134: 42139 | U134: Non spécifiée | V134: NATIONAL | Y134: PRIVE
B135: P-0113-BGFI-2015 | C135: 2015 | D135: =YEAR(U135) -> #VALUE! | E135: Projet d'investissement | F135: Transition numérique au Bénin | G135: Structurer le financement à moyen terme destiné aux investissements lourds de numérisation de l'administration et des médias publics. | H135: https://gouv.bj | I135: BGFI BANK Bénin | J135: BGFI | K135: NUMÉRIQUE | L135: Prêt | M135: 3000000000 | N135: 0 | O135: 3000000000 | P135: XOF | Q135: 3000000000 | R135: Prêt commercial | S135: 42207 | T135: 42139 | U135: Non spécifiée | V135: NATIONAL | Y135: PRIVE
B136: P-0113-BOA-BENIN-2015 | C136: 2015 | D136: =YEAR(U136) -> #VALUE! | E136: Projet d'investissement | F136: Transition numérique au Bénin | G136: Mobiliser le financement nécessaire au déploiement des infrastructures techniques de la Télévision Numérique Terrestre (TNT) au Bénin. | H136: https://gouv.bj | I136: Bank of Africa – Bénin | J136: BOA-BENIN | K136: NUMÉRIQUE | L136: Prêt | M136: 13730000000 | N136: 0 | O136: 13730000000 | P136: XOF | Q136: 13730000000 | R136: Prêt commercial | S136: 42207 | T136: 42139 | U136: Non spécifiée | V136: NATIONAL | Y136: PRIVE
B137: P-0113-ECOBANK-Bénin-2015 | C137: 2015 | D137: =YEAR(U137) -> #VALUE! | E137: Projet d'investissement | F137: Transition numérique au Bénin | G137: Participer au pool bancaire national pour le préfinancement des équipements de transmission numérique requis pour la mise en œuvre de la TNT. | H137: https://gouv.bj | I137: ECOBANK-Bénin | J137: ECOBANK-Bénin | K137: NUMÉRIQUE | L137: Prêt | M137: 10000000000 | N137: 0 | O137: 10000000000 | P137: XOF | Q137: 10000000000 | R137: Prêt commercial | S137: 42207 | T137: 42139 | U137: Non spécifiée | V137: NATIONAL | Y137: PRIVE
B138: P-0114-BOAD-2015 | C138: 2015 | D138: =YEAR(U138) -> 2021 | E138: Projet d'investissement | F138: Projet de pavage de rues et d'assainissement dans les villes d'Allada, Banikoara, Bantè, Bassila, Covè, Djidja, Glazoué, Gogounou, Matéri, Ouèssè, Ségbana et Toffo (12 villes) | G138: Réduire l'insalubrité urbaine et améliorer les conditions de mobilité locale dans douze communes secondaires par l'aménagement de voiries urbaines pavées. | H138: boad.org | I138: Banque Ouest Africaine de Développement | J138: BOAD | K138: CADRE DE VIE | L138: Prêt | M138: 15000000000 | N138: 0 | O138: 15000000000 | P138: XOF | Q138: 15000000000 | R138: Prêt non concessionnel | S138: 42271 | T138: 42207 | U138: 44561 | V138: ATLANTIQUE (ALLADA, TOFFO) ; ALIBORI (BANIKOARA, GOGOUNOU, SÉGBANA) ; COLLINES (BANTÈ, GLAZOUÉ, OUÈSSÈ) ; DONGA (BASSILA) ; ZOU (COVÈ, DJIDJA) ; ATACORA (MATÉRI). | Y138: MULTILATERAUX
B139: P-0115-FKDEA-2015 | C139: 2015 | D139: =YEAR(U139) -> 2022 | E139: Projet d'investissement | F139: Projet de construction et d'équipement de l'hôpital de zone de Tchaourou et de six centres de santé | G139: Améliorer la couverture sanitaire de référence dans la commune de Tchaourou par l'érection d'un hôpital de zone moderne équipé et la mise à niveau de dispensaires ruraux. | H139: evaluation.gouv.bj | I139: Fonds Koweïtien pour le Développement Économique Arabe | J139: FKDEA | K139: SANTÉ | L139: Prêt | M139: 8537808015 | N139: 0 | O139: 8537808015 | P139: KWD | Q139: 5000000 | R139: Prêt concessionnel | S139: 42289 | T139: 42216 | U139: 44926 | V139: BORGOU (TCHAOUROU) ; ALIBORI ; ATACORA ; DONGA. | Y139: BILATERAUX
B140: P-0116-BOA-BENIN-2015 | C140: 2015 | D140: =YEAR(U140) -> 2017 | E140: Projet d'investissement | F140: Financement des travaux d'amélioration et complémentaires pour l'achèvement de la construction et de l'équipement de l'aéroport de Tourou | G140: Réaliser les derniers chantiers de voirie, de sécurité incendie et de sécurisation périphérique de l'enceinte aéroportuaire de Tourou à Parakou. | H140: documentation-anbenin.org | I140: Bank of Africa – Bénin | J140: BOA-BENIN | K140: INFRASTRUCTURES ROUTIERES ET TRANSPORT | L140: Prêt | M140: 30000000000 | N140: 0 | O140: 30000000000 | P140: XOF | Q140: 30000000000 | R140: Prêt commercial | S140: 42235 | T140: 42046 | U140: 43100 | V140: BORGOU (PARAKOU(TOUROU)). | Y140: PRIVE
B141: P-0117-ATLANTIQUE BANK-2015 | C141: 2015 | D141: =YEAR(U141) -> 2019 | E141: Projet d'investissement | F141: Projet de valorisation de l'énergie solaire (Phase 1) : Acquisition de panneaux solaires photovoltaïques (2ème et 3ème tirages) | G141: Financer de façon ciblée l'électrification solaire autonome de centres de santé ruraux isolés pour sécuriser les chaînes de froid médicales. | H141: documentation-anbenin.org | I141: Banque Atlantique Bénin | J141: ATLANTIQUE BANK | K141: ÉNERGIE | L141: Prêt | M141: 11000000000 | N141: 0 | O141: 11000000000 | P141: XOF | Q141: 11000000000 | R141: Prêt commercial | S141: 42326 | T141: 42242 | U141: 43830 | V141: NATIONAL | Y141: PRIVE
B142: P-0117-BGFI-2015 | C142: 2015 | D142: =YEAR(U142) -> 2019 | E142: Projet d'investissement | F142: Projet de valorisation de l'énergie solaire (Phase 1) : Acquisition de panneaux solaires photovoltaïques (2ème et 3ème tirages) | G142: Structurer le crédit nécessaire au déploiement de l'éclairage public solaire autonome le long d'axes de circulation dans des localités raccordées ou non au réseau SBEE. | H142: documentation-anbenin.org | I142: BGFI BANK Bénin | J142: BGFI | K142: ÉNERGIE | L142: Prêt | M142: 2000000000 | N142: 0 | O142: 2000000000 | P142: XOF | Q142: 2000000000 | R142: Prêt commercial | S142: 42326 | T142: 42242 | U142: 43830 | V142: NATIONAL | Y142: PRIVE
B143: P-0117-BIA Togo-2015 | C143: 2015 | D143: =YEAR(U143) -> 2019 | E143: Projet d'investissement | F143: Projet de valorisation de l'énergie solaire (Phase 1) : Acquisition de panneaux solaires photovoltaïques (2ème et 3ème tirages) | G143: Apporter le concours financier régional pour l'acquisition en volume de kits d'éclairage solaire destinés aux infrastructures publiques d'enseignement. | H143: documentation-anbenin.org | I143: Banque Internationale pour l’Afrique au Togo | J143: BIA Togo | K143: ÉNERGIE | L143: Prêt | M143: 2000000000 | N143: 0 | O143: 2000000000 | P143: XOF | Q143: 2000000000 | R143: Prêt commercial | S143: 42326 | T143: 42242 | U143: 43830 | V143: NATIONAL | Y143: PRIVE
B144: P-0118-MCA/MCC-2015 | C144: 2015 | D144: =YEAR(U144) -> 2023 | E144: Projet d'investissement | F144: Financement du deuxième programme du Bénin pour le Millennium Challenge Account (MCA) | G144: Accroître la productivité et stimuler les investissements privés au Bénin en modernisant le système d'énergie électrique (production, distribution et réformes de la SBEE). | H144: evaluation.gouv.bj | I144: Millennium Challenge Corporation | J144: MCA/MCC | K144: GOUVERNANCE | L144: Don | M144: 0 | N144: 206250000000 | O144: 206250000000 | P144: USD | Q144: 375000000 | R144: Don | S144: 42256 | T144: 42256 | U144: 45099 | V144: NATIONAL | Y144: BILATERAUX
B145: P-0119-BAD-2015 | C145: 2015 | D145: =YEAR(U145) -> 2021 | E145: Projet d'investissement | F145: Financement complémentaire du projet de transport urbain à Parakou | G145: Assurer la couverture financière des avenants techniques requis pour l'achèvement qualitatif des travaux de doublement de la traversée urbaine de Parakou. | H145: documentation-anbenin.org | I145: Banque Africaine de Développement | J145: BAD | K145: INFRASTRUCTURES ROUTIERES ET TRANSPORT | L145: Prêt | M145: 8460000000 | N145: 0 | O145: 8460000000 | P145: UC | Q145: 11530000 | R145: Prêt concessionnel | S145: 42354 | T145: 42262 | U145: 44561 | V145: BORGOU (PARAKOU). | Y145: MULTILATERAUX
B146: P-0119-UBA-Bénin-2015 | C146: 2015 | D146: =YEAR(U146) -> 2020 | E146: Projet d'investissement | F146: Financement complémentaire du projet de transport urbain à Parakou | G146: Consolider le plan de financement pour la réhabilitation lourde et le doublement des voies de contournement routier de la ville de Parakou. | H146: https://boad.org | I146: UBA-Bénin | J146: UBA-Bénin | K146: INFRASTRUCTURES ROUTIERES ET TRANSPORT | L146: Prêt | M146: 15156000000 | N146: 0 | O146: 15156000000 | P146: XOF | Q146: 15156000000 | R146: Prêt commercial | S146: 42354 | T146: 42137 | U146: 44196 | V146: BORGOU (PARAKOU). | Y146: PRIVE
B147: P-0120-BOA-BENIN-2015 | C147: 2015 | D147: =YEAR(U147) -> 2018 | E147: Projet d'investissement | F147: Renforcement du Programme des Micro crédits aux Plus Pauvres - Nouvelle génération | G147: Accroître les capacités financières du Fonds National de la Microfinance pour étendre les lignes de crédit de subsistance à très faible taux d'intérêt aux femmes et artisans vulnérables. | H147: evaluation.gouv.bj | I147: Bank of Africa – Bénin | J147: BOA-BENIN | K147: MICROFINANCE | L147: Prêt | M147: 10000000000 | N147: 0 | O147: 10000000000 | P147: XOF | Q147: 10000000000 | R147: Prêt commercial | S147: 42264 | T147: 42138 | U147: 43465 | V147: NATIONAL | Y147: PRIVE
B148: P-0121-BM-2015 | C148: 2015 | D148: =YEAR(U148) -> 2016 | E148: Projet d'investissement | F148: Dixième Crédit d'Appui à la Réduction de la Pauvreté (PRSC-10) | G148: Fournir l'appui budgétaire pour sécuriser l'exécution des réformes de transparence financière publique et pérenniser le financement direct des programmes sociaux prioritaires de santé de base. | H148: banquemondiale.org | I148: Banque mondiale | J148: BM | K148: GOUVERNANCE | L148: Prêt | M148: 10000000000 | N148: 0 | O148: 10000000000 | P148: USD | Q148: 20000000 | R148: Prêt concessionnel | S148: 42325 | T148: 42282 | U148: 42735 | V148: NATIONAL | Y148: MULTILATERAUX
B149: P-0122-BADEA-2015 | C149: 2015 | D149: =YEAR(U149) -> 2019 | E149: Ligne de crédit | F149: Deuxième ligne de crédit au profit du Fonds National de la Microfinance | G149: Diversifier et densifier les ressources financières des institutions de microfinance pour soutenir le financement d'activités génératrices de revenus portées par des groupements féminins ruraux. | H149: documentation-anbenin.org | I149: Banque Arabe pour le Développement Économique en Afrique | J149: BADEA | K149: MICROFINANCE | L149: Prêt | M149: 2750000000 | N149: 0 | O149: 2750000000 | P149: USD | Q149: 5000000 | R149: Prêt concessionnel | S149: 42287 | T149: 42076 | U149: 43830 | V149: NATIONAL | Y149: MULTILATERAUX
B150: P-0123-AFD-2015 | C150: 2015 | D150: =YEAR(U150) -> 2019 | E150: Assistance technique / Renforcement institutionnel | F150: Deuxième Fonds d'Etudes et de Renforcement des Capacités (FERC II) | G150: Mettre à disposition des ministères des financements d'expertise technique pour la maturation des projets structurants du Programme d'Action du Gouvernement. | H150: evaluation.gouv.bj | I150: Agence Française de Développement | J150: AFD | K150: GOUVERNANCE | L150: Don | M150: 0 | N150: 327000000 | O150: 327000000 | P150: EUR | Q150: 500000 | R150: Don | S150: 42292 | T150: 42073 | U150: 43830 | V150: NATIONAL | Y150: BILATERAUX
B151: P-0124-BGFI-2015 | C151: 2015 | D151: =YEAR(U151) -> #VALUE! | E151: Projet d'investissement | F151: Financement des travaux de réfection du Marché International de Dantokpa | G151: Réhabiliter les réseaux d'assainissement et moderniser les zones à risque d'incendie du marché de Dantokpa pour sécuriser les commerçants et fluidifier les transactions de la sous-région. | H151: https://gouv.bj | I151: BGFI BANK Bénin | J151: BGFI | K151: CADRE DE VIE | L151: Prêt | M151: 3000000000 | N151: 0 | O151: 3000000000 | P151: XOF | Q151: 3000000000 | R151: Prêt commercial | S151: 42321 | T151: 42227 | U151: Non spécifiée | V151: LITTORAL (COTONOU). | Y151: PRIVE
B152: P-0125-BAD-2015 | C152: 2015 | D152: =YEAR(U152) -> 2021 | E152: Projet d'investissement | F152: Projet de réduction des pertes d'eau et amélioration de la viabilité des systèmes d'AEP de Cotonou, Porto-Novo et leurs agglomérations | G152: Améliorer l'efficacité de la distribution d'eau potable de la SONEB par la détection des fuites, le renouvellement des conduites vétustes et la modernisation du comptage des abonnés du Grand Nokoué. | H152: documentation-anbenin.org | I152: Banque Africaine de Développement | J152: BAD | K152: EAU ET ASSAINISSEMENT | L152: Prêt | M152: 5500000000 | N152: 0 | O152: 5500000000 | P152: UC | Q152: 6000000 | R152: Prêt concessionnel | S152: 42354 | T152: 42324 | U152: 44561 | V152: LITTORAL (COTONOU) ; OUÉMÉ (PORTO-NOVO, SÈMÈ-PODJI) ; ATLANTIQUE (ABOMEY-CALAVI). | Y152: MULTILATERAUX
B153: P-0126-BAD-2015 | C153: 2015 | D153: =YEAR(U153) -> 2023 | E153: Projet d'investissement | F153: Projet d'Appui à la Production Vivrière et au Renforcement de la résilience dans les départements de l'Alibori, du Borgou et des Collines (PAPVIRE-ABC) | G153: Accroître de manière durable la productivité des filières maïs, riz et manioc et renforcer la résilience climatique des exploitations familiales du Centre et du Nord par des infrastructures de maîtrise de l'eau. | H153: documentation-anbenin.org | I153: Banque Africaine de Développement | J153: BAD | K153: AGRICULTURE | L153: Don | M153: 0 | N153: 13200000000 | O153: 13200000000 | P153: USD | Q153: 24000000 | R153: Don | S153: 42354 | T153: 42324 | U153: 45107 | V153: ALIBORI ; BORGOU ; COLLINES. | Y153: MULTILATERAUX
B154: P-0127-BAD-2015 | C154: 2015 | D154: =YEAR(U154) -> 2017 | E154: Programme d'investissement | F154: Programme d'Adhésion des pays membres régionaux à l'Assurance du Commerce en Afrique (ACA) | G154: Permettre au Bénin de finaliser son adhésion à l'ACA afin de sécuriser et d'assurer les investissements directs étrangers contre les risques politiques et souverains majeurs. | H154: documentation-anbenin.org | I154: Banque Africaine de Développement | J154: BAD | K154: GOUVERNANCE | L154: Prêt | M154: 4100000000 | N154: 0 | O154: 4100000000 | P154: UC | Q154: 4970000 | R154: Prêt concessionnel | S154: 42333 | T154: 42324 | U154: 43100 | V154: NATIONAL | Y154: MULTILATERAUX
B155: P-0128-UBA-Bénin-2015 | C155: 2015 | D155: =YEAR(U155) -> 2018 | E155: Projet d'investissement | F155: Projet d'aménagement des aires de jeux de football en gazon synthétique de huit (08) stades omnisports à Djougou, Kandi, Tchaourou, Djakotomey, Zakpota, Bohicon, Lokossa et à l'Université d'Abomey-Calavi | G155: Doter huit communes de pelouses synthétiques modernes conformes aux normes sportives nationales pour favoriser la détection des jeunes talents et dynamiser le sport à la base. | H155: https://gouv.bj | I155: UBA-Bénin | J155: UBA-Bénin | K155: SPORTS ET LOISIRS | L155: Prêt | M155: 2000000000 | N155: 0 | O155: 2000000000 | P155: XOF | Q155: 2000000000 | R155: Prêt commercial | S155: 42324 | T155: 42137 | U155: 43465 | V155: DONGA (DJOUGOU) ; ALIBORI (KANDI) ; BORGOU (TCHAOUROU) ; COUFFO (DJAKOTOMEY) ; ZOU (ZAKPOTA, BOHICON) ; MONO (LOKOSSA) ; ATLANTIQUE (ABOMEY-CALAVI). | Y155: PRIVE
B156: P-0129-UBA-Bénin-2015 | C156: 2015 | D156: =YEAR(U156) -> 2020 | E156: Projet d'investissement | F156: Projet de valorisation de l'énergie solaire (Phase 2) : Acquisition et installation de 105 microcentrales solaires photovoltaïques (1er tirage) | G156: Électrifier de manière autonome 105 villages et centres d'intérêt économique isolés par la construction de mini-centrales photovoltaïques indépendantes de proximité. | H156: https://gouv.bj | I156: UBA-Bénin | J156: UBA-Bénin | K156: ÉNERGIE | L156: Prêt | M156: 25000000000 | N156: 0 | O156: 25000000000 | P156: XOF | Q156: 25000000000 | R156: Prêt commercial | S156: 42341 | T156: 42137 | U156: 44196 | V156: NATIONAL | Y156: PRIVE
B157: P-0130-ATLANTIQUE BANK-2015 | C157: 2015 | D157: =YEAR(U157) -> 2019 | E157: Projet d'investissement | F157: Financement par ADEOTI des travaux d'aménagement et de bitumage des tronçons Lalo-Klouékanmè (30,80 Km) et Dogbo-Toviklin-Klouékanmè-Adjahonmè (07,85 Km) | G157: Assurer la mobilisation de la ligne de crédit pour le bitumage et la modernisation géométrique de deux liaisons routières clés traversant le département du Couffo. | H157: documentation-anbenin.org | I157: Banque Atlantique Bénin | J157: ATLANTIQUE BANK | K157: INFRASTRUCTURES ROUTIERES ET TRANSPORT | L157: Prêt | M157: 23000000000 | N157: 0 | O157: 23000000000 | P157: XOF | Q157: 23000000000 | R157: Prêt commercial | S157: 42349 | T157: 42088 | U157: 43830 | V157: COUFFO (LALO, KLOUÉKANMÈ, DOGBO, TOVIKLIN) ; MONO (DJAKOTOMEY(ADJAHONMÈ)). | Y157: PRIVE
B158: P-0131-COOPERATION SUISSE-2015 | C158: 2015 | D158: =YEAR(U158) -> 2020 | E158: Projet d'investissement | F158: Projet d'électrification de 300 localités rurales en République du Bénin (1ère phase) | G158: Raccorder les zones rurales prioritaires au réseau électrique ou via des mini-réseaux isolés pour accroître le taux d'accès à l'énergie hors des grands centres urbains. | H158: https://evaluation.gouv.bj | I158: Coopération Suisse | J158: COOPERATION SUISSE | K158: ÉNERGIE | L158: Prêt | M158: 55756345000 | N158: 0 | O158: 55756345000 | P158: EUR | Q158: 85000000 | R158: Crédit acheteur | S158: 42353 | T158: 42166 | U158: 44012 | V158: NATIONAL | Y158: BILATERAUX
B159: P-0132-EXIMBANK DE CHINE-2015 | C159: 2015 | D159: =YEAR(U159) -> 2021 | E159: Projet d'investissement | F159: Projet de construction du barrage hydroélectrique d'Adjarala | G159: Valoriser le potentiel énergétique du fleuve Mono par l'édification d'un barrage hydroélectrique d'envergure régionale pour augmenter l'offre d'énergie propre. | H159: https://documentation-anbenin.org | I159: Banque chinoise d’import-export | J159: EXIMBANK DE CHINE | K159: ÉNERGIE | L159: Prêt | M159: 105605655000 | N159: 0 | O159: 105605655000 | P159: USD | Q159: 211311310 | R159: Crédit acheteur | S159: 42356 | T159: 42032 | U159: 44561 | V159: COUFFO (APLAHOUÉ). | Y159: BILATERAUX
B160: P-0133-Allemagne-2015 | C160: 2015 | D160: =YEAR(U160) -> 2019 | E160: Projet d'investissement | F160: Promotion de Agriculture-Fonds d'Investissement Agriculture Phase III | G160: Financer les infrastructures marchandes, de stockage et de transformation gérées par les filières porteuses nationales pour accroître la valeur ajoutée locale. | H160: https://evaluation.gouv.bj | I160: Allemagne | J160: Allemagne | K160: AGRICULTURE | L160: Don | M160: 0 | N160: 7871484000 | O160: 7871484000 | P160: EUR | Q160: 12000000 | R160: Don | S160: 42359 | T160: 42311 | U160: 43830 | V160: NATIONAL | Y160: BILATERAUX
B161: P-0134-Allemagne-2015 | C161: 2015 | D161: =YEAR(U161) -> 2019 | E161: Projet d'investissement | F161: Contrat de financement et d'exécution du Programme de Renforcement des Structures Centrales de Gouvernance (PRSCG) | G161: Optimiser la gestion interne des ministères clés à travers le renforcement de la transparence budgétaire et des outils informatisés de programmation. | H161: https://evaluation.gouv.bj | I161: Allemagne | J161: Allemagne | K161: GOUVERNANCE | L161: Don | M161: 0 | N161: 6559750000 | O161: 6559750000 | P161: EUR | Q161: 10000000 | R161: Don | S161: 42368 | T161: 42352 | U161: 43830 | V161: LITTORAL (COTONOU). | Y161: BILATERAUX
B162: P-0135-ECOBANK-Bénin-2015 | C162: 2015 | D162: =YEAR(U162) -> 2018 | E162: Projet d'investissement | F162: Préfinancement par EBOMAF du projet d'aménagement et de bitumage des tronçons de route Ouègbo-Toffo (12,25 km) et Tangbo-Zè (17 km) | G162: Financer les travaux d'asphaltage et de désenclavement routier de pôles de production agricole hautement stratégiques au sein du département de l'Atlantique. | H162: https://documentation-anbenin.org | I162: ECOBANK-Bénin | J162: ECOBANK-Bénin | K162: INFRASTRUCTURES ROUTIERES ET TRANSPORT | L162: Prêt | M162: 15983239315 | N162: 0 | O162: 15983239315 | P162: XOF | Q162: 15983239315 | R162: Préfinancement | S162: 42368 | T162: 42060 | U162: 43465 | V162: ATLANTIQUE (TOFFO(OUÈGBO, TOFFO CENTRE), ZÈ(TANGBO, ZÈ CENTRE)). | Y162: PRIVE
B163: P-0746-AFD-2015 | C163: 2015 | D163: =YEAR(U163) -> 2023 | E163: Projet d'investissement | F163: Projet d'Appui au Développement Agricole des Collines (PADAC) | G163: Contribuer au développement économique des territoires du département des Collines en renforçant le rôle des communes dans le développement rural, en finançant des investissements agricoles durables et en améliorant durablement les conditions de vie des petits producteurs. | H163: Évaluation officielle du PADAC (AFD, 2024) ; fiche projet AFD | I163: Agence Française de Développement | J163: AFD | K163: AGRICULTURE | L163: Prêt | M163: 7871484000 | N163: 0 | O163: 7871484000 | P163: EUR | Q163: 12000000 | R163: Prêt concessionnel | S163: 42051 | U163: 44957 | V163: 6 COMMUNES DU DÉPARTEMENT DES COLLINES (BANTÈ, DASSA ZOUÈ, GLAZOUÉ, OUESSÈ, SAVALOU, SAVÈ). | Y163: BILATERAUX
B164: P-0132-EXIMBANK DE CHINE-2016 | C164: 2016 | D164: =YEAR(U164) -> 2024 | E164: Projet d'investissement | F164: Projet de construction du barrage hydroélectrique d'Adjarala | G164: Consolider le budget de génie civil lourd alloué au complexe hydroélectrique binationale d'Adjarala pour assurer la poursuite des grands travaux de retenue. | H164: https://documentation-anbenin.org | I164: Banque chinoise d’import-export | J164: EXIMBANK DE CHINE | K164: ÉNERGIE | L164: Prêt | M164: 32400000000 | N164: 0 | O164: 32400000000 | P164: CNY | Q164: 400000000 | R164: Prêt concessionnel | S164: 42604 | T164: 42563 | U164: 45657 | V164: COUFFO (APLAHOUÉ). | Y164: BILATERAUX
B165: P-0136-BIDC-2016 | C165: 2016 | D165: =YEAR(U165) -> 2018 | E165: Étude / Préparation | F165: Lettre d'Accord relative à l'avance de fonds pour la préparation du projet d'appui à la gestion des investissements publics et à la gouvernance (PAGIPG) | G165: Réaliser les études et appuyer la formulation technique des réformes visant à améliorer l'efficacité et la sélection de la programmation budgétaire de l'État. | H165: https://evaluation.gouv.bj/57 | I165: Banque d’Investissement et de Développement de la CEDEAO | J165: BIDC | K165: GOUVERNANCE | L165: Prêt | M165: 3000000000 | N165: 0 | O165: 3000000000 | P165: XOF | Q165: 3000000000 | R165: Avance de préparation de projet | S165: 42464 | T165: 42387 | U165: 43465 | V165: LITTORAL (COTONOU). | Y165: MULTILATERAUX
B166: P-0137-BGFI-2016 | C166: 2016 | D166: =YEAR(U166) -> 2023 | E166: Projet d'investissement | F166: Projet d'Appui au Développement du Maraîchage (PADMAR) | G166: Améliorer les rendements et faciliter l'accès au marché des groupements de maraîchers par des aménagements hydro-agricoles de proximité et des intrants spécialisés. | H166: https://evaluation.gouv.bj | I166: BGFI BANK Bénin | J166: BGFI | K166: AGRICULTURE | L166: Prêt | M166: 16984914535 | N166: 0 | O166: 16984914535 | P166: XOF | Q166: 16984914535 | R166: Prêt commercial | S166: 42501 | T166: 42401 | U166: 45291 | V166: OUÉMÉ ; PLATEAU ; ATLANTIQUE ; LITTORAL ; MONO ; COUFFO ; ZOU ; COLLINES. | W166: APD | X166: PRÊT + DON | Y166: PRIVE | Z166: PRODUCTION AGRICOLE | AA166: AXE 4 | AB166: PILIER 2 | AC166: ODD 2 | AD166: 2.3 | AE166: Économique | AF166: Non trouvé
B167: P-0137-BIDC-2016 | C167: 2016 | D167: =YEAR(U167) -> 2023 | E167: Projet d'investissement | F167: Projet d'Appui au Développement du Maraîchage (PADMAR) | G167: Mettre en place des lignes de microfinance agricole adaptées aux cycles de production des petits maraîchers, en priorité les coopératives de femmes ruraux. | H167: https://evaluation.gouv.bj/57 | I167: Banque d’Investissement et de Développement de la CEDEAO | J167: BIDC | K167: AGRICULTURE | L167: Prêt | M167: 15000000000 | N167: 0 | O167: 15000000000 | P167: XOF | Q167: 15000000000 | R167: Prêt non concessionnel | S167: 42432 | T167: 42401 | U167: 45291 | V167: OUÉMÉ ; PLATEAU ; ATLANTIQUE ; LITTORAL ; MONO ; COUFFO ; ZOU ; COLLINES. | W167: APD | X167: PRÊT + DON | Y167: MULTILATERAUX | Z167: PRODUCTION AGRICOLE | AA167: AXE 4 | AB167: PILIER 2 | AC167: ODD 2 | AD167: 2.3 | AE167: Économique | AF167: Non trouvé
B168: P-0137-BOAD-2016 | C168: 2016 | D168: =YEAR(U168) -> 2023 | E168: Projet d'investissement | F168: Projet d'Appui au Développement du Maraîchage (PADMAR) | G168: Développer les plateformes de commercialisation et de conservation pour réduire de façon structurelle les pertes post-récolte des exploitants maraîchers. | H168: https://boad.org | I168: Banque Ouest Africaine de Développement | J168: BOAD | K168: AGRICULTURE | L168: Prêt | M168: 15000000000 | N168: 0 | O168: 15000000000 | P168: XOF | Q168: 15000000000 | R168: Prêt non concessionnel | S168: 42510 | T168: 42401 | U168: 45291 | V168: OUÉMÉ ; PLATEAU ; ATLANTIQUE ; LITTORAL ; MONO ; COUFFO ; ZOU ; COLLINES. | W168: APD | X168: PRÊT + DON | Y168: MULTILATERAUX | Z168: PRODUCTION AGRICOLE | AA168: AXE 4 | AB168: PILIER 2 | AC168: ODD 2 | AD168: 2.3 | AE168: Économique | AF168: Non trouvé
B169: P-0137-OPEP-2016 | C169: 2016 | D169: =YEAR(U169) -> 2023 | E169: Projet d'investissement | F169: Projet d'Appui au Développement du Maraîchage (PADMAR) | G169: Soutenir le déploiement d'équipements de micro-irrigation et l'organisation des filières de distribution pour valoriser la production maraîchère nationale. | H169: evaluation.gouv.bj | I169: OPEP | J169: OFID/OPEP | K169: AGRICULTURE | L169: Prêt | M169: 7000000000 | N169: 0 | O169: 7000000000 | P169: USD | Q169: 12000000 | R169: Prêt concessionnel | S169: 42683 | T169: 42535 | U169: 45291 | V169: OUÉMÉ ; PLATEAU ; ATLANTIQUE ; LITTORAL ; MONO ; COUFFO ; ZOU ; COLLINES. | W169: APD | X169: PRÊT + DON | Y169: MULTILATERAUX | Z169: PRODUCTION AGRICOLE | AA169: AXE 4 | AB169: PILIER 2 | AC169: ODD 2 | AD169: 2.3 | AE169: Économique | AF169: Non trouvé
B170: P-0138-BM-2016 | C170: 2016 | D170: =YEAR(U170) -> 2018 | E170: Étude / Préparation | F170: Lettre d'Accord relative à l'avance de fonds pour la préparation du projet de Compétitivité du Tourisme Transfrontalier (PCTT) | G170: Financer les expertises préalables et la structuration des projets de valorisation du patrimoine touristique de Ouidah et de la zone littorale. | H170: https://banquemondiale.org | I170: Banque mondiale | J170: BM | K170: CULTURE ET TOURISME | L170: Prêt | M170: 15000000000 | N170: 0 | O170: 15000000000 | P170: USD | Q170: 25000000 | R170: Avance de préparation de projet | S170: 42472 | T170: 42405 | U170: 43465 | V170: ATLANTIQUE (OUIDAH) ; LITTORAL (COTONOU) ; MONO (GRAND-POPO). | Y170: MULTILATERAUX
B171: P-0139-BID-2016 | C171: 2016 | D171: =YEAR(U171) -> 2021 | E171: Projet d'investissement | F171: Faitière des Caisses d'Epargne et de Crédit Agricole Mutuel du Bénin (FECECAM) | G171: Renforcer les capacités financières de la FECECAM par une ligne de refinancement dédiée à l'octroi de crédits de production à destination des paysans. | H171: https://documentation-anbenin.org | I171: Banque Islamique de Développement | J171: BID | K171: MICROFINANCE | L171: Prêt | M171: 5500000000 | N171: 0 | O171: 5500000000 | P171: USD | Q171: 10000000 | R171: Prêt concessionnel | S171: 42515 | T171: 42433 | U171: 44561 | V171: NATIONAL | W171: APD | X171: DON | Y171: MULTILATERAUX | Z171: PRODUCTION AGRICOLE | AA171: AXE 4 | AB171: PILIER 2 | AC171: ODD 2 | AD171: 2.3 | AE171: Économique | AF171: Non trouvé
B172: P-0140-BID-2016 | C172: 2016 | D172: =YEAR(U172) -> 2022 | E172: Projet d'investissement | F172: Préfinancement par SOGEA SATOM du projet d'aménagement et de bitumage de la route Bétérou-Tchaourou-Frontière du Nigeria | G172: Permettre le lancement sans délai des opérations de terrassement et d'asphaltage lourd sur cet axe de transport transfrontalier hautement stratégique. | H172: https://documentation-anbenin.org | I172: Banque Islamique de Développement | J172: BID | K172: INFRASTRUCTURES ROUTIERES ET TRANSPORT | L172: Prêt | M172: 2750000000 | N172: 0 | O172: 2750000000 | P172: USD | Q172: 5000000 | R172: Prêt concessionnel | S172: 42525 | T172: 42439 | U172: 44926 | V172: BORGOU (TCHAOUROU(BÉTÉROU, TCHAOUROU CENTRE)). | Y172: MULTILATERAUX
B173: P-0141-BOAD-2016 | C173: 2016 | D173: =YEAR(U173) -> 2021 | E173: Projet d'investissement | F173: Travaux d'aménagement et de bitumage du tronçon Savalou – Tchetti – frontière du Togo (42 km) et Bretelle Logozohè – Glazoué (17 km) | G173: Asphaltage de l'axe Savalou-Tchetti pour désenclaver les communes agricoles frontalières et fluidifier les liaisons commerciales avec le Togo. | H173: https://boad.org | I173: Banque Ouest Africaine de Développement | J173: BOAD | K173: INFRASTRUCTURES ROUTIERES ET TRANSPORT | L173: Prêt | M173: 10000000000 | N173: 0 | O173: 10000000000 | P173: XOF | Q173: 10000000000 | R173: Prêt non concessionnel | S173: 42501 | T173: 42443 | U173: 44561 | V173: COLLINES (SAVALOU(TCHETTI, LOGOZOHÉ), GLAZOUÉ). | Y173: MULTILATERAUX
B174: P-0142-JICA-2016 | C174: 2016 | D174: =YEAR(U174) -> 2020 | E174: Projet d'investissement | F174: Projet d'approvisionnement en eau potable à partir des eaux souterraines des communes de Glazoué et de Dassa | G174: Résorber durablement la pénurie d'eau potable dans le département des Collines en mobilisant les ressources hydriques souterraines pour alimenter les foyers urbains. | H174: https://evaluation.gouv.bj | I174: Agence Japonaise de Coopération Internationale | J174: JICA | K174: EAU ET ASSAINISSEMENT | L174: Don | M174: 0 | N174: 5300000000 | O174: 5300000000 | P174: USD | Q174: 10710000 | R174: Don | S174: 42502 | T174: 42460 | U174: 44196 | V174: COLLINES (GLAZOUÉ, DASSA-ZOUMÉ). | W174: APD | X174: DON | Y174: BILATERAUX | Z174: ACCÈS À L’EAU POTABLE | AA174: AXE 6 | AB174: PILIER 3 | AC174: ODD 6 | AD174: 6.1 | AE174: Environnemental | AF174: Non trouvé
B175: P-0143-BID-2016 | C175: 2016 | D175: =YEAR(U175) -> 2023 | E175: Projet d'investissement | F175: Projet de construction de l'Université Polytechnique d'Abomey et de la deuxième phase du projet de construction de l'Université d'Agriculture de Kétou (PADES) | G175: Édifier des complexes universitaires modernes équipés de laboratoires pour accroître la qualité de la formation professionnelle supérieure scientifique et agricole. ; Doter les deux pôles universitaires thématiques d'infrastructures de recherche avancée et de logements adéquats au profit des étudiants. | H175: https://documentation-anbenin.org | I175: Banque Islamique de Développement | J175: BID | K175: ÉDUCATION | L175: Prêt | M175: 96200000000 | N175: 0 | O175: 96200000000 | P175: EUR | Q175: 146650000 | R175: Ijara | Istisna'a | S175: 42515 | T175: 42467 | U175: 45291 | V175: ZOU (ABOMEY) ; PLATEAU (KÉTOU). | W175: APD | X175: PRÊT | Y175: MULTILATERAUX | Z175: ENSEIGNEMENT SUPÉRIEUR | AA175: AXE 5 | AB175: PILIER 2 | AC175: ODD 4 | AD175: 4.1 | AE175: Social | AF175: Non trouvé
B176: P-0144-BID-2016 | C176: 2016 | D176: =YEAR(U176) -> 2021 | E176: Projet d'investissement | F176: Deuxième phase du programme intégré d'Appui à la Microfinance (PIAMF II) | G176: Améliorer le cadre opérationnel des SFD et étendre l'accès aux micro-crédits productifs de subsistance au bénéfice des ménages vivant sous le seuil de pauvreté. | H176: https://documentation-anbenin.org | I176: Banque Islamique de Développement | J176: BID | K176: MICROFINANCE | L176: Prêt | M176: 16500000000 | N176: 0 | O176: 16500000000 | P176: USD | Q176: 30000000 | R176: Mudarabah | S176: 42515 | T176: 42467 | U176: 44561 | V176: NATIONAL | Y176: MULTILATERAUX
B177: P-0144-FSID-2016 | C177: 2016 | D177: =YEAR(U177) -> 2021 | E177: Projet d'investissement | F177: Deuxième phase du programme intégré d'Appui à la Microfinance (PIAMF II) | G177: Consolider l'inclusion financière rurale par des dotations d'appui ciblant l'auto-emploi des femmes et le financement de petites activités artisanales. | H177: https://documentation-anbenin.org | I177: Fonds de Solidarité Islamique pour le Développement | J177: FSID | K177: MICROFINANCE | L177: Prêt | M177: 11000000000 | N177: 0 | O177: 11000000000 | P177: USD | Q177: 20000000 | R177: Prêt | S177: 42515 | T177: 42467 | U177: 44561 | V177: NATIONAL | Y177: MULTILATERAUX
B178: P-0145-Allemagne-2016 | C178: 2016 | D178: =YEAR(U178) -> 2022 | E178: Projet d'investissement | F178: Projet d'AEP des zones périurbaines de Grand Cotonou et de Porto-Novo | G178: Étendre de manière significative le réseau de distribution d'eau potable de la SONEB au sein des agglomérations périphériques en pleine expansion démographique. | H178: https://evaluation.gouv.bj | I178: Allemagne | J178: Allemagne | K178: EAU ET ASSAINISSEMENT | L178: Don | M178: 0 | N178: 9839355000 | O178: 9839355000 | P178: EUR | Q178: 15000000 | R178: Don | S178: 42654 | T178: 42474 | U178: 44926 | V178: LITTORAL (COTONOU) ; ATLANTIQUE (ABOMEY-CALAVI, SÔ-AVA) ; OUÉMÉ (PORTO-NOVO, SÈMÈ-PODJI, AKPRO-MISSÉRÉTÉ). | Y178: BILATERAUX
B179: P-0146-AFD-2016 | C179: 2016 | D179: =YEAR(U179) -> 2022 | E179: Projet d'investissement | F179: Projet "Soutien à l'Enseignement Secondaire au Bénin (SEnS)" | G179: Améliorer la gouvernance et le niveau d'encadrement pédagogique des collèges publics d'enseignement général au sein des départements ciblés du Nord-Bénin. ; Financer la réhabilitation, l'équipement de bibliothèques et de blocs de sciences pour rehausser les performances scolaires des élèves du secondaire. | H179: https://evaluation.gouv.bj | I179: Agence Française de Développement | J179: AFD | K179: ÉDUCATION | L179: Don | Prêt | M179: 9839355000 | N179: 655957000 | O179: 10495312000 | P179: EUR | Q179: 16000000 | R179: Don | Prêt concessionnel | S179: 42559 | T179: 42558 | U179: 44834 | V179: ATACORA ; DONGA ; BORGOU ; ALIBORI. | Y179: BILATERAUX
B180: P-0147-AFD-2016 | C180: 2016 | D180: =YEAR(U180) -> 2021 | E180: Projet d'investissement | F180: Troisième Fonds d'Etudes et de Renforcement de Capacités (FERC-3) | G180: Apporter l'expertise technique et financière requise aux administrations de l'État pour mener à bien les phases préparatoires des grands chantiers publics. | H180: https://evaluation.gouv.bj | I180: Agence Française de Développement | J180: AFD | K180: GOUVERNANCE | L180: Don | M180: 0 | N180: 327978500 | O180: 327978500 | P180: EUR | Q180: 500000 | R180: Don | S180: 42559 | T180: 42558 | U180: 44561 | V180: LITTORAL (COTONOU). | Y180: BILATERAUX
B181: P-0148-ATLANTIQUE BANK-2016 | C181: 2016 | D181: =YEAR(U181) -> 2019 | E181: Projet d'investissement | F181: Préfinancement complémentaire du projet d'aménagement et de bitumage des tronçons de route Zinvié-Sèdjèdénou-Zè, RNIE1-Cococodji-Hèvié-Ouèdo, Missésinto-Zinvié et Calavi Kpota-Ouèdo | G181: Fluidifier la circulation inter-quartiers au sein de la commune d'Abomey-Calavi par l'asphaltage accéléré d'axes de raccordement urbains et périurbains à forte densité. | H181: https://documentation-anbenin.org | I181: Banque Atlantique Bénin | J181: ATLANTIQUE BANK | K181: INFRASTRUCTURES ROUTIERES ET TRANSPORT | L181: Prêt | M181: 64288219505 | N181: 0 | O181: 64288219505 | P181: XOF | Q181: 64288219505 | R181: Prêt commercial | S181: 42573 | T181: 42501 | U181: 43830 | V181: ATLANTIQUE (ABOMEY-CALAVI(HÈVIÉ, OUÈDO, ZINVIÉ), ZÈ(SÉDJÈDENOU, ZÈ CENTRE)). | Y181: PRIVE
B182: P-0149-BID-2016 | C182: 2016 | D182: =YEAR(U182) -> 2022 | E182: Projet d'investissement | F182: Projet de construction de la route Bétérou-Tchaourou-Frontière du Nigeria | G182: Désenclaver la zone agricole et assurer la liaison moderne bitumée entre l'axe de la RNIE 2 et le réseau frontalier pour stimuler le trafic d'échange régional. ; Financer la pose des couches de roulement lourdes et ériger les ponts d'assainissement d'eau requis le long de l'itinéraire transversal de Tchaourou. | H182: documentation-anbenin.org | I182: Banque Islamique de Développement | J182: BID | K182: INFRASTRUCTURES ROUTIERES ET TRANSPORT | L182: Prêt | M182: 44684446797 | N182: 0 | O182: 44684446797 | P182: EUR | Q182: 68121000 | R182: Ijara | Istisna'a | S182: 42590 | T182: 42515 | U182: 44926 | V182: BORGOU (TCHAOUROU(BÉTÉROU, TCHAOUROU CENTRE)). | Y182: MULTILATERAUX
B183: P-0150-BGFI-2016 | C183: 2016 | D183: =YEAR(U183) -> 2020 | E183: Projet d'investissement | F183: Financement partiel du projet d'aménagement et de bitumage de la route Comé-Lokossa-Dogbo et de la Bretelle Zounhouè-Athiémé-Frontière du Togo (71 km) | G183: Apporter le cofinancement de marché requis pour moderniser et asphalter de façon durable cet axe routier structurant liant les départements du Mono et du Couffo. | H183: evaluation.gouv.bj | I183: BGFI BANK Bénin | J183: BGFI | K183: INFRASTRUCTURES ROUTIERES ET TRANSPORT | L183: Prêt | M183: 29505766907 | N183: 0 | O183: 29505766907 | P183: XOF | Q183: 29505766907 | R183: Prêt commercial | S183: 42614 | T183: 42501 | U183: 44196 | V183: MONO (COMÈ, LOKOSSA, ATHIÉMÉ) ; COUFFO (DOGBO). | Y183: PRIVE
B184: P-0151-BM-2016 | C184: 2016 | D184: =YEAR(U184) -> 2023 | E184: Projet d'investissement | F184: Projet de Compétitivité du Tourisme Transfrontalier (PCTT) | G184: Diversifier l'économie nationale par la valorisation de la destination Ouidah et de sa Route des Esclaves, en modernisant les infrastructures culturelles et en appuyant les MPME locales. | H184: banquemondiale.org | I184: Banque mondiale | J184: BM | K184: CULTURE ET TOURISME | L184: Prêt | M184: 30108426300 | N184: 0 | O184: 30108426300 | P184: USD | Q184: 50000000 | R184: Prêt concessionnel | S184: 42628 | T184: 42453 | U184: 45289 | V184: ATLANTIQUE (OUIDAH) ; LITTORAL (COTONOU) ; MONO (GRAND-POPO). | W184: APD | X184: PRÊT | Y184: MULTILATERAUX | Z184: TOURISME | AA184: AXE 4 | AB184: PILIER 2 | AC184: ODD 11 | AD184: 11.3 | AE184: Social | AF184: Non trouvé
B185: P-0152-Pays-Bas-2016 | C185: 2016 | D185: =YEAR(U185) -> 2018 | E185: Projet d'investissement | F185: Projet "Fonds de Transition Eau" | G185: Assurer la continuité et l'ancrage institutionnel des investissements hydrauliques décentralisés au profit des communes pendant la phase de restructuration sectorielle. | H185: evaluation.gouv.bj | I185: Pays-Bas | J185: Pays-Bas | K185: EAU ET ASSAINISSEMENT | L185: Don | M185: 0 | N185: 6203460000 | O185: 6203460000 | P185: EUR | Q185: 6203460000 | R185: Don | S185: 42628 | T185: 42474 | U185: 43465 | V185: NATIONAL | Y185: BILATERAUX
B186: P-0153-BM-2016 | C186: 2016 | D186: =YEAR(U186) -> 2022 | E186: Projet d'investissement | F186: Projet d'appui à la gestion des investissements publics et de la gouvernance (PAGIPG) | G186: Optimiser l'allocation et le suivi des ressources de l'État en automatisant les processus de sélection, de programmation et d'évaluation des projets d'investissements publics. | H186: banquemondiale.org | I186: Banque mondiale | J186: BM | K186: GOUVERNANCE | L186: Prêt | M186: 17317264800 | N186: 0 | O186: 17317264800 | P186: EUR | Q186: 26400000 | R186: Prêt concessionnel | S186: 42650 | T186: 42544 | U186: 44926 | V186: LITTORAL (COTONOU). | Y186: MULTILATERAUX
...
